Workbook

Sheet Bank Balance
A2: Bank Balance
A4: Row Labels | B4: Sum of Amount (USD)
A5: Jan | B5: 1955526.2
A6: Feb | B6: 947096.7
A7: Mar | B7: 987757.94
A8: Apr | B8: 793996.47
A9: May | B9: 663264.51
A10: Jun | B10: 735495.79
A11: Jul | B11: 735495.79
A12: Aug | B12: 735495.79
A13: Sep | B13: 735495.79
A14: Oct | B14: 735495.79
A15: Nov | B15: 735495.79
A16: Dec | B16: 735495.79
A17: Grand Total | B17: 10496112

Sheet Bank 
A1: Raw Data | J1: Overall
A2: Date | B2: Entity | C2: Bank Balance | D2: Currency | E2: Currency Amount | F2: Amount (USD) | H2: FOREX
A3: 46023 | B3: HQ | C3: East West | D3: USD | E3: ='AXT -Eastwest Bank'!I5 -> 825438.09 | F3: =E3*H3 -> 825438.09 | H3: 1 | J3: Row Labels | K3: Sum of Amount (USD)
A4: 46023 | B4: SG | C4: AXT USD | D4: USD | E4: ='AXT - USD'!J5 -> 57825.83 | F4: =E4*H4 -> 57825.83 | H4: 1 | J4: Jan | K4: 1955526.2
A5: 46023 | B5: SG | C5: AXT SGD | D5: SGD | E5: ='AXT- SGD'!I5 -> 173074.36 | F5: =E5*H5 -> 136265.08 | H5: 0.787321 | J5: CN | K5: 163686.69
A6: 46023 | B6: SG | C6: AXT CNY | D6: CNY | E6: 14245.44 | F6: =E6*H6 -> 2049.2778 | H6: =FOREX!K2 -> 0.143855 | J6: AXS CNY | K6: 123483.85
A7: 46023 | B7: MY | C7: AXI USD | D7: USD | E7: ='AXI - USD'!I6 -> 11798.62 | F7: =E7*H7 -> 11798.62 | H7: 1 | J7: AXS CNY - Capital Fund | K7: 40202.835
A8: 46023 | B8: MY | C8: AXI MYR | D8: MYR | E8: ='AXI - MYR'!I5 -> 351069.83 | F8: =E8*H8 -> 89090.289 | H8: =FOREX!G2 -> 0.253768 | J8: HQ | K8: 1350855.9
A9: 46023 | B9: CN | C9: AXS CNY - Capital Fund | D9: CNY | E9: 139733.88 | F9: =E9*H9 -> 20101.417 | H9: =FOREX!K2 -> 0.143855 | J9: East West | K9: 1350855.9
A10: 46023 | B10: CN | C10: AXS CNY | D10: CNY | E10: 301052.42 | F10: =E10*H10 -> 43307.896 | H10: =FOREX!K2 -> 0.143855 | J10: MY | K10: 145647.34
A11: 46053 | B11: HQ | C11: East West | D11: USD | E11: ='AXT -Eastwest Bank'!I10 -> 525417.86 | F11: =E11*H11 -> 525417.86 | H11: 1 | J11: AXI MYR | K11: 133649.45
A12: 46053 | B12: SG | C12: AXT USD | D12: USD | E12: ='AXT - USD'!J18 -> 12669.95 | F12: =E12*H12 -> 12669.95 | H12: 1 | J12: AXI USD | K12: 11997.89
A13: 46053 | B13: SG | C13: AXT SGD | D13: SGD | E13: ='AXT- SGD'!I66 -> 107296.56 | F13: =E13*H13 -> 84476.835 | H13: =FOREX!C2 -> 0.787321 | J13: SG | K13: 295336.25
A14: 46053 | B14: SG | C14: AXT CNY | D14: CNY | E14: =E6 -> 14245.44 | F14: =E14*H14 -> 2049.2778 | H14: =FOREX!K2 -> 0.143855 | J14: AXT CNY | K14: 4098.5555
A15: 46053 | B15: MY | C15: AXI USD | D15: USD | E15: ='AXI - USD'!I22 -> 199.27 | F15: =E15*H15 -> 199.27 | H15: 1 | J15: AXT SGD | K15: 220741.91
A16: 46053 | B16: MY | C16: AXI MYR | D16: MYR | E16: ='AXI - MYR'!I44 -> 175590.15 | F16: =E16*H16 -> 44559.161 | H16: =FOREX!G2 -> 0.253768 | J16: AXT USD | K16: 70495.78
A17: 46053 | B17: CN | C17: AXS CNY - Capital Fund | D17: CNY | E17: =E9 -> 139733.88 | F17: =E17*H17 -> 20101.417 | H17: =FOREX!K2 -> 0.143855 | J17: Feb | K17: 947096.7
A18: 46053 | B18: CN | C18: AXS CNY | D18: CNY | E18: ='AXS-CNY'!I44 -> 557338.69 | F18: =E18*H18 -> 80175.957 | H18: =FOREX!K2 -> 0.143855 | J18: CN | K18: 79998.145
A19: 46081 | B19: HQ | C19: East West | D19: USD | E19: ='AXT -Eastwest Bank'!I15 -> 525421.95 | F19: =E19*H19 -> 525421.95 | H19: 1 | J19: AXS CNY | K19: 59625.364
A20: 46081 | B20: SG | C20: AXT USD | D20: USD | E20: ='AXT - USD'!J18 -> 12669.95 | F20: =E20*H20 -> 12669.95 | H20: 1 | J20: AXS CNY - Capital Fund | K20: 20372.781
A21: 46081 | B21: SG | C21: AXT SGD | D21: SGD | E21: ='AXT- SGD'!I116 -> 85042.2 | F21: =E21*H21 -> 67235.554 | H21: =FOREX!C3 -> 0.790614 | J21: HQ | K21: 525421.95
A22: 46081 | B22: SG | C22: AXT CNY | D22: CNY | E22: =E6 -> 14245.44 | F22: =E22*H22 -> 2076.9424 | H22: =FOREX!K3 -> 0.145797 | J22: East West | K22: 525421.95
A23: 46081 | B23: MY | C23: AXI USD | D23: USD | E23: ='AXI - USD'!I22 -> 199.27 | F23: =E23*H23 -> 199.27 | H23: 1 | J23: MY | K23: 259694.16
A24: 46081 | B24: MY | C24: AXI MYR | D24: MYR | E24: ='AXI - MYR'!I99 -> 1010053.6 | F24: =E24*H24 -> 259494.89 | H24: =FOREX!G3 -> 0.256912 | J24: AXI MYR | K24: 259494.89
A25: 46081 | B25: CN | C25: AXS CNY - Capital Fund | D25: CNY | E25: =E17 -> 139733.88 | F25: =E25*H25 -> 20372.781 | H25: =FOREX!K3 -> 0.145797 | J25: AXI USD | K25: 199.27
A26: 46081 | B26: CN | C26: AXS CNY | D26: CNY | E26: ='AXS-CNY'!I75 -> 408961.53 | F26: =E26*H26 -> 59625.364 | H26: =FOREX!K3 -> 0.145797 | J26: SG | K26: 81982.446
A27: 46112 | B27: HQ | C27: East West | D27: USD | E27: ='AXT -Eastwest Bank'!I23 -> 675398.53 | F27: =E27*H27 -> 675398.53 | H27: 1 | J27: AXT CNY | K27: 2076.9424
A28: 46112 | B28: SG | C28: AXT USD | D28: USD | E28: ='AXT - USD'!J35 -> 66399.97 | F28: =E28*H28 -> 66399.97 | H28: 1 | J28: AXT SGD | K28: 67235.554
A29: 46112 | B29: SG | C29: AXT SGD | D29: SGD | E29: ='AXT- SGD'!I216 -> 99091.407 | F29: =E29*H29 -> 76810.307 | H29: =FOREX!C4 -> 0.775146 | J29: AXT USD | K29: 12669.95
A30: 46112 | B30: SG | C30: AXT CNY | D30: CNY | E30: 2245.44 | F30: =E30*H30 -> 325.49674 | H30: =FOREX!K4 -> 0.144959 | J30: Mar | K30: 987757.94
A31: 46112 | B31: MY | C31: AXI USD | D31: USD | E31: ='AXI - USD'!I27 -> 172.51 | F31: =E31*H31 -> 172.51 | H31: 1 | J31: CN | K31: 37017.301
A32: 46112 | B32: MY | C32: AXI MYR | D32: MYR | E32: ='AXI - MYR'!I155 -> 532919.67 | F32: =E32*H32 -> 131633.82 | H32: =FOREX!G4 -> 0.247005 | J32: AXS CNY | K32: 16759.085
A33: 46112 | B33: CN | C33: AXS CNY - Capital Fund | D33: CNY | E33: 139751.35 | F33: =E33*H33 -> 20258.216 | H33: =FOREX!K4 -> 0.144959 | J33: AXS CNY - Capital Fund | K33: 20258.216
A34: 46112 | B34: CN | C34: AXS CNY | D34: CNY | E34: ='AXS-CNY'!I100 -> 115612.59 | F34: =E34*H34 -> 16759.085 | H34: =FOREX!K4 -> 0.144959 | J34: HQ | K34: 675398.53
A35: 46142 | B35: HQ | C35: East West | D35: USD | E35: ='AXT -Eastwest Bank'!I30 -> 425377.12 | F35: =E35*H35 -> 425377.12 | H35: 1 | J35: East West | K35: 675398.53
A36: 46142 | B36: SG | C36: AXT USD | D36: USD | E36: ='AXT - USD'!J48 -> 124366.3 | F36: =E36*H36 -> 124366.3 | H36: 1 | J36: MY | K36: 131806.33
A37: 46142 | B37: SG | C37: AXT SGD | D37: SGD | E37: ='AXT- SGD'!I280 -> 121074.26 | F37: =E37*H37 -> 95028.247 | H37: =FOREX!C5 -> 0.78487574 | J37: AXI MYR | K37: 131633.82
A38: 46142 | B38: SG | C38: AXT CNY | D38: CNY | E38: =E30 -> 2245.44 | F38: =E38*H38 -> 328.80724 | H38: =FOREX!K5 -> 0.14643332 | J38: AXI USD | K38: 172.51
A39: 46142 | B39: MY | C39: AXI USD | D39: USD | E39: ='AXI - USD'!I27 -> 172.51 | F39: =E39*H39 -> 172.51 | H39: 1 | J39: SG | K39: 143535.77
A40: 46142 | B40: MY | C40: AXI MYR | D40: MYR | E40: ='AXI - MYR'!I188 -> 537094.84 | F40: =E40*H40 -> 135285.04 | H40: =FOREX!G5 -> 0.25188297 | J40: AXT CNY | K40: 325.49674
A41: 46142 | B41: CN | C41: AXS CNY - Capital Fund | D41: CNY | E41: 46884.57 | F41: =E41*H41 -> 6865.4634 | H41: =FOREX!K5 -> 0.14643332 | J41: AXT SGD | K41: 76810.307
A42: 46142 | B42: CN | C42: AXS CNY | D42: CNY | E42: ='AXS-CNY'!I126 -> 44486.28 | F42: =E42*H42 -> 6572.9813 | H42: =FOREX!K6 -> 0.147753 | J42: AXT USD | K42: 66399.97
A43: 46173 | B43: HQ | C43: East West | D43: USD | E43: ='AXT -Eastwest Bank'!I35 -> 425380.78 | F43: =E43*H43 -> 425380.78 | H43: 1 | J43: Apr | K43: 793996.47
A44: 46173 | B44: SG | C44: AXT USD | D44: USD | E44: ='AXT - USD'!J59 -> 12350.96 | F44: =E44*H44 -> 12350.96 | H44: 1 | J44: CN | K44: 13438.445
A45: 46173 | B45: SG | C45: AXT SGD | D45: SGD | E45: ='AXT- SGD'!I366 -> 122067.73 | F45: =E45*H45 -> 95603.443 | H45: =FOREX!C6 -> 0.7832 | J45: AXS CNY | K45: 6572.9813
A46: 46173 | B46: SG | C46: AXT CNY | D46: CNY | E46: =E30 -> 2245.44 | F46: =E46*H46 -> 331.7705 | H46: =FOREX!K6 -> 0.147753 | J46: AXS CNY - Capital Fund | K46: 6865.4634
A47: 46173 | B47: MY | C47: AXI USD | D47: USD | E47: ='AXI - USD'!I27 -> 172.51 | F47: =E47*H47 -> 172.51 | H47: 1 | J47: HQ | K47: 425377.12
A48: 46173 | B48: MY | C48: AXI MYR | D48: MYR | E48: ='AXI - MYR'!I234 -> 284781.85 | F48: =E48*H48 -> 71769.298 | H48: =FOREX!G6 -> 0.252015 | J48: East West | K48: 425377.12
A49: 46173 | B49: CN | C49: AXS CNY - Capital Fund | D49: CNY | E49: =0 -> 0 | F49: =E49*H49 -> 0 | H49: =FOREX!K6 -> 0.147753 | J49: MY | K49: 135457.55
A50: 46173 | B50: CN | C50: AXS CNY | D50: CNY | E50: ='AXS-CNY'!I150 -> 390217.13 | F50: =E50*H50 -> 57655.752 | H50: =FOREX!K6 -> 0.147753 | J50: AXI MYR | K50: 135285.04
A51: 46203 | B51: HQ | C51: East West | D51: USD | E51: ='AXT -Eastwest Bank'!I43 -> 225380.78 | F51: =E51*H51 -> 225380.78 | H51: 1 | J51: AXI USD | K51: 172.51
A52: 46234 | B52: HQ | C52: East West | D52: USD | E52: ='AXT -Eastwest Bank'!I53 -> 225380.78 | F52: =E52*H52 -> 225380.78 | H52: 1 | J52: SG | K52: 219723.35
A53: 46265 | B53: HQ | C53: East West | D53: USD | E53: ='AXT -Eastwest Bank'!I64 -> 225380.78 | F53: =E53*H53 -> 225380.78 | H53: 1 | J53: AXT CNY | K53: 328.80724
A54: 46295 | B54: HQ | C54: East West | D54: USD | E54: ='AXT -Eastwest Bank'!I74 -> 225380.78 | F54: =E54*H54 -> 225380.78 | H54: 1 | J54: AXT SGD | K54: 95028.247
A55: 46326 | B55: HQ | C55: East West | D55: USD | E55: ='AXT -Eastwest Bank'!I84 -> 225380.78 | F55: =E55*H55 -> 225380.78 | H55: 1 | J55: AXT USD | K55: 124366.3
A56: 46356 | B56: HQ | C56: East West | D56: USD | E56: ='AXT -Eastwest Bank'!I95 -> 225380.78 | F56: =E56*H56 -> 225380.78 | H56: 1 | J56: May | K56: 663264.51
A57: 46387 | B57: HQ | C57: East West | D57: USD | E57: ='AXT -Eastwest Bank'!I105 -> 225380.78 | F57: =E57*H57 -> 225380.78 | H57: 1 | J57: CN | K57: 57655.752
A58: 46203 | B58: SG | C58: AXT USD | D58: USD | E58: ='AXT - USD'!J75 -> 210734.01 | F58: =E58*H58 -> 210734.01 | H58: 1 | J58: AXS CNY | K58: 57655.752
A59: 46234 | B59: SG | C59: AXT USD | D59: USD | E59: ='AXT - USD'!J82 -> 210734.01 | F59: =E59*H59 -> 210734.01 | H59: 1 | J59: AXS CNY - Capital Fund | K59: 0
A60: 46265 | B60: SG | C60: AXT USD | D60: USD | E60: ='AXT - USD'!J85 -> 210734.01 | F60: =E60*H60 -> 210734.01 | H60: 1 | J60: HQ | K60: 425380.78
A61: 46295 | B61: SG | C61: AXT USD | D61: USD | E61: ='AXT - USD'!J98 -> 210734.01 | F61: =E61*H61 -> 210734.01 | H61: 1 | J61: East West | K61: 425380.78
A62: 46326 | B62: SG | C62: AXT USD | D62: USD | E62: ='AXT - USD'!J105 -> 210734.01 | F62: =E62*H62 -> 210734.01 | H62: 1 | J62: MY | K62: 71941.808
A63: 46356 | B63: SG | C63: AXT USD | D63: USD | E63: ='AXT - USD'!J112 -> 210734.01 | F63: =E63*H63 -> 210734.01 | H63: 1 | J63: AXI MYR | K63: 71769.298
A64: 46387 | B64: SG | C64: AXT USD | D64: USD | E64: ='AXT - USD'!J119 -> 210734.01 | F64: =E64*H64 -> 210734.01 | H64: 1 | J64: AXI USD | K64: 172.51
A65: 46203 | B65: SG | C65: AXT SGD | D65: SGD | E65: ='AXT- SGD'!I444 -> 252292.02 | F65: =E65*H65 -> 197595.11 | H65: =FOREX!C7 -> 0.7832 | J65: SG | K65: 108286.17
A66: 46234 | B66: SG | C66: AXT SGD | D66: SGD | E66: ='AXT- SGD'!I452 -> 252292.02 | F66: =E66*H66 -> 197595.11 | H66: =FOREX!C8 -> 0.7832 | J66: AXT CNY | K66: 331.7705
A67: 46265 | B67: SG | C67: AXT SGD | D67: SGD | E67: ='AXT- SGD'!I460 -> 252292.02 | F67: =E67*H67 -> 197595.11 | H67: =FOREX!C9 -> 0.7832 | J67: AXT SGD | K67: 95603.443
A68: 46295 | B68: SG | C68: AXT SGD | D68: SGD | E68: ='AXT- SGD'!I468 -> 252292.02 | F68: =E68*H68 -> 197595.11 | H68: =FOREX!C10 -> 0.7832 | J68: AXT USD | K68: 12350.96
A69: 46326 | B69: SG | C69: AXT SGD | D69: SGD | E69: ='AXT- SGD'!I476 -> 252292.02 | F69: =E69*H69 -> 197595.11 | H69: =FOREX!C11 -> 0.7832 | J69: Jun | K69: 735495.79
A70: 46356 | B70: SG | C70: AXT SGD | D70: SGD | E70: ='AXT- SGD'!I484 -> 252292.02 | F70: =E70*H70 -> 197595.11 | H70: =FOREX!C12 -> 0.7832 | J70: Jul | K70: 735495.79
A71: 46387 | B71: SG | C71: AXT SGD | D71: SGD | E71: ='AXT- SGD'!I492 -> 252292.02 | F71: =E71*H71 -> 197595.11 | H71: =FOREX!C13 -> 0.7832 | J71: Aug | K71: 735495.79
A72: 46203 | B72: MY | C72: AXI MYR | D72: MYR | E72: ='AXI - MYR'!I276 -> 174424.66 | F72: =E72*H72 -> 43957.631 | H72: =FOREX!G7 -> 0.252015 | J72: Sep | K72: 735495.79
A73: 46234 | B73: MY | C73: AXI MYR | D73: MYR | E73: ='AXI - MYR'!I284 -> 174424.66 | F73: =E73*H73 -> 43957.631 | H73: =FOREX!G8 -> 0.252015 | J73: Oct | K73: 735495.79
A74: 46265 | B74: MY | C74: AXI MYR | D74: MYR | E74: ='AXI - MYR'!I292 -> 174424.66 | F74: =E74*H74 -> 43957.631 | H74: =FOREX!G9 -> 0.252015 | J74: Nov | K74: 735495.79
A75: 46295 | B75: MY | C75: AXI MYR | D75: MYR | E75: ='AXI - MYR'!I300 -> 174424.66 | F75: =E75*H75 -> 43957.631 | H75: =FOREX!G10 -> 0.252015 | J75: Dec | K75: 735495.79
A76: 46326 | B76: MY | C76: AXI MYR | D76: MYR | E76: ='AXI - MYR'!I308 -> 174424.66 | F76: =E76*H76 -> 43957.631 | H76: =FOREX!G11 -> 0.252015 | J76: Grand Total | K76: 10496112
A77: 46356 | B77: MY | C77: AXI MYR | D77: MYR | E77: ='AXI - MYR'!I316 -> 174424.66 | F77: =E77*H77 -> 43957.631 | H77: =FOREX!G12 -> 0.252015
A78: 46387 | B78: MY | C78: AXI MYR | D78: MYR | E78: ='AXI - MYR'!I324 -> 174424.66 | F78: =E78*H78 -> 43957.631 | H78: =FOREX!G13 -> 0.252015
A79: 46203 | B79: MY | C79: AXI USD | D79: USD | E79: ='AXI - USD'!I33 -> 172.51 | F79: =E79*H79 -> 172.51 | H79: 1
A80: 46234 | B80: MY | C80: AXI USD | D80: USD | E80: ='AXI - USD'!I40 -> 172.51 | F80: =E80*H80 -> 172.51 | H80: 1
A81: 46265 | B81: MY | C81: AXI USD | D81: USD | E81: ='AXI - USD'!I47 -> 172.51 | F81: =E81*H81 -> 172.51 | H81: 1
A82: 46295 | B82: MY | C82: AXI USD | D82: USD | E82: ='AXI - USD'!I56 -> 172.51 | F82: =E82*H82 -> 172.51 | H82: 1
A83: 46326 | B83: MY | C83: AXI USD | D83: USD | E83: ='AXI - USD'!I63 -> 172.51 | F83: =E83*H83 -> 172.51 | H83: 1
A84: 46356 | B84: MY | C84: AXI USD | D84: USD | E84: ='AXI - USD'!I70 -> 172.51 | F84: =E84*H84 -> 172.51 | H84: 1
A85: 46387 | B85: MY | C85: AXI USD | D85: USD | E85: ='AXI - USD'!I77 -> 172.51 | F85: =E85*H85 -> 172.51 | H85: 1
A86: 46203 | B86: CN | C86: AXS CNY | D86: CNY | E86: ='AXS-CNY'!I166 -> 390217.13 | F86: =E86*H86 -> 57655.752 | H86: =FOREX!K7 -> 0.147753
A87: 46234 | B87: CN | C87: AXS CNY | D87: CNY | E87: ='AXS-CNY'!I173 -> 390217.13 | F87: =E87*H87 -> 57655.752 | H87: =FOREX!K8 -> 0.147753
A88: 46265 | B88: CN | C88: AXS CNY | D88: CNY | E88: ='AXS-CNY'!I179 -> 390217.13 | F88: =E88*H88 -> 57655.752 | H88: =FOREX!K9 -> 0.147753
A89: 46295 | B89: CN | C89: AXS CNY | D89: CNY | E89: ='AXS-CNY'!I186 -> 390217.13 | F89: =E89*H89 -> 57655.752 | H89: =FOREX!K10 -> 0.147753
A90: 46326 | B90: CN | C90: AXS CNY | D90: CNY | E90: ='AXS-CNY'!I193 -> 390217.13 | F90: =E90*H90 -> 57655.752 | H90: =FOREX!K11 -> 0.147753
A91: 46356 | B91: CN | C91: AXS CNY | D91: CNY | E91: ='AXS-CNY'!I200 -> 390217.13 | F91: =E91*H91 -> 57655.752 | H91: =FOREX!K12 -> 0.147753
A92: 46387 | B92: CN | C92: AXS CNY | D92: CNY | E92: ='AXS-CNY'!I207 -> 390217.13 | F92: =E92*H92 -> 57655.752 | H92: =FOREX!K13 -> 0.147753

Sheet Actual Cash Inflow
A3: Sum of Amount (USD) | B3: Column Labels
B4: <11/12/2025 | C4: 2025 | D4: 2026 | J4: 2026 Total | K4: Grand Total
A5: Row Labels | D5: Jan | E5: Feb | F5: Mar | G5: Apr | H5: May | I5: Jun
A6: SG | B6: 610519.62 | D6: 9786.02 | E6: 26431.461 | F6: 29867.021 | G6: 43635.949 | H6: 139172.16 | I6: 278239.45 | J6: 527132.06 | K6: 1137651.7
A7: CN | C7: 80217.28 | D7: 80217.28 | H7: 61504.021 | J7: 141721.3 | K7: 221938.58
A8: MY | B8: 172939.19 | E8: 455699.68 | F8: 7743.3277 | G8: 51666.386 | H8: 967.91597 | J8: 516077.31 | K8: 689016.5
A9: Grand Total | B9: 783458.81 | C9: 80217.28 | D9: 90003.3 | E9: 482131.14 | F9: 37610.349 | G9: 95302.336 | H9: 201644.1 | I9: 278239.45 | J9: 1184930.7 | K9: 2048606.8

Sheet Forecast Cash Inflow
A1: Status | B1: (Multiple Items)
A3: Sum of Amount (USD) | B3: Column Labels
B4: 2026 | I4: 2026 Total | J4: 2027 | K4: Grand Total
A5: Row Labels | B5: Jun | C5: Jul | D5: Aug | E5: Sep | F5: Oct | G5: Nov | H5: Dec
A6: MY | B6: 76124.171 | D6: 96815.02 | I6: 172939.19 | K6: 172939.19
A7: SG | C7: 161048.15 | D7: 102750.48 | E7: 53729.594 | F7: 32666.627 | G7: 63621.872 | H7: 65300.745 | I7: 479117.47 | J7: 67315.392 | K7: 546432.86
A8: Grand Total | B8: 76124.171 | C8: 161048.15 | D8: 199565.5 | E8: 53729.594 | F8: 32666.627 | G8: 63621.872 | H8: 65300.745 | I8: 652056.66 | J8: 67315.392 | K8: 719372.05

Sheet Revenue
A1: Status | B1: (Multiple Items)
A3: Sum of Amount (USD) | B3: Column Labels
B4: 2025 | C4: 2026 | I4: 2026 Total | J4: Grand Total
A5: Row Labels | C5: Jan | D5: Feb | E5: Mar | F5: Apr | G5: May | H5: Jun
A6: CN | B6: 160434.56 | F6: 1403.5877 | G6: 60100.433 | I6: 61504.021 | J6: 221938.58
A7: MY | B7: 507366.06 | D7: 7743.3277 | G7: 173907.11 | I7: 181650.44 | J7: 689016.5
A8: SG | B8: 9786.02 | C8: 33874.465 | D8: 43635.949 | E8: 69308.043 | F8: 248280.53 | G8: 308945.73 | H8: 34216.365 | I8: 738261.09 | J8: 748047.11
A9: Grand Total | B9: 677586.64 | C9: 33874.465 | D9: 51379.277 | E9: 69308.043 | F9: 249684.12 | G9: 542953.28 | H9: 34216.365 | I9: 981415.54 | J9: 1659002.2

Sheet AR
A1: Alpha X Technology Pte Ltd (Singapore) | J1: SGD | K1: 0.77012503
A2: Status | B2: Entity | C2: Invoice Date | D2: Due Date | E2: Expected Inflow | F2: Payment Received Date | G2: Currency | H2: Sub Total | I2: Tax | J2: Total Amount | K2: Amount (USD) | L2: Client Name | M2: Invoice Number | N2: Description | O2: Project Code | Q2: Account Code | R2: Account Category | S2: Department | T2: SST | U2: Remarks
A3: Paid | B3: SG | C3: 46021 | D3: 46051 | E3: 46049 | F3: 46049 | G3: USD | H3: 8978 | I3: 808.02 | J3: =H3+I3 -> 9786.02 | K3: =IF(G3="SGD", J3*$K$1, J3) -> 9786.02 | L3: Soitec Microelectronics Singapore Pte Ltd | M3: INV 2512002 | N3: Development Support Services for PR1 Visual Inspect automation - December 2025 | O3: Soitec 001-202501- PR1 ADSS | P3: SG-00017-7 | Q3: Revenue | R3: Revenue | S3: Sales & Pre-sales | T3: Yes
A4: Paid | B4: SG | C4: 46043 | D4: 46073 | E4: 46108 | F4: 46108 | G4: SGD | H4: 8866.67 | I4: 798 | J4: =H4+I4 -> 9664.67 | K4: =IF(G4="SGD", J4*$K$1, J4) -> 7443.0043 | L4: VisionPower Semiconductor Manufacturing Company Pte Ltd | M4: INV 2601001 | N4: Power BI Consultant Fees - December 2025 | O4: VSMC 001-202508-Power BI | P4: SG-00010-1 | Q4: Revenue | R4: Revenue | S4: Sales & Pre-sales | T4: Yes
A5: Paid | B5: SG | C5: 46044 | D5: 46074 | E5: 46080 | F5: 46080 | G5: SGD | H5: 5000 | I5: 0 | J5: =H5+I5 -> 5000 | K5: =IF(G5="SGD", J5*$K$1, J5) -> 3850.6252 | L5: Armstrong Industrial Corporation Limited | M5: INV 2601002 | N5: AX JIT - IOT BOX (Tianjin) | O5: Armstrong 002-202509- AX JIT (AEM) | P5: SG-00031-1 | Q5: Revenue | R5: Revenue | S5: R&D - Team D | T5: No
A6: Paid | B6: SG | C6: 46052 | D6: 46082 | E6: 46080 | F6: 46080 | G6: SGD | H6: 26900 | I6: 2421 | J6: =H6+I6 -> 29321 | K6: =IF(G6="SGD", J6*$K$1, J6) -> 22580.836 | L6: Armstrong Industrial Corporation Limited | M6: INV 2601003 | N6: Implementation fees - CN Suzhou (Part 2) | O6: Armstrong 001-202508-MES | P6: SG-00008-Suzhou-2 | Q6: Revenue | R6: Revenue | S6: R&D - Team D | T6: Yes
A7: Paid | B7: SG | C7: 46056 | D7: 46086 | E7: 46142 | F7: 46140 | G7: SGD | H7: 8866.67 | I7: 798 | J7: =H7+I7 -> 9664.67 | K7: =IF(G7="SGD", J7*$K$1, J7) -> 7443.0043 | L7: VisionPower Semiconductor Manufacturing Company Pte Ltd | M7: INV 2602001 | N7: Power BI Consultant Fees - January 2026 | O7: VSMC 001-202508-Power BI | P7: SG-00010-2 | Q7: Revenue | R7: Revenue | S7: Sales & Pre-sales | T7: Yes
A8: Paid | B8: SG | C8: 46056 | D8: 46086 | E8: 46091 | F8: 46091 | G8: USD | H8: 8978 | I8: 808.02 | J8: =H8+I8 -> 9786.02 | K8: =IF(G8="SGD", J8*$K$1, J8) -> 9786.02 | L8: Soitec Microelectronics Singapore Pte Ltd | M8: INV 2602002 | N8: Development Support Services for PR1 Visual Inspect automation - January 2026 | O8: Soitec 001-202501- PR1 ADSS | P8: SG-00017-8 | Q8: Revenue | R8: Revenue | S8: Sales & Pre-sales | T8: Yes
A9: Paid | B9: SG | C9: 46062 | D9: 46092 | E9: 46142 | F9: 46125 | G9: SGD | H9: 26900 | I9: 2421 | J9: =H9+I9 -> 29321 | K9: =IF(G9="SGD", J9*$K$1, J9) -> 22580.836 | L9: Armstrong Industrial Corporation Limited | M9: INV 2602003 | N9: Implementation fees - CN Tianjin (UAT Completion) | O9: Armstrong 001-202508-MES | P9: SG-00008-Tianjin-5 | Q9: Revenue | R9: Revenue | S9: R&D - Team D | T9: Yes
A10: Paid | B10: SG | C10: 46063 | D10: 46093 | E10: 46142 | F10: 46125 | G10: SGD | H10: 2609.69 | I10: 234.87 | J10: =H10+I10 -> 2844.56 | K10: =IF(G10="SGD", J10*$K$1, J10) -> 2190.6669 | L10: Armstrong Industrial Corporation Limited | M10: INV 2602004 | N10: Consultation Fee : AOT 17th Nov to 21st Nov 2025 | O10: Armstrong 001-202508-MES | Q10: Revenue | R10: Revenue | S10: R&D - Team D | T10: Yes
A11: Paid | B11: SG | C11: 46080 | D11: 46110 | E11: 46142 | F11: 46125 | G11: SGD | H11: 1948.24 | I11: 175.34 | J11: =H11+I11 -> 2123.58 | K11: =IF(G11="SGD", J11*$K$1, J11) -> 1635.4221 | L11: Armstrong Industrial Corporation Limited | M11: INV 2602005 | N11: Consultation Fee: AOT and ATS 4th Jan - 16th Jan 2026 | O11: Armstrong 001-202508-MES | Q11: Revenue | R11: Revenue | S11: R&D - Team D | T11: Yes
A12: Paid | B12: SG | C12: 46084 | D12: 46114 | E12: 46142 | F12: 46154 | G12: SGD | H12: 585.13 | I12: 52.66 | J12: =H12+I12 -> 637.79 | K12: =IF(G12="SGD", J12*$K$1, J12) -> 491.17804 | L12: Armstrong Industrial Corporation Limited | M12: INV 2603001 | N12: Consultation Fee : ATS Go Live 2 Feb - 6 Feb 2026. | O12: Armstrong 001-202508-MES | Q12: Revenue | R12: Revenue | S12: R&D - Team D | T12: Yes
A13: Paid | B13: SG | C13: 46084 | D13: 46114 | E13: 46142 | F13: 46149 | G13: SGD | H13: 8866.67 | I13: 798 | J13: =H13+I13 -> 9664.67 | K13: =IF(G13="SGD", J13*$K$1, J13) -> 7443.0043 | L13: VisionPower Semiconductor Manufacturing Company Pte Ltd | M13: INV 2603002 | N13: Power BI Consultant Fees - February 2026 | O13: VSMC 001-202508-Power BI | P13: SG-00010-3 | Q13: Revenue | R13: Revenue | S13: Sales & Pre-sales | T13: Yes
A14: Paid | B14: SG | C14: 46086 | D14: 46116 | E14: 46107 | F14: 46107 | G14: USD | H14: 8978 | I14: 808.02 | J14: =H14+I14 -> 9786.02 | K14: =IF(G14="SGD", J14*$K$1, J14) -> 9786.02 | L14: Soitec Microelectronics Singapore Pte Ltd | M14: INV 2603003 | N14: Development Support Services for PR1 Visual Inspect automation - February 2025 | O14: Soitec 001-202501- PR1 ADSS | P14: SG-00017-9 | Q14: Revenue | R14: Revenue | S14: Sales & Pre-sales | T14: Yes
A15: Paid | B15: SG | C15: 46087 | D15: 46117 | E15: 46090 | F15: 46090 | G15: SGD | H15: 2099 | I15: 188.91 | J15: =H15+I15 -> 2287.91 | K15: =IF(G15="SGD", J15*$K$1, J15) -> 1761.9768 | L15: Infinix Hospitality Management Pte Ltd | M15: INV 2603004 | N15: AI Scheduler Setup Fee (Phase 1) + AI Scheduler Monthly Subscription | O15: Infinix 001-202603-AX trace | P15: SG-00045-1 | Q15: Revenue | R15: Revenue | S15: R&D - Team D | T15: Yes
A16: Paid | B16: SG | C16: 46093 | D16: 46123 | E16: 46142 | F16: 46154 | G16: SGD | H16: 46400 | I16: 4176 | J16: =H16+I16 -> 50576 | K16: =IF(G16="SGD", J16*$K$1, J16) -> 38949.844 | L16: Armstrong Industrial Corporation Limited | M16: INV 2603005 | N16: Implementation Fees – CN Changchun (Kick Off) | O16: Armstrong 001-202508-MES | P16: SG-00008-Changchun-7 | Q16: Revenue | R16: Revenue | S16: R&D - Team D | T16: Yes
A17: Paid | B17: SG | C17: 46094 | D17: 46124 | E17: 46107 | F17: 46107 | G17: USD | H17: 1000 | I17: 90 | J17: =H17+I17 -> 1090 | K17: =IF(G17="SGD", J17*$K$1, J17) -> 1090 | L17: Gtrontec Technology Pte Ltd | M17: INV 2603006 | N17: AX Trace Digital Marketing Solution 19 Feb 2026 – 18 Mar 2026 (1/6) | O17: GT 002-202602-AX Trace Digital Mktg Solution | P17: SG-00041-1 | R17: Revenue | S17: R&D - Team D | T17: Yes
A18: Paid | B18: SG | C18: 46111 | D18: 46141 | E18: 46173 | F18: 46139 | G18: USD | H18: 8978 | I18: 808.02 | J18: =H18+I18 -> 9786.02 | K18: =IF(G18="SGD", J18*$K$1, J18) -> 9786.02 | L18: Soitec Microelectronics Singapore Pte Ltd | M18: INV 2603007 | N18: Development Support Services for PR1 Visual Inspect automation - March 2026 | O18: Soitec 001-202501- PR1 ADSS | P18: SG-00017-10 | Q18: Revenue | R18: Revenue | S18: Sales & Pre-sales | T18: Yes
A19: Paid | B19: SG | C19: 46113 | D19: 46143 | E19: 46173 | F19: 46170 | G19: SGD | H19: 8866.67 | I19: 798 | J19: =H19+I19 -> 9664.67 | K19: =IF(G19="SGD", J19*$K$1, J19) -> 7443.0043 | L19: VisionPower Semiconductor Manufacturing Company Pte Ltd | M19: INV 2604001 | N19: Power BI Consultant Fees - March 2026 | O19: VSMC 001-202508-Power BI (1st)
A20: Paid | B20: SG | C20: 46113 | D20: 46143 | E20: 46173 | F20: 46170 | G20: SGD | H20: 8866.67 | I20: 798 | J20: =H20+I20 -> 9664.67 | K20: =IF(G20="SGD", J20*$K$1, J20) -> 7443.0043 | L20: VisionPower Semiconductor Manufacturing Company Pte Ltd | M20: INV 2604002 | N20: Power BI Consultant Fees - March 2026 | O20: VSMC 004-202603-Power BI (2nd)
A21: Paid | B21: SG | C21: 46113 | D21: 46143 | E21: 46173 | F21: 46188 | G21: SGD | H21: 16000 | I21: 1440 | J21: =H21+I21 -> 17440 | K21: =IF(G21="SGD", J21*$K$1, J21) -> 13430.981 | L21: Armstrong Industrial Corporation Limited | M21: INV 2604003 | N21: Project milestone: Phase 1 - 40% upon kick off AX Trace Smart Factory Data Platform | O21: Armstrong 004-202603-AX Trace Smart Factory Data Platform
A22: Declined | B22: SG | C22: 46119 | D22: 46127 | E22: 46142 | G22: SGD | H22: 76345 | I22: 6871.05 | J22: =H22+I22 -> 83216.05 | K22: =IF(G22="SGD", J22*$K$1, J22) -> 64086.763 | L22: Gtrontec Technology Pte Ltd | M22: INV 2604004 | N22: OHT related IP License Fee for 2 years | O22: Nil
A23: Due | B23: SG | C23: 46121 | D23: 46151 | E23: 46234 | G23: SGD | H23: 10800 | I23: 972 | J23: =H23+I23 -> 11772 | K23: =IF(G23="SGD", J23*$K$1, J23) -> 9065.9119 | L23: Armstrong Industrial Corporation Limited | M23: INV 2604005 | N23: Implementation Fees - MY JB (Kick Off) | O23: Armstrong 001-202508-MES
A24: Due | B24: SG | C24: 46121 | D24: 46151 | E24: 46234 | G24: SGD | H24: 46400 | I24: 4176 | J24: =H24+I24 -> 50576 | K24: =IF(G24="SGD", J24*$K$1, J24) -> 38949.844 | L24: Armstrong Industrial Corporation Limited | M24: INV 2604006 | N24: Implementation Fees - MY JB (Kick Off) | O24: Armstrong 001-202508-MES
A25: Due | B25: SG | C25: 46121 | D25: 46151 | E25: 46234 | G25: SGD | H25: 40000 | I25: 3600 | J25: =H25+I25 -> 43600 | K25: =IF(G25="SGD", J25*$K$1, J25) -> 33577.451 | L25: Armstrong Industrial Corporation Limited | M25: INV 2604007 | N25: Implementation Fees - CN Wuhan | O25: Armstrong 001-202508-MES
A26: Paid | B26: SG | C26: 46122 | D26: 46152 | E26: 46173 | F26: 46153 | G26: SGD | H26: 99 | I26: 8.91 | J26: =H26+I26 -> 107.91 | K26: =IF(G26="SGD", J26*$K$1, J26) -> 83.104192 | L26: Infinix Hospitality Management Pte Ltd | M26: INV 2604008 | N26: Ax Trace AI Scheduler Monthly Subscription - April 2026 (2/6) | O26: Infinix 001-202603-AX trace | P26: SG-00045-2 | Q26: Revenue | R26: Revenue | S26: R&D - Team D | T26: Yes
A27: Paid | B27: SG | C27: 46126 | D27: 46156 | E27: 46173 | F27: 46155 | G27: USD | H27: 1000 | I27: 90 | J27: =H27+I27 -> 1090 | K27: =IF(G27="SGD", J27*$K$1, J27) -> 1090 | L27: Gtrontec Technology Pte Ltd | M27: INV 2604009 | N27: Ax Trace Digital Marketing Solution a) Website content audit & revamp plan b) New LinkedIn page setup blog framework & ongoing blog / content creation (weekly) Period : 19 Mar 2026 – 18 Apr 2026 | O27: GT 002-202602-AX Trace Digital Mktg Solution | P27: AXQ00028 | Q27: Revenue | R27: Revenue | T27: Yes
A28: Paid | B28: SG | C28: 46133 | D28: 46163 | E28: 46173 | F28: 46199 | G28: SGD | H28: 8866.67 | I28: 798.0003 | J28: =H28+I28 -> 9664.6703 | K28: =IF(G28="SGD", J28*$K$1, J28) -> 7443.0045 | L28: VisionPower Semiconductor Manufacturing Company Pte Ltd | M28: INV 2604011 | N28: POWER BI CONSULTANTS AS QUO : AXQ00015 for the month of April 2026 | O28: VSMC 001-202508-Power BI (1st) | P28: PO 3325001371 | Q28: Revenue | R28: Revenue | T28: Yes
A29: Paid | B29: SG | C29: 46133 | D29: 46163 | E29: 46173 | F29: 46170 | G29: SGD | H29: 8866.67 | I29: 798.0003 | J29: =H29+I29 -> 9664.6703 | K29: =IF(G29="SGD", J29*$K$1, J29) -> 7443.0045 | L29: VisionPower Semiconductor Manufacturing Company Pte Ltd | M29: INV 2604012 | N29: 2nd POWER BI CONSULTANTS AS QUO : AXQ00015 for the month of April 2026 | O29: VSMC 004-202603-Power BI (2nd) | P29: PO 3325001593 | Q29: Revenue | R29: Revenue | T29: Yes
A30: Pending | B30: SG | C30: 46133 | D30: 46194 | E30: 46265 | G30: USD | H30: 56000 | I30: 5040 | J30: =H30+I30 -> 61040 | K30: =IF(G30="SGD", J30*$K$1, J30) -> 61040 | L30: Advanced Micro Foundry Pte Ltd | M30: INV 2604010 | N30: Implementation of Equipment Automation for 4 equipment types | O30: AMF 003-202506-EAS | P30: PO002149 Ver. 1.2 | Q30: Revenue | R30: Revenue | T30: Yes
A31: Due | B31: SG | C31: 46140 | D31: 46170 | E31: 46234 | G31: SGD | H31: 2705.65 | I31: 243.5085 | J31: =H31+I31 -> 2949.1585 | K31: =IF(G31="SGD", J31*$K$1, J31) -> 2271.2208 | L31: Armstrong Industrial Corporation Limited | M31: INV 2604013 | N31: Consultation Fee: Tianjin (AOT) Go-Live 4 Mar, and Changchun (AOC) kick off 9 Mar - 13 Mar 2026 | O31: Armstrong 001-202508-MES | P31: PO26M00038 | Q31: Revenue | R31: Revenue | T31: Yes
A32: Paid | B32: SG | C32: 46141 | D32: 46142 | E32: 46172 | F32: 46150 | G32: USD | H32: 59000 | I32: 0 | J32: =H32+I32 -> 59000 | K32: =IF(G32="SGD", J32*$K$1, J32) -> 59000 | L32: Shanghai Wilson Optimus Technology Co., Ltd., | M32: INV 2604014 | N32: Taiwan IP License | O32: Wilson 001-202604-IP Licenseout | Q32: Revenue | R32: Revenue
A33: Paid | B33: SG | C33: 46147 | D33: 46177 | E33: 46203 | F33: 46168 | G33: USD | H33: 8978 | I33: 808.02 | J33: =H33+I33 -> 9786.02 | K33: =IF(G33="SGD", J33*$K$1, J33) -> 9786.02 | L33: Soitec Microelectronics Singapore Pte Ltd | M33: INV 2605001 | N33: Development Support Services for PR1 Visual Inspect automation - April 2026 | O33: Soitec 001-202501- PR1 ADSS | P33: SG-00017-11 | Q33: Revenue | R33: Revenue
A34: Paid | B34: SG | C34: 46150 | D34: 46180 | E34: 46203 | F34: 46176 | G34: CNY | H34: 1575966.3 | I34: 0 | J34: =H34+I34 -> 1575966.3 | K34: 232853.75 | L34: Getech (ShenZhen) Co., Ltd | M34: INV 2605002 | N34: Technical Service Fee - 50% kick off payment | O34: GT 001-202604-Resources Service | Q34: Revenue | R34: Revenue
A35: Pending | B35: SG | C35: 46157 | D35: 46187 | E35: 46234 | G35: SGD | H35: 18800 | I35: 1692 | J35: =H35+I35 -> 20492 | K35: =IF(G35="SGD", J35*$K$1, J35) -> 15781.402 | L35: Armstrong Industrial Corporation Limited | M35: INV 2605003 | N35: Implementation Fees – CHN ChangChun (UAT) | O35: Armstrong 001-202508-MES | P35: PO25M00126 | Q35: Revenue | R35: Revenue | T35: Yes
A36: Pending | B36: SG | C36: 46157 | D36: 46187 | E36: 46234 | G36: SGD | H36: 8100 | I36: 729 | J36: =H36+I36 -> 8829 | K36: =IF(G36="SGD", J36*$K$1, J36) -> 6799.4339 | L36: Armstrong Industrial Corporation Limited | M36: INV 2605004 | N36: Implementation Fees – MY JB (UAT) | O36: Armstrong 001-202508-MES | P36: PO26M00034 | Q36: Revenue | R36: Revenue | T36: Yes
A37: Pending | B37: SG | C37: 46157 | D37: 46187 | E37: 46234 | G37: SGD | H37: 18800 | I37: 1692 | J37: =H37+I37 -> 20492 | K37: =IF(G37="SGD", J37*$K$1, J37) -> 15781.402 | L37: Armstrong Industrial Corporation Limited | M37: INV 2605005 | N37: Implementation Fees – MY JB (UAT) | O37: Armstrong 001-202508-MES | P37: PO25M00126 | Q37: Revenue | R37: Revenue | T37: Yes
A38: Forecast | B38: SG | C38: 46157 | D38: 46218 | E38: 46233 | G38: USD | J38: =H38+I38 -> 0 | K38: =IF(G38="SGD", J38*$K$1, J38) -> 0 | L38: Advanced Micro Foundry Pte Ltd | M38: N/A | N38: 20% payment (every 4 tools) | O38: AMF 003-202506-EAS | P38: SG-00005-2
A39: Forecast | B39: SG | C39: 46157 | D39: 46218 | E39: 46233 | G39: USD | J39: =H39+I39 -> 0 | K39: =IF(G39="SGD", J39*$K$1, J39) -> 0 | L39: Advanced Micro Foundry Pte Ltd | M39: N/A | N39: 20% payment (1 tool only) | O39: AMF 003-202506-EAS | P39: SG-00005-3
A40: Paid | B40: SG | C40: 46164 | D40: 46194 | E40: 46203 | F40: 46202 | G40: SGD | H40: 2599 | I40: 233.91 | J40: =H40+I40 -> 2832.91 | K40: =IF(G40="SGD", J40*$K$1, J40) -> 2181.6949 | L40: Infinix Hospitality Management Pte Ltd | M40: INV 2605006 | N40: Ax Trace AI Scheduler Monthly Subscription - May 2026 (3/6) | O40: Infinix 001-202603-AX trace | P40: SG-00045-3 | Q40: Revenue | R40: Revenue | S40: R&D - Team D | T40: Yes
A41: Paid | B41: SG | C41: 46164 | D41: 46194 | E41: 46203 | F41: 46199 | G41: SGD | H41: 8866.67 | I41: 798 | J41: =H41+I41 -> 9664.67 | K41: =IF(G41="SGD", J41*$K$1, J41) -> 7443.0043 | L41: VisionPower Semiconductor Manufacturing Company Pte Ltd | M41: INV 2605008 | N41: Power BI Consultant Fees - May 2026 | O41: VSMC 001-202508-Power BI (1st) | P41: SG-00010-6 | Q41: Revenue | R41: Revenue | S41: Sales & Pre-sales | T41: Yes
A42: Paid | B42: SG | C42: 46164 | D42: 46194 | E42: 46203 | F42: 46199 | G42: SGD | H42: 8866.67 | I42: 798 | J42: =H42+I42 -> 9664.67 | K42: =IF(G42="SGD", J42*$K$1, J42) -> 7443.0043 | L42: VisionPower Semiconductor Manufacturing Company Pte Ltd | M42: INV 2605009 | N42: Power BI Consultant Fees - May 2026 | O42: VSMC 004-202603-Power BI (2nd) | P42: SG-00010-6 | Q42: Revenue | R42: Revenue | S42: Sales & Pre-sales | T42: Yes
A43: Pending | B43: SG | C43: 46164 | D43: 46194 | E43: 46234 | G43: USD | H43: 1000 | I43: 90 | J43: =H43+I43 -> 1090 | K43: =IF(G43="SGD", J43*$K$1, J43) -> 1090 | L43: Gtrontec Technology Pte Ltd | M43: INV 2605007 | N43: AX Trace Digital Marketing Solution 19 Apr 2026 – 18 May 2026 (2/6) | O43: GT 002-202602-AX Trace Digital Mktg Solution | P43: SG-00041-2 | R43: Revenue | S43: R&D - Team D | T43: Yes
A44: Pending | B44: SG | C44: 46170 | D44: 46200 | E44: 46234 | G44: USD | H44: 8978 | I44: 808.02 | J44: =H44+I44 -> 9786.02 | K44: =IF(G44="SGD", J44*$K$1, J44) -> 9786.02 | L44: Soitec Microelectronics Singapore Pte Ltd | M44: INV 2605010 | N44: Development Support Services for PR1 Visual Inspect automation - May 2026 | O44: Soitec 001-202501- PR1 ADSS | P44: SG-00017-12 | Q44: Revenue | R44: Revenue | S44: Sales & Pre-sales | T44: Yes
A45: Pending | B45: SG | C45: 46176 | D45: 46206 | E45: 46234 | G45: SGD | H45: 569.41 | I45: 51.25 | J45: =H45+I45 -> 620.66 | K45: =IF(G45="SGD", J45*$K$1, J45) -> 477.9858 | L45: Armstrong Industrial Corporation Limited | M45: INV 2606001 | N45: Consultation Fee: AOC UAT 13th to 17th April 2026 | O45: Armstrong 001-202508-MES | P45: PO26M00053 | Q45: Revenue | R45: Revenue | T45: Yes
A46: Pending | B46: SG | C46: 46176 | D46: 46206 | E46: 46234 | G46: SGD | H46: 2093.66 | I46: 188.43 | J46: =H46+I46 -> 2282.09 | K46: =IF(G46="SGD", J46*$K$1, J46) -> 1757.4946 | L46: Armstrong Industrial Corporation Limited | M46: INV 2606002 | N46: Consultation Fee: AEM Kick Off 7th to 10th Apr 2026 | O46: Armstrong 001-202508-MES | P46: PO26M00054 | Q46: Revenue | R46: Revenue | T46: Yes
A47: Pending | B47: SG | C47: 46191 | D47: 46221 | E47: 46234 | G47: SGD | H47: 8866.67 | I47: 798 | J47: 9664.67 | K47: 7443.0043 | L47: VisionPower Semiconductor Manufacturing Company Pte Ltd | M47: INV 2606003 | N47: Power BI Consultant Fees - June 2026 | O47: VSMC 001-202508-Power BI (1st) | P47: SG-00010-7 | Q47: Revenue | R47: Revenue | S47: Sales & Pre-sales | T47: Yes
A48: Pending | B48: SG | C48: 46195 | D48: 46225 | E48: 46234 | G48: SGD | H48: 2364.12 | I48: 212.77 | J48: =H48+I48 -> 2576.89 | K48: =IF(G48="SGD", J48*$K$1, J48) -> 1984.5275 | L48: Armstrong Industrial Corporation Limited | M48: INV 2606004 | N48: Consultation fee for AEM MES UAT between 10th to 15th May 2026 | O48: Armstrong 001-202508-MES | Q48: Revenue | R48: Revenue | S48: Sales & Pre-sales | T48: Yes
A49: Pending | B49: SG | C49: 46195 | D49: 46225 | E49: 46234 | G49: SGD | H49: 1700.91 | I49: 153.08 | J49: =H49+I49 -> 1853.99 | K49: =IF(G49="SGD", J49*$K$1, J49) -> 1427.8041 | L49: Armstrong Industrial Corporation Limited | M49: INV 2606005 | N49: Consultation fee for AOC MES Go-Live between 19th May to 27th May 2026 | O49: Armstrong 001-202508-MES | Q49: Revenue | R49: Revenue | S49: Sales & Pre-sales | T49: Yes
A50: Paid | B50: SG | C50: 46195 | D50: 46225 | E50: 46234 | F50: 46195 | G50: SGD | H50: 99 | I50: 8.91 | J50: =H50+I50 -> 107.91 | K50: 7444.0043 | L50: Infinix Hospitality Management Pte Ltd | M50: INV 2606006 | N50: Ax Trace AI Scheduler Monthly Subscription - June 2026 (4/6) | O50: Infinix 001-202603-AX trace | P50: SG-00045-4 | Q50: Revenue | R50: Revenue | S50: Sales & Pre-sales | T50: Yes
A51: Pending | B51: SG | C51: 46197 | D51: 46227 | E51: 46234 | G51: SGD | H51: 15000 | I51: 1350 | J51: =H51+I51 -> 16350 | K51: =IF(G51="SGD", J51*$K$1, J51) -> 12591.544 | L51: Armstrong Industrial Corporation Limited | M51: INV 2606007 | N51: MES Consulting service for Wuhan (AOW) 29 June 2026 - 28 July 2026 | O51: Armstrong 011-202606-UAT and GO Live support for Wuhan (AOW) | P51: SG-00065-1 | Q51: Revenue | R51: Revenue | S51: Sales & Pre-sales | T51: Yes
A52: Pending | B52: SG | C52: 46198 | D52: 46228 | E52: 46234 | G52: USD | H52: 1000 | I52: 90 | J52: 1090 | K52: 1090 | L52: Gtrontec Technology Pte Ltd | M52: INV 2606008 | N52: AX Trace Digital Marketing Solution 19 May 2026 – 18 Jun 2026 (3/6) | O52: GT 002-202602-AX Trace Digital Mktg Solution | P52: SG-00041-3 | Q52: Revenue | R52: Revenue | S52: Sales & Pre-sales | T52: Yes
A53: Forecast | B53: SG | C53: 46204 | D53: 46235 | E53: 46265 | G53: SGD | H53: 18900 | I53: 1701 | J53: =H53+I53 -> 20601 | K53: =IF(G53="SGD", J53*$K$1, J53) -> 15865.346 | L53: Armstrong Industrial Corporation Limited | M53: N/A | N53: (Suzhou)Go Live 18% Payment | O53: Armstrong 001-202508-MES | P53: SG-00008-Suzhou-3
A54: Forecast | B54: SG | C54: 46235 | D54: 46266 | E54: 46295 | G54: SGD | H54: 18900 | I54: 1701 | J54: =H54+I54 -> 20601 | K54: =IF(G54="SGD", J54*$K$1, J54) -> 15865.346 | L54: Armstrong Industrial Corporation Limited | M54: N/A | N54: (Tianjin)Go Live 18% Payment | O54: Armstrong 001-202508-MES | P54: SG-00008-Tianjin-6
A55: Forecast | B55: SG | C55: 46235 | D55: 46266 | E55: 46295 | G55: SGD | H55: 14318.08 | I55: 1288.6272 | J55: =H55+I55 -> 15606.707 | K55: =IF(G55="SGD", J55*$K$1, J55) -> 12019.116 | L55: Armstrong Industrial Corporation Limited | M55: N/A | N55: (Changchun) UAT 17% Payment | O55: Armstrong 001-202508-MES | P55: SG-00008-Changchun-8
A56: Forecast | B56: SG | C56: 46266 | D56: 46296 | E56: 46325 | G56: SGD | H56: 8225.28 | I56: 740.2752 | J56: =H56+I56 -> 8965.5552 | K56: =IF(G56="SGD", J56*$K$1, J56) -> 6904.5985 | L56: Armstrong Industrial Corporation Limited | M56: N/A | N56: (Changchun) Go Live 16% Payment | O56: Armstrong 001-202508-MES | P56: SG-00008-Changchun-9
A57: Forecast | B57: SG | C57: 46296 | D57: 46327 | E57: 46356 | G57: SGD | H57: 46400 | I57: 4176 | J57: =H57+I57 -> 50576 | K57: =IF(G57="SGD", J57*$K$1, J57) -> 38949.844 | L57: Armstrong Industrial Corporation Limited | M57: N/A | N57: (Thailand) Kick Off 61% Payment | O57: Armstrong 001-202508-MES | P57: SG-00008-Thailand-13
A58: Forecast | B58: SG | C58: 46332 | D58: 46362 | E58: 46387 | G58: SGD | H58: 18800 | I58: 1692 | J58: =H58+I58 -> 20492 | K58: =IF(G58="SGD", J58*$K$1, J58) -> 15781.402 | L58: Armstrong Industrial Corporation Limited | M58: N/A | N58: (JB) UAT 25% Payment | O58: Armstrong 001-202508-MES | P58: SG-00008-JB-11
A59: Forecast | B59: SG | C59: 46332 | D59: 46362 | E59: 46387 | G59: SGD | H59: 10800 | I59: 972 | J59: =H59+I59 -> 11772 | K59: =IF(G59="SGD", J59*$K$1, J59) -> 9065.9119 | L59: Armstrong Industrial Corporation Limited | M59: N/A | N59: (JB) Go Live 14% Payment | O59: Armstrong 001-202508-MES | P59: SG-00008-JB-12
A60: Forecast | B60: SG | C60: 46341 | D60: 46371 | E60: 46387 | G60: SGD | H60: 18800 | I60: 1692 | J60: =H60+I60 -> 20492 | K60: =IF(G60="SGD", J60*$K$1, J60) -> 15781.402 | L60: Armstrong Industrial Corporation Limited | M60: N/A | N60: (Thailand) UAT 25% Payment | O60: Armstrong 001-202508-MES | P60: SG-00008-Thailand-14
A61: Forecast | B61: SG | C61: 46371 | D61: 46402 | E61: 46418 | G61: SGD | H61: 10800 | I61: 972 | J61: =H61+I61 -> 11772 | K61: =IF(G61="SGD", J61*$K$1, J61) -> 9065.9119 | L61: Armstrong Industrial Corporation Limited | M61: N/A | N61: (Thailand) Go Live 14% Payment | O61: Armstrong 001-202508-MES | P61: SG-00008-Thailand-15
A62: Forecast | B62: SG | C62: 46402 | D62: 46433 | E62: 46446 | G62: SGD | H62: 40000 | I62: 3600 | J62: =H62+I62 -> 43600 | K62: =IF(G62="SGD", J62*$K$1, J62) -> 33577.451 | L62: Armstrong Industrial Corporation Limited | M62: N/A | N62: (Shen Yang) Go Live 100% | O62: Armstrong 001-202508-MES | P62: SG-00008-Shen Yang-17
A63: Forecast | B63: SG | E63: 46234 | G63: SGD | H63: 99 | I63: 8.91 | J63: =H63+I63 -> 107.91 | K63: =IF(G63="SGD", J63*$K$1, J63) -> 83.104192 | L63: Infinix Hospitality Management Pte Ltd | M63: N/A | N63: Ax Trace AI Scheduler Monthly Subscription - June 2026 (4/6) | O63: Infinix 001-202603-AX trace | P63: SG-00045-4
A64: Forecast | B64: SG | E64: 46265 | G64: SGD | H64: 99 | I64: 8.91 | J64: =H64+I64 -> 107.91 | K64: =IF(G64="SGD", J64*$K$1, J64) -> 83.104192 | L64: Infinix Hospitality Management Pte Ltd | M64: N/A | N64: Ax Trace AI Scheduler Monthly Subscription - July 2026 (5/6) | O64: Infinix 001-202603-AX trace | P64: SG-00045-5
A65: Forecast | B65: SG | E65: 46295 | G65: SGD | H65: 99 | I65: 8.91 | J65: =H65+I65 -> 107.91 | K65: =IF(G65="SGD", J65*$K$1, J65) -> 83.104192 | L65: Infinix Hospitality Management Pte Ltd | M65: N/A | N65: Ax Trace AI Scheduler Monthly Subscription - August 2026 (6/6) | O65: Infinix 001-202603-AX trace | P65: SG-00045-6
A66: Forecast | B66: SG | E66: 46265 | G66: SGD | H66: 8866.67 | I66: 798 | J66: =H66+I66 -> 9664.67 | K66: =IF(G66="SGD", J66*$K$1, J66) -> 7443.0043 | L66: VisionPower Semiconductor Manufacturing Company Pte Ltd | M66: N/A | N66: Power BI Consultant Fees - June 2026 | O66: VSMC 001-202508-Power BI (1st) | P66: SG-00010-7
A67: Forecast | B67: SG | E67: 46295 | G67: SGD | H67: 8866.67 | I67: 798 | J67: =H67+I67 -> 9664.67 | K67: =IF(G67="SGD", J67*$K$1, J67) -> 7443.0043 | L67: VisionPower Semiconductor Manufacturing Company Pte Ltd | M67: N/A | N67: Power BI Consultant Fees - July 2026 | O67: VSMC 001-202508-Power BI (1st) | P67: SG-00010-8
A68: Forecast | B68: SG | E68: 46326 | G68: SGD | H68: 8866.67 | I68: 798 | J68: =H68+I68 -> 9664.67 | K68: =IF(G68="SGD", J68*$K$1, J68) -> 7443.0043 | L68: VisionPower Semiconductor Manufacturing Company Pte Ltd | M68: N/A | N68: Power BI Consultant Fees - August 2026 | O68: VSMC 001-202508-Power BI (1st) | P68: SG-00010-9
A69: Forecast | B69: SG | E69: 46356 | G69: SGD | H69: 8866.67 | I69: 798 | J69: =H69+I69 -> 9664.67 | K69: =IF(G69="SGD", J69*$K$1, J69) -> 7443.0043 | L69: VisionPower Semiconductor Manufacturing Company Pte Ltd | M69: N/A | N69: Power BI Consultant Fees - September 2026 | O69: VSMC 001-202508-Power BI (1st) | P69: SG-00010-10
A70: Forecast | B70: SG | E70: 46387 | G70: SGD | H70: 8866.67 | I70: 798 | J70: =H70+I70 -> 9664.67 | K70: =IF(G70="SGD", J70*$K$1, J70) -> 7443.0043 | L70: VisionPower Semiconductor Manufacturing Company Pte Ltd | M70: N/A | N70: Power BI Consultant Fees - October 2026 | O70: VSMC 001-202508-Power BI (1st) | P70: SG-00010-11
A71: Forecast | B71: SG | E71: 46418 | G71: SGD | H71: 8866.67 | I71: 798 | J71: =H71+I71 -> 9664.67 | K71: =IF(G71="SGD", J71*$K$1, J71) -> 7443.0043 | L71: VisionPower Semiconductor Manufacturing Company Pte Ltd | M71: N/A | N71: Power BI Consultant Fees - November 2026 | O71: VSMC 001-202508-Power BI (1st) | P71: SG-00010-12
A72: Forecast | B72: SG | E72: 46265 | G72: SGD | H72: 8866.67 | I72: 798 | J72: =H72+I72 -> 9664.67 | K72: =IF(G72="SGD", J72*$K$1, J72) -> 7443.0043 | L72: VisionPower Semiconductor Manufacturing Company Pte Ltd | M72: N/A | N72: Power BI Consultant Fees - June 2026 | O72: VSMC 004-202603-Power BI (2nd) | P72: SG-00010-7
A73: Forecast | B73: SG | E73: 46295 | G73: SGD | H73: 8866.67 | I73: 798 | J73: =H73+I73 -> 9664.67 | K73: =IF(G73="SGD", J73*$K$1, J73) -> 7443.0043 | L73: VisionPower Semiconductor Manufacturing Company Pte Ltd | M73: N/A | N73: Power BI Consultant Fees - July 2026 | O73: VSMC 004-202603-Power BI (2nd) | P73: SG-00010-8
A74: Forecast | B74: SG | E74: 46326 | G74: SGD | H74: 8866.67 | I74: 798 | J74: =H74+I74 -> 9664.67 | K74: =IF(G74="SGD", J74*$K$1, J74) -> 7443.0043 | L74: VisionPower Semiconductor Manufacturing Company Pte Ltd | M74: N/A | N74: Power BI Consultant Fees - August 2026 | O74: VSMC 004-202603-Power BI (2nd) | P74: SG-00010-9
... A87: Forecast | B87: SG | E87: 46418 | G87: USD | H87: 8978 | I87: 808.02 | J87: =H87+I87 -> 9786.02 | K87: =IF(G87="SGD", J87*$K$1, J87) -> 9786.02 | L87: Soitec Microelectronics Singapore Pte Ltd | M87: N/A | N87: Development Support Services for PR1 Visual Inspect automation - November 2026 | O87: Soitec 003-202605-6 months Application Development Services | P87: SG-00051-6
A88: Paid | B88: MY | C88: 46000 | D88: 46090 | E88: 46142 | F88: 46135 | G88: MYR | H88: 197700 | I88: 15816 | J88: =H88+I88 -> 213516 | K88: 51666.386 | L88: S.E.H (Shah Alam) Sdn Bhd | M88: INV 2512001 | N88: 99-SPOT-PRO3743L / PROJECT-90504 | O88: SEH 001-202505-napson | P88: MY-00006-1 | Q88: Revenue | R88: Revenue | S88: Sales & Pre-sales | T88: Yes
A89: Paid | B89: MY | C89: 46008 | D89: 46038 | E89: 46081 | F89: 46066 | G89: MYR | H89: 1876020 | I89: 7200 | J89: =H89+I89 -> 1883220 | K89: 455699.68 | L89: Dai-Ichi Jitsugyo (Malaysia) Sdn Bhd | M89: INV 2512002 | N89: Phase 2 - 60% payment milestone upon Hardware Delivery, Installation of License and MES Integration Test | O89: MIMOS 001-202504-MES, EAS | P89: MY-00004-2 | Q89: Revenue | R89: Revenue | S89: Sales & Pre-sales | T89: Yes
A90: Paid | B90: MY | C90: 46057 | D90: 46087 | E90: 46112 | F90: 46094 | G90: MYR | H90: 32000 | I90: 0 | J90: =H90+I90 -> 32000 | K90: 7743.3277 | L90: Dai-Ichi Jitsugyo (Malaysia) Sdn Bhd | M90: INV 2502001 | N90: Phase 1 - Project Implementation (Balance payment milestone) | O90: Denso 001-202509-Simulation | P90: MY-00032-2 | Q90: Revenue | R90: Revenue | S90: Sales & Pre-sales | T90: No
A91: Pending | B91: MY | C91: 46147 | D91: 46238 | E91: 46265 | G91: MYR | H91: 26000 | I91: 2080 | J91: =H91+I91 -> 28080 | K91: 6794.7701 | L91: S.E.H (Shah Alam) Sdn Bhd | M91: INV 2605001 | N91: Software compatibility alignment, interface configuration & data handling, Deployment readiness & support | O91: SEH 006-202603-stocker change request | P91: PO No.: SAPO024440
A92: Pending | B92: MY | C92: 46147 | D92: 46238 | E92: 46265 | G92: MYR | H92: 102990 | I92: 8239.2 | J92: =H92+I92 -> 111229.2 | K92: 26915.13 | L92: S.E.H (Shah Alam) Sdn Bhd | M92: INV 2605002 | N92: Software & Licenses, Services & Support | O92: SEH 003-202411-Stocker | P92: PO No.: SAPO018003
A93: Paid | B93: MY | C93: 46149 | D93: 46179 | E93: 46173 | F93: 46171 | G93: MYR | H93: 4000 | I93: 0 | J93: =H93+I93 -> 4000 | K93: 967.91597 | L93: Dai-Ichi Jitsugyo (Malaysia) Sdn Bhd | M93: INV 2605003 | N93: Enhancement for Burn In and I/R Simulation Project | O93: Denso 002-202604-Simulation Enhancement | P93: PO No.: HP/26/04/512 as at 07/04/2026
A94: Pending | B94: MY | C94: 46164 | D94: 46254 | E94: 46264 | G94: MYR | H94: 241470 | I94: 19317.6 | J94: =H94+I94 -> 260787.6 | K94: 63105.121 | L94: S.E.H (Shah Alam) Sdn Bhd | M94: INV 2605004 | N94: IG#11 & IG#12 Automation Implementation | O94: SEH 002-202506-IG Project | P94: PO No.: SAPO023182 | Q94: Revenue | R94: Revenue | T94: Yes
A95: Pending | B95: MY | C95: 46171 | D95: 46201 | E95: 46203 | G95: MYR | H95: 313870 | I95: 720 | J95: =H95+I95 -> 314590 | K95: 76124.171 | L95: Dai-Ichi Jitsugyo (Malaysia) Sdn Bhd | M95: INV 2605005 | N95: Phase 3 - 10% payment milestone upon Hardware Delivery, Installation of License and MES Integration Test | O95: MIMOS 001-202504-MES, EAS | P95: MY-00004-3 | Q95: Revenue | R95: Revenue | S95: Sales & Pre-sales | T95: Yes
A96: Paid | B96: CN | C96: 45985 | D96: 45996 | E96: 46022 | F96: 46002 | G96: CNY | H96: 65526.89 | I96: 3931.61 | J96: =H96+I96 -> 69458.5 | K96: 9784.3336 | L96: 格创东智（深圳）科技有限公司 | M96: 25312000000383595327 | N96: 大章鱼 - 软件开发服务 | O96: GT 001-202511-章鱼 | Q96: Revenue | R96: Revenue | S96: R&D
A97: Paid | B97: CN | C97: 45985 | D97: 45996 | E97: 46022 | F97: 46002 | G97: CNY | H97: 235849.06 | I97: 14150.94 | J97: =H97+I97 -> 250000 | K97: 35216.473 | L97: 格创东智（深圳）科技有限公司 | M97: 25312000000383591535 | N97: 大章鱼 - 软件开发服务 | O97: GT 001-202511-章鱼 | Q97: Revenue | R97: Revenue | S97: R&D
A98: Paid | B98: CN | C98: 45985 | D98: 45996 | E98: 46022 | F98: 46002 | G98: CNY | H98: 235849.06 | I98: 14150.94 | J98: =H98+I98 -> 250000 | K98: 35216.473 | L98: 格创东智（深圳）科技有限公司 | M98: 25312000000383592715 | N98: 大章鱼 - 软件开发服务 | O98: GT 001-202511-章鱼 | Q98: Revenue | R98: Revenue | S98: R&D
A99: Paid | B99: CN | C99: 46020 | D99: 46034 | E99: 46052 | F99: 46045 | G99: CNY | H99: 537225 | I99: 32233.5 | J99: =H99+I99 -> 569458.5 | K99: 80217.28 | L99: 格创东智（深圳）科技有限公司 | M99: 25312000000435000000 | N99: 大章鱼 - 软件开发服务 | O99: GT 001-202511-章鱼 | Q99: Revenue | R99: Revenue | S99: R&D
A100: Paid | B100: CN | C100: 46127 | D100: 46142 | E100: 46142 | F100: 46169 | G100: CNY | H100: 9400 | I100: 564 | J100: =H100+I100 -> 9964 | K100: 1403.5877 | L100: 格创东智（武汉）科技有限公司 | M100: 26312000002309900000 | N100: 长电FDC POC项目 | O100: 长电绍兴 JCET 002-202603 | Q100: Revenue | R100: Revenue
A101: Paid | B101: CN | C101: 46167 | D101: 46173 | E101: 46173 | F101: 46169 | G101: CNY | H101: 402500 | I101: 24150 | J101: =H101+I101 -> 426650 | K101: 60100.433 | L101: 格创东智（深圳）科技有限公司 | O101: 大章鱼 - 软件开发服务 | Q101: Revenue | R101: Revenue

Sheet Detail1
A1: Details for Sum of Amount (USD) - Entity: MY, Group: ERROR, Months (Payment Date/ Planned Date ): May, Years (Payment Date/ Planned Date ): 2026, Status: Paid (+)
A3: Status | B3: Entity | C3: Billing Date | D3: Due Date | E3: Payment Date/ Planned Date | F3: Currency | G3: Sub Total | H3: Tax | I3: Total Amount | J3: Amount (USD) | K3: Payee | L3: Invoice Number | M3: Description | N3: Account Code | O3: Account Category | P3: Department | Q3: Group | R3: Submitter | S3: Approval | T3: Authorisation | U3: Remarks | V3: GST Claimable
A4: Paid | B4: MY | C4: 46173 | D4: 46173 | E4: 46171 | F4: MYR | J4: 15742.95 | K4: MY Staff | L4: Net Pay - May 2026 | M4: Net Pay - May 2026 | N4: Salaries & Wages | O4: Headcount Costs | P4: R&D - MY Team | Q4: ERROR

Sheet Actual Cash Outflow
A1: Status | B1: Paid
A2: Amount (USD) | B2: (Multiple Items)
A4: Sum of Amount (USD) | B4: Column Labels
B5: 2026 | H5: 2026 Total | I5: Grand Total
A6: Row Labels | B6: Jan | C6: Feb | D6: Mar | E6: Apr | F6: May | G6: Jun
A7: DSC | B7: 26646.327 | C7: 11781.977 | D7: 132634.77 | E7: 28722.289 | F7: 13277.291 | G7: 3505.3275 | H7: 216567.98 | I7: 216567.98
A8: SG | B8: 20532.76 | C8: 5797.04 | D8: 78660.742 | E8: 22263.5 | F8: 5811.7935 | H8: 133065.84 | I8: 133065.84
A9: Employee Benefits | F9: 49.353546 | H9: 49.353546 | I9: 49.353546
A10: Staff Welfare - Gift & Tokens | F10: 49.353546 | H10: 49.353546 | I10: 49.353546
A11: Headcount Costs | B11: 20532.76 | C11: 5797.04 | D11: 37639.17 | E11: 22263.5 | F11: 5762.44 | H11: 91994.91 | I11: 91994.91
A12: Salaries & Wages | B12: 20532.76 | C12: 3053.23 | D12: 37329.25 | E12: 16700.13 | F12: 5.43 | H12: 77620.8 | I12: 77620.8
A13: Statutory Contribution | C13: 2743.81 | D13: 309.92 | E13: 5563.37 | F13: 5757.01 | H13: 14374.11 | I13: 14374.11
A14: Travelling Expenses | D14: 41021.572 | H14: 41021.572 | I14: 41021.572
A15: Transportation fee - National | D15: 41021.572 | H15: 41021.572 | I15: 41021.572
A16: MY | B16: 6113.5671 | C16: 5984.9373 | D16: 53974.03 | E16: 6458.7886 | F16: 7465.497 | G16: 3505.3275 | H16: 83502.148 | I16: 83502.148
A17: General & Administrative | B17: 322851.76 | C17: 275433.43 | D17: 238343.26 | E17: 129925.27 | F17: 264494.88 | G17: 1.0460758e+09 | H17: 1.0473069e+09 | I17: 1.0473069e+09
A18: SG | B18: 145791.4 | C18: 53522.87 | D18: 206138.89 | E18: 112710.01 | F18: 242949.16 | G18: 1.0459179e+09 | H18: 1.046679e+09 | I18: 1.046679e+09
A19: Accrual | F19: 19716.608 | H19: 19716.608 | I19: 19716.608
A20: Accrual | F20: 19716.608 | H20: 19716.608 | I20: 19716.608
A21: Accrual - Expenses of 2025 | B21: 40570.651 | G21: 120800.18 | H21: 161370.83 | I21: 161370.83
A22: Accrual - Expenses of 2025 | B22: 40570.651 | G22: 120800.18 | H22: 161370.83 | I22: 161370.83
A23: Bank | F23: 180760.77 | G23: 62000 | H23: 242760.77 | I23: 242760.77
A24: OCBC SG - SGD | F24: 180760.77 | G24: 62000 | H24: 242760.77 | I24: 242760.77
A25: Bank Charges | B25: 119.44452 | C25: 0.30225956 | D25: 99.85226 | E25: 39.44226 | F25: 40.89226 | G25: 23.27226 | H25: 323.20582 | I25: 323.20582
A26: Bank Charges | B26: 119.44452 | C26: 0.30225956 | D26: 99.85226 | E26: 39.44226 | F26: 40.89226 | G26: 23.27226 | H26: 323.20582 | I26: 323.20582
A27: Corporate Tax Expenses | D27: 8853.79 | H27: 8853.79 | I27: 8853.79
A28: Corporate Income Tax Expenses | D28: 8853.79 | H28: 8853.79 | I28: 8853.79
A29: Courier Charges | B29: 101.96177 | D29: 65.337408 | F29: 55.174892 | H29: 222.47407 | I29: 222.47407
A30: Courier Charges | B30: 101.96177 | D30: 65.337408 | F30: 55.174892 | H30: 222.47407 | I30: 222.47407
A31: Current Asset | D31: 138.70722 | H31: 138.70722 | I31: 138.70722
A32: Prepayment | D32: 138.70722 | H32: 138.70722 | I32: 138.70722
A33: Direct Costs | G33: 1.0435574e+09 | H33: 1.0435574e+09 | I33: 1.0435574e+09
A34: Contract Services - Project delivery | G34: 1.0435574e+09 | H34: 1.0435574e+09 | I34: 1.0435574e+09
A35: Employee Benefits | B35: 6720.698 | C35: 11950.492 | D35: 25811.694 | E35: 4185.3138 | F35: 3620.4232 | G35: 684626.63 | H35: 736915.25 | I35: 736915.25
A36: Insurance expenses | B36: 1106.0522 | C36: 8254.177 | D36: 24285.978 | E36: 2403.7605 | F36: 1114.4972 | H36: 37164.464 | I36: 37164.464
A37: Staff Welfare - Gift & Tokens | C37: 200.23251 | D37: 61.53299 | E37: 133.18542 | F37: 49.089996 | H37: 444.04092 | I37: 444.04092
A38: Staff Welfare - Meal & Refreshment | B38: 1464.0234 | C38: 3218.8839 | D38: 1346.6623 | E38: 1648.3679 | F38: 1442.0586 | G38: 684626.63 | H38: 693746.63 | I38: 693746.63
A39: Staff Welfare - Medical Expenses | B39: 4150.6225 | D39: 117.52108 | H39: 4268.1435 | I39: 4268.1435
A40: Staff Welfare - Recreation, Training & Events | C40: 277.1988 | F40: 1014.7774 | H40: 1291.9762 | I40: 1291.9762
A41: General Expenses | E41: 4.2356877 | F41: 43.020603 | H41: 47.256291 | I41: 47.256291
A42: General Expenses | E42: 4.2356877 | F42: 43.020603 | H42: 47.256291 | I42: 47.256291
A43: Headcount Costs | B43: 33691.04 | C43: 27762.191 | D43: 115487.94 | E43: 78190.211 | F43: 32580.94 | G43: 24590.549 | H43: 312302.87 | I43: 312302.87
A44: Salaries & Wages | B44: 33691.04 | C44: 25680.711 | D44: 115129.2 | E44: 72719.241 | F44: 25157.86 | G44: 24590.549 | H44: 296968.6 | I44: 296968.6
A45: Statutory Contribution | C45: 2081.48 | D45: 358.74 | E45: 5470.97 | F45: 7423.08 | H45: 15334.27 | I45: 15334.27
A46: License Fee | F46: 309.28325 | H46: 309.28325 | I46: 309.28325
A47: License Fee | F47: 309.28325 | H47: 309.28325 | I47: 309.28325
A48: Network & Server | B48: 797.04441 | D48: 216.59258 | E48: 108.08705 | H48: 1121.724 | I48: 1121.724
A49: Network & Server | B49: 797.04441 | D49: 216.59258 | E49: 108.08705 | H49: 1121.724 | I49: 1121.724
A50: Non-Current Liabilities | B50: 561.33625 | C50: 549.07604 | D50: 549.07527 | G50: 681.71 | H50: 2341.1976 | I50: 2341.1976
A51: Leasing | B51: 561.33625 | C51: 549.07604 | D51: 549.07527 | G51: 681.71 | H51: 2341.1976 | I51: 2341.1976
A52: Office Supplies | B52: 332.91868 | C52: 132.85427 | D52: 95.695736 | E52: 9.6034591 | F52: 239.03177 | G52: 62.293 | H52: 872.39692 | I52: 872.39692
A53: Consumable Tools | B53: 62.670752 | H53: 62.670752 | I53: 62.670752
A54: Office Supplies | B54: 270.24793 | C54: 132.85427 | D54: 95.695736 | E54: 7.6242378 | F54: 147.52579 | G54: 62.293 | H54: 716.24096 | I54: 716.24096
A55: Printing & Stationery | E55: 1.9792213 | F55: 91.505985 | H55: 93.485207 | I55: 93.485207
A56: Penalty | D56: 231.03751 | H56: 231.03751 | I56: 231.03751
A57: Penalty | D57: 231.03751 | H57: 231.03751 | I57: 231.03751
A58: Professional & Consultancy Fees | B58: 27999.142 | C58: 69.311253 | D58: 1068.9335 | H58: 29137.387 | I58: 29137.387
A59: Professional & Consultancy Fees | B59: 27999.142 | C59: 69.311253 | D59: 1068.9335 | H59: 29137.387 | I59: 29137.387
A60: Recruitment Related Fees | D60: 2643.0691 | E60: 48.517877 | F60: 197.66223 | H60: 2889.2492 | I60: 2889.2492
A61: Recruitment Related Fees | D61: 2643.0691 | E61: 48.517877 | F61: 197.66223 | H61: 2889.2492 | I61: 2889.2492
A62: Rental | B62: 20503.634 | D62: 40111.623 | E62: 20055.812 | G62: 20055.81 | H62: 100726.88 | I62: 100726.88
A63: Rental of Office | B63: 20503.634 | D63: 40111.623 | E63: 20055.812 | G63: 20055.81 | H63: 100726.88 | I63: 100726.88
A64: Repair & Maintenance | C64: 316.5984 | H64: 316.5984 | I64: 316.5984
A65: Repair & Maintenance | C65: 316.5984 | H65: 316.5984 | I65: 316.5984
A66: Sales Expenses | B66: 2240.2825 | C66: 5124.7532 | D66: 1639.5322 | E66: 3259.7467 | F66: 2523.2702 | G66: 1443313.1 | H66: 1458100.7 | I66: 1458100.7
A67: Business Meals - International | B67: 785.48654 | C67: 369.32886 | D67: 769.9325 | E67: 361.88945 | F67: 143.41751 | H67: 2430.0549 | I67: 2430.0549
A68: Business Meals - National | B68: 1305.6459 | C68: 4741.1 | D68: 689.61377 | E68: 2897.8573 | F68: 2379.8526 | G68: 1443313.1 | H68: 1455327.2 | I68: 1455327.2
A69: Hampers & Gift | B69: 149.15009 | C69: 14.324326 | D69: 179.98592 | H69: 343.46034 | I69: 343.46034
A70: Small Value Assets | B70: 2281.6563 | D70: 839.43628 | H70: 3121.0925 | I70: 3121.0925
A71: Small Value Assets | B71: 2281.6563 | D71: 839.43628 | H71: 3121.0925 | I71: 3121.0925
A72: Subscription Fee | B72: 163.32974 | D72: 339.54813 | E72: 124.92968 | F72: 172.27715 | G72: 104.2811 | H72: 904.3658 | I72: 904.3658
A73: Subscription Fee | B73: 163.32974 | D73: 339.54813 | E73: 124.92968 | F73: 172.27715 | G73: 104.2811 | H73: 904.3658 | I73: 904.3658
A74: Tax Expenses (GST/SST/VAT) | C74: 6292.6916 | H74: 6292.6916 | I74: 6292.6916
A75: Tax Expenses (GST/SST/VAT) | C75: 6292.6916 | H75: 6292.6916 | I75: 6292.6916
A76: Travelling Expenses | B76: 9192.3663 | C76: 831.71963 | D76: 7252.3916 | E76: 5635.3899 | F76: 2570.5702 | G76: 3762.7051 | H76: 29245.143 | I76: 29245.143
A77: Accommodation - International | B77: 2120.405 | C77: 9.7035754 | F77: 820.43778 | G77: 129.4293 | H77: 3079.9757 | I77: 3079.9757
A78: Personal Meals - International | B78: 76.881896 | C78: 18.359781 | D78: 52.715058 | E78: 28.155771 | F78: 5.239987 | G78: 26.1338 | H78: 207.48629 | I78: 207.48629
A79: Personal Meals - National | B79: 7.87321 | C79: 159.85485 | D79: 20.532534 | E79: 35.7261 | F79: 14.223929 | H79: 238.21063 | I79: 238.21063
A80: Transportation fee - International | B80: 6932.3299 | C80: 541.37479 | D80: 7170.4031 | E80: 3938.9277 | F80: 1674.982 | G80: 2389.541 | H80: 22647.559 | I80: 22647.559
A81: Transportation fee - National | B81: 54.876274 | C81: 102.42663 | D81: 8.7409191 | E81: 1632.5804 | F81: 55.686489 | G81: 1217.601 | H81: 3071.9117 | I81: 3071.9117
A82: Upkeep of Office | B82: 377.91408 | C82: 492.88002 | D82: 462.07502 | E82: 924.15004 | G82: 462.07502 | H82: 2719.0942 | I82: 2719.0942
A83: Cleaning Fees | C83: 462.07502 | D83: 462.07502 | E83: 924.15004 | G83: 462.07502 | H83: 2310.3751 | I83: 2310.3751
A84: Upkeep of Offices | B84: 377.91408 | C84: 30.805001 | H84: 408.71908 | I84: 408.71908
A85: Utilities | B85: 137.97801 | D85: 232.55466 | E85: 124.57542 | F85: 119.23832 | H85: 614.34641 | I85: 614.34641
A86: Electricity | B86: 137.97801 | D86: 232.55466 | E86: 124.57542 | F86: 119.23832 | H86: 614.34641 | I86: 614.34641
A87: MY | B87: 174772.94 | C87: 220586.44 | D87: 24346.812 | E87: 16170.667 | F87: 21171.414 | G87: 157991.91 | H87: 615040.18 | I87: 615040.18
A88: CN | B88: 2287.4211 | C88: 1324.12 | D88: 7857.56 | E88: 1044.59 | F88: 374.3 | H88: 12887.991 | I88: 12887.991
A89: Others | B89: 5924.5905 | D89: 3080.7312 | E89: 26 | H89: 9031.3217 | I89: 9031.3217
A90: SG | B90: 5924.5905 | D90: 3080.7312 | E90: 26 | H90: 9031.3217 | I90: 9031.3217
A91: Bank Charges | E91: 26 | H91: 26 | I91: 26
A92: Bank Charges | E92: 26 | H92: 26 | I92: 26
A93: Non-Current Asset | B93: 5924.5905 | H93: 5924.5905 | I93: 5924.5905
A94: Renovation | B94: 5924.5905 | H94: 5924.5905 | I94: 5924.5905
A95: Small Value Assets | D95: 3080.7312 | H95: 3080.7312 | I95: 3080.7312
A96: Small Value Assets | D96: 3080.7312 | H96: 3080.7312 | I96: 3080.7312
A97: Research & Development | B97: 87959.49 | C97: 47206.402 | D97: 217454.26 | E97: 93964.07 | F97: 54299.694 | G97: 13213.22 | H97: 514097.13 | I97: 514097.13
A98: SG | B98: 61693.253 | C98: 6743.8945 | D98: 161699.24 | E98: 55953.09 | F98: 3964.144 | G98: 4619.1299 | H98: 294672.75 | I98: 294672.75
A99: Accrual - Expenses of 2025 | C99: 118.32201 | H99: 118.32201 | I99: 118.32201
A100: Accrual - Expenses of 2025 | C100: 118.32201 | H100: 118.32201 | I100: 118.32201
A101: Bank Charges | G101: 0.0077 | H101: 0.0077 | I101: 0.0077
...

Sheet Forecast Cash Outflow
A1: Status | B1: (Multiple Items)
A3: Row Labels | B3: Sum of Amount (USD)
A4: 2026 | B4: 2072175.3
A5: Jun | B5: 339241.5
A6: 46188 | B6: 8916.2844
A7: CN | B7: 8916.2844
A8: 46198 | B8: 2035
A9: MY | B9: 2035
A10: 46203 | B10: 328290.21
A11: SG | B11: 242514.34
A12: CN | B12: 23650.33
A13: MY | B13: 62125.541
A14: Jul | B14: 305694.94
A15: 46218 | B15: 4164.4003
A16: CN | B16: 90.2
A17: MY | B17: 4074.2003
A18: 46228 | B18: 33724.633
A19: SG | B19: 31968.369
A20: MY | B20: 1756.2645
A21: 46233 | B21: 113.55729
A22: SG | B22: 113.55729
A23: 46234 | B23: 267692.35
A24: SG | B24: 195644.93
A25: CN | B25: 4150.33
A26: MY | B26: 67897.094
A27: Aug | B27: 301533.5
A28: 46249 | B28: 4074.2003
A29: MY | B29: 4074.2003
A30: 46259 | B30: 35322.091
A31: SG | B31: 31109.176
A32: MY | B32: 4212.9145
A33: 46265 | B33: 262137.21
A34: SG | B34: 182987.21
A35: MY | B35: 79150
A36: Sep | B36: 264694.5
A37: 46280 | B37: 4074.2003
A38: MY | B38: 4074.2003
A39: 46290 | B39: 35322.091
A40: SG | B40: 31109.176
A41: MY | B41: 4212.9145
A42: 46295 | B42: 225298.21
A43: SG | B43: 189148.21
A44: MY | B44: 36150
A45: Oct | B45: 275528.27
A46: 46310 | B46: 4074.2003
A47: MY | B47: 4074.2003
A48: 46320 | B48: 30816.86
A49: SG | B49: 26603.945
A50: MY | B50: 4212.9145
A51: 46326 | B51: 240637.21
A52: SG | B52: 182987.21
A53: MY | B53: 57650
A54: Nov | B54: 289794.84
A55: 46341 | B55: 4536.2753
A56: SG | B56: 462.07502
A57: MY | B57: 4074.2003
A58: 46351 | B58: 44621.351
A59: SG | B59: 40408.436
A60: MY | B60: 4212.9145
A61: 46356 | B61: 240637.21
A62: SG | B62: 182987.21
A63: MY | B63: 57650
A64: Dec | B64: 295687.76
A65: 46371 | B65: 4074.2003
A66: MY | B66: 4074.2003
A67: 46381 | B67: 49299.86
A68: SG | B68: 45086.946
A69: MY | B69: 4212.9145
A70: 46387 | B70: 242313.7
A71: SG | B71: 185163.7
A72: MY | B72: 57150
A73: 2027 | B73: 28162.11
A74: Jan | B74: 9679.1092
A75: 46402 | B75: 4074.2003
A76: MY | B76: 4074.2003
A77: 46412 | B77: 5604.9089
A78: SG | B78: 5348.5183
A79: MY | B79: 256.39055
A80: Mar | B80: 18483.001
A81: 46477 | B81: 18483.001
A82: SG | B82: 18483.001
A83: Grand Total | B83: 2100337.4

Sheet COGS
A1: Status | B1: Paid
A2: Group | B2: DSC
A4: Row Labels | B4: Sum of Amount (USD)
A5: 2026 | B5: 219507.67
A6: Jan | B6: 26646.327
A7: MY | B7: 6113.5671
A8: SG | B8: 20532.76
A9: Headcount Costs | B9: 20532.76
A10: Feb | B10: 11781.977
A11: MY | B11: 5984.9373
A12: SG | B12: 5797.04
A13: Headcount Costs | B13: 5797.04
A14: Mar | B14: 132634.77
A15: MY | B15: 53974.03
A16: SG | B16: 78660.742
... A35: Grand Total | B35: 219507.67

Sheet Expenses
A1: Status | B1: (All)
A3: Row Labels | B3: Sum of Amount (USD)
A4: 2026
A5: Jan
A6: CN | B6: -64687.108
A7: General & Administrative | B7: 2232.48
A8: Finance | B8: 344.51834
A9: Bank Charges | B9: 4.6119913
A10: Bank Charges | B10: 4.6119913
A11: Headcount Costs | B11: 96.590001
A12: Statutory Contribution | B12: 96.590001
A13: Other Income | B13: -54.941102
A14: Interest Income | B14: -54.941102
A15: Subscription Fee | B15: 298.25745
A16: Subscription Fee | B16: 298.25745
A17: General | B17: 1735.2049
... A255: Grand Total | B255: 7.830918e+08

Sheet Detail3
A1: Details for Sum of Amount (USD) - Account Category: Direct Costs, Entity: SG, Months (Payment Date/ Planned Date ): Jun, Years (Payment Date/ Planned Date ): 2026, Department : Business Operation (+)
A3: Status | B3: Entity | C3: Billing Date | D3: Due Date | E3: Payment Date/ Planned Date | F3: Currency | G3: Sub Total | H3: Tax | I3: Total Amount | J3: Amount (USD) | K3: Payee | L3: Invoice Number | M3: Description | N3: Account Code | O3: Account Category | P3: Department | Q3: Group | R3: Submitter | S3: Approval | T3: Authorisation | U3: Remarks | V3: GST Claimable
A4: Paid | B4: SG | C4: 46140 | D4: 46185 | E4: 46185 | F4: SGD | G4: 245688 | H4: 22111.92 | I4: 267799.92 | J4: 267799.92 | K4: ABeam Consulting (Singapore) Pte Ltd | L4: 1200312539 | M4: Purchase of S4 HAHA PMC License - SAP Finance Base - SAP Supply Chain Base - SAP Integration Suite,Standard edition - SAP AI Unit | N4: Contract Services - Project delivery | O4: Direct Costs | P4: Finance | Q4: General & Administrative

Sheet Detail4
A1: Details for Sum of Amount (USD) - Account Category: Accrual, Entity: SG, Months (Payment Date/ Planned Date ): May, Years (Payment Date/ Planned Date ): 2026, Department : Business Operation (+)
A3: Status | B3: Entity | C3: Billing Date | D3: Due Date | E3: Payment Date/ Planned Date | F3: Currency | G3: Sub Total | H3: Tax | I3: Total Amount | J3: Amount (USD) | K3: Payee | L3: Invoice Number | M3: Description | N3: Account Code | O3: Account Category | P3: Department | Q3: Group | R3: Submitter | S3: Approval | T3: Authorisation | U3: Remarks | V3: GST Claimable
A4: Paid | B4: SG | C4: 46161 | D4: 46171 | E4: 46170 | F4: SGD | G4: 16377.27 | H4: 0 | I4: 16377.27 | J4: 12612.55 | K4: Iras-Income Tax | L4: Payment Slip Number 25530286881052 | M4: Directive to Pay Tax for Wu WenLong | N4: Accrual | O4: Accrual | P4: HR | Q4: General & Administrative | R4: OCBC SGD
A5: Paid | B5: SG | C5: 46148 | D5: 46160 | E5: 46160 | F5: SGD | G5: 9164.8 | H5: 0 | I5: 9164.8 | J5: 7104.0581 | K5: Iras-Income Tax | L5: Payment Slip Number 25530281007030 | M5: Directive to Pay Tax for Jin Chao | N5: Accrual | O5: Accrual | P5: HR | Q5: General & Administrative

Sheet Detail5
A1: Details for Sum of Amount (USD) - Account Code : Accrual - Expenses of 2025, Account Category: Accrual - Expenses of 2025, Months (Payment Date/ Planned Date ): Jun, Years (Payment Date/ Planned Date ): 2026, Department : Business Operation (+)
A3: Status | B3: Entity | C3: Billing Date | D3: Due Date | E3: Payment Date/ Planned Date | F3: Currency | G3: Sub Total | H3: Tax | I3: Total Amount | J3: Amount (USD) | K3: Payee | L3: Invoice Number | M3: Description | N3: Account Code | O3: Account Category | P3: Department | Q3: Group | R3: Submitter | S3: Approval | T3: Authorisation | U3: Remarks | V3: GST Claimable
A4: Paid | B4: SG | C4: 46182 | D4: 46195 | E4: 46185 | F4: SGD | G4: 31 | H4: 0 | I4: 31 | J4: 120800.18 | K4: SkillsFuture Singapore Agency | M4: Outstanding SDL Payable for year 2025 | N4: Accrual - Expenses of 2025 | O4: Accrual - Expenses of 2025 | P4: HR | Q4: General & Administrative

Sheet Sheet1
A1: Department | B1: (Multiple Items)
A3: Sum of Amount (USD) | B3: Column Labels
B4: 2026 | N4: 2027 | P4: Grand Total
A5: Row Labels | B5: Jan | C5: Feb | D5: Mar | E5: Apr | F5: May | G5: Jun | H5: Jul | I5: Aug | J5: Sep | K5: Oct | L5: Nov | M5: Dec | N5: Jan | O5: Mar
A6: Research & Development | B6: 6054.4613 | C6: 20774.941 | D6: 217454.25 | E6: 67557.145 | F6: 54299.694 | G6: -2.6493834e+08 | H6: 77244.646 | I6: 92784.335 | J6: 60784.335 | K6: 72279.103 | L6: 86545.67 | M6: 72279.103 | N6: 5256.1033 | P6: -2.6410502e+08
A7: SG | B7: 61707.677 | C7: -19687.567 | D7: 161699.23 | E7: 29546.165 | F7: 3964.144 | G7: -2.6499093e+08 | H7: 52744.646 | I7: 52284.335 | J7: 52284.335 | K7: 47779.103 | L7: 62045.67 | M7: 47779.103 | N7: 5256.1033 | P7: -2.6443353e+08
A8: Accrual - Expenses of 2025 | C8: 118.32201 | P8: 118.32201
A9: Accrual - Expenses of 2025 | C9: 118.32201 | P9: 118.32201
A10: Bank Charges | G10: 0.0077 | P10: 0.0077
A11: Bank Charges | G11: 0.0077 | P11: 0.0077
A12: Employee Benefits | C12: 21.563501 | G12: 149.2645 | P12: 170.828
A13: Insurance expenses | C13: 21.563501 | P13: 21.563501
A14: Staff Welfare - Medical Expenses | G14: 149.2645 | P14: 149.2645
A15: Headcount Costs | B15: 56907.16 | C15: 5535.06 | D15: 132626.35 | E15: 49403.7 | F15: 2331.64 | G15: 44448 | H15: 42523 | I15: 42523 | J15: 42523 | K15: 42523 | L15: 42523 | M15: 42523 | P15: 546389.91
A16: Salaries & Wages | B16: 56907.16 | C16: 2960.72 | D16: 132325.52 | E16: 36691.53 | F16: 2.33 | G16: 40003 | H16: 40003 | I16: 40003 | J16: 40003 | K16: 40003 | L16: 40003 | M16: 40003 | P16: 508908.26
A17: Staff Allowance | E17: 7701.2503 | G17: 1925 | P17: 9626.2503
A18: Statutory Contribution | C18: 2574.34 | D18: 300.83 | E18: 5010.92 | F18: 2329.31 | G18: 2520 | H18: 2520 | I18: 2520 | J18: 2520 | K18: 2520 | L18: 2520 | M18: 2520 | P18: 27855.4
A19: Intercompany | B19: 14.423721 | P19: 14.423721
A20: Intercompany - Alpha X (Shanghai) Technology Co Ltd | B20: 14.423721 | P20: 14.423721
A21: Network & Server | D21: 25829.335 | E21: 4696.5459 | G21: 5314.5819 | H21: 10221.646 | I21: 9761.3348 | J21: 9761.3348 | K21: 5256.1033 | L21: 19522.67 | M21: 5256.1033 | N21: 5256.1033 | P21: 100875.76
A22: Network & Server | D22: 25829.335 | E22: 4696.5459 | G22: 5314.5819 | H22: 10221.646 | I22: 9761.3348 | J22: 9761.3348 | K22: 5256.1033 | L22: 19522.67 | M22: 5256.1033 | N22: 5256.1033 | P22: 100875.76
A23: Office Supplies | B23: 40.940692 | F23: 84.614937 | P23: 125.55563
A24: Consumable Tools | B24: 40.940692 | P24: 40.940692
A25: Office Supplies | F25: 84.614937 | P25: 84.614937
A26: Revenue | C26: -26431.461 | E26: -26406.925 | G26: -2.6504339e+08 | P26: -2.6509623e+08
A27: Sales - Services Fees | E27: -26406.925 | G27: -2.6504339e+08 | P27: -2.650698e+08
A28: Sales - Software | C28: -26431.461 | P28: -26431.461
A29: Sales Expenses | E29: 28.363705 | F29: 15.409902 | G29: 1242.934 | P29: 1286.7076
A30: Business Meals - International | E30: 28.363705 | F30: 15.409902 | P30: 43.773607
A31: Business Meals - National | G31: 1242.934 | P31: 1242.934
A32: Subscription Fee | B32: 4335.4067 | C32: 0 | D32: 125.0375 | E32: 275.29659 | F32: 173.05134 | G32: 95.4646 | P32: 5004.2567
A33: Subscription Fee | B33: 4335.4067 | C33: 0 | D33: 125.0375 | E33: 275.29659 | F33: 173.05134 | G33: 95.4646 | P33: 5004.2567
A34: Travelling Expenses | B34: 409.74547 | C34: 1068.9489 | D34: 3118.5058 | E34: 1549.1835 | F34: 1359.4278 | G34: 1206.4591 | P34: 8712.2706
A35: Accommodation - International | D35: 430.03012 | E35: 236.15884 | F35: 730.97818 | P35: 1397.1671
A36: Personal Meals - International | C36: 223.80604 | D36: 164.05203 | F36: 154.03701 | G36: 179.7873 | P36: 721.68238
A37: Transportation fee - International | B37: 368.41112 | C37: 719.95909 | D37: 2335.3271 | E37: 1206.1852 | F37: 388.01483 | G37: 988.6723 | P37: 6006.5697
A38: Transportation fee - National | B38: 41.334353 | C38: 125.18382 | D38: 189.0965 | E38: 106.83945 | F38: 86.397773 | G38: 37.9995 | P38: 586.85139
A39: CN | B39: -69957.271 | C39: 18164.18 | D39: 28817.26 | E39: 13019.82 | F39: 26600.6 | G39: 19500 | P39: 36144.589
A40: Employee Benefits | E40: 1006 | P40: 1006
A41: Staff Welfare - Meal & Refreshment | E41: 1006 | P41: 1006
A42: General Expenses | B42: 701.29313 | P42: 701.29313
A43: General Expenses | B43: 701.29313 | P43: 701.29313
A44: Headcount Costs | B44: 10359.73 | C44: 18164.18 | D44: 28758.94 | E44: 11683.35 | F44: 26600.6 | G44: 19500 | P44: 115066.8
A45: Salaries & Wages | B45: 10359.73 | C45: 18164.18 | D45: 28758.94 | E45: 11683.35 | F45: 26600.6 | G45: 19500 | P45: 115066.8
A46: R&D Contract Services | B46: 791.63407 | P46: 791.63407
A47: R&D Contract Services | B47: 791.63407 | P47: 791.63407
A48: Revenue | B48: -81919.453 | P48: -81919.453
A49: Sales - Services Fees | B49: -81919.453 | P49: -81919.453
A50: Travelling Expenses | B50: 109.524 | D50: 58.32 | E50: 330.47 | P50: 498.314
A51: Personal Meals - National | D51: 58.32 | P51: 58.32
A52: Transportation fee - National | B52: 109.524 | E52: 330.47 | P52: 439.994
A53: MY | B53: 14304.056 | C53: 22298.328 | D53: 26937.76 | E53: 24991.16 | F53: 23734.95 | G53: 33094.09 | H53: 24500 | I53: 40500 | J53: 8500 | K53: 24500 | L53: 24500 | M53: 24500 | P53: 292360.34
A54: Headcount Costs | B54: 14304.056 | C54: 22298.328 | D54: 26937.76 | E54: 24991.16 | F54: 23734.95 | G54: 33094.09 | H54: 24500 | I54: 40500 | J54: 8500 | K54: 24500 | L54: 24500 | M54: 24500 | P54: 292360.34
A55: Salaries & Wages | B55: 14304.056 | C55: 19443.288 | D55: 19218.912 | E55: 24991.16 | F55: 20989.038 | G55: 26954.54 | H55: 21500 | I55: 37500 | J55: 5500 | K55: 21500 | L55: 21500 | M55: 21500 | P55: 254900.99
A56: Statutory Contribution | C56: 2855.04 | D56: 7718.848 | F56: 2745.912 | G56: 6139.55 | H56: 3000 | I56: 3000 | J56: 3000 | K56: 3000 | L56: 3000 | M56: 3000 | P56: 37459.35
A57: Sales & Marketing | B57: 59541.768 | C57: -451490.61 | D57: 61878.3 | E57: 5407.3527 | F57: -156141.61 | G57: -186091.62 | H57: 77160 | I57: 73160 | J57: 73160 | K57: 73160 | L57: 73160 | M57: 74160 | P57: -222936.42
A58: SG | B58: 43503.177 | C58: 11275.762 | D58: 45713.079 | E58: 40511.689 | F58: -106169.33 | G58: -205448.54 | H58: 59510 | I58: 59510 | J58: 59510 | K58: 59510 | L58: 59510 | M58: 59510 | P58: 186445.83
A59: Direct Costs | G59: 168.7532 | P59: 168.7532
A60: Contract Services - Project delivery | G60: 168.7532 | P60: 168.7532
A61: Employee Benefits | C61: 7.7012503 | P61: 7.7012503
A62: Staff Welfare - Recreation, Training & Events | C62: 7.7012503 | P62: 7.7012503
A63: Headcount Costs | B63: 52437.15 | C63: 7945.06 | D63: 71174.8 | E63: 57364.8 | F63: 9882.36 | G63: 59569.3 | H63: 59510 | I63: 59510 | J63: 59510 | K63: 59510 | L63: 59510 | M63: 59510 | P63: 615433.47
A64: Salaries & Wages | B64: 52437.15 | C64: 4186.98 | D64: 70750.24 | E64: 47601.76 | F64: 1971.07 | G64: 51010.39 | H64: 51010 | I64: 51010 | J64: 51010 | K64: 51010 | L64: 51010 | M64: 51010 | P64: 534017.59
A65: Statutory Contribution | C65: 3758.08 | D65: 424.56 | E65: 9763.04 | F65: 7911.29 | G65: 8558.91 | H65: 8500 | I65: 8500 | J65: 8500 | K65: 8500 | L65: 8500 | M65: 8500 | P65: 81415.88
A66: Marketing Expense | D66: 1040.9241 | F66: 177.43092 | G66: 251.79 | P66: 1470.145
A67: Marketing Expense | D67: 1040.9241 | F67: 177.43092 | G67: 251.79 | P67: 1470.145
A68: Revenue | B68: -9786.02 | D68: -29867.021 | E68: -17229.024 | F68: -117081.54 | G68: -265861.61 | P68: -439825.22
A69: Sales - Services Fees | B69: -9786.02 | D69: -29867.021 | E69: -17229.024 | F69: -117081.54 | G69: -265861.61 | P69: -439825.22
A70: Sales Expenses | B70: 852.04666 | C70: 218.08 | D70: 1134.2324 | F70: 108.55145 | P70: 2312.9105
A71: Business Development Cost (Entertainment) | D71: 485.17877 | F71: 25.796859 | P71: 510.97563
A72: Business Meals - International | F72: 57.577845 | P72: 57.577845
A73: Business Meals - National | B73: 802.87059 | C73: 218.08 | D73: 649.05367 | F73: 25.176742 | P73: 1695.181
A74: Hampers & Gift | B74: 49.17607 | P74: 49.17607
A75: Subscription Fee | E75: 80.185418 | F75: 208.24984 | G75: 357.9268 | P75: 646.36206
A76: Subscription Fee | E76: 80.185418 | F76: 208.24984 | G76: 357.9268 | P76: 646.36206
A77: Travelling Expenses | C77: 3104.9208 | D77: 2230.1435 | E77: 295.72801 | F77: 535.61813 | G77: 65.296 | P77: 6231.7064
A78: Accommodation - International | D78: 85.044907 | E78: 295.72801 | F78: 288.021 | P78: 668.79392
A79: Accommodation - National | C79: 2310.3751 | D79: 1217.0055 | P79: 3527.3806
A80: Personal Meals - International | F80: 7.8212231 | P80: 7.8212231
A81: Personal Meals - National | C81: 191.72263 | D81: 74.16304 | P81: 265.88567
A82: Transportation fee - International | C82: 318.28497 | D82: 667.0669 | F82: 171.84987 | P82: 1157.2017
A83: Transportation fee - National | C83: 284.5381 | D83: 186.86314 | F83: 67.926044 | G83: 65.296 | P83: 604.62328
A84: CN | B84: 3037.6836 | C84: 3150.14 | D84: 5502.4 | E84: 2182.16 | F84: -58542.44 | G84: 4000 | H84: 4000 | P84: -36670.056
A85: Headcount Costs | B85: 1920.72 | C85: 3150.14 | D85: 5502.4 | E85: 2182.16 | F85: 5392.4 | G85: 4000 | H85: 4000 | P85: 26147.82
A86: Salaries & Wages | B86: 1920.72 | C86: 3150.14 | D86: 5502.4 | E86: 2182.16 | F86: 5392.4 | G86: 4000 | H86: 4000 | P86: 26147.82
A87: Revenue | F87: -63934.84 | P87: -63934.84
A88: Sales - Services Fees | F88: -63934.84 | P88: -63934.84
A89: Telecommunication | B89: 9.622461 | P89: 9.622461
A90: Telecommunication | B90: 9.622461 | P90: 9.622461
A91: Travelling Expenses | B91: 1107.3411 | P91: 1107.3411
A92: Transportation fee - International | B92: 1101.2 | P92: 1101.2
A93: Transportation fee - National | B93: 6.14117 | P93: 6.14117
A94: MY | B94: 13000.908 | C94: -465916.52 | D94: 10662.821 | E94: -37286.496 | F94: 8570.1581 | G94: 15356.925 | H94: 13650 | I94: 13650 | J94: 13650 | K94: 13650 | L94: 13650 | M94: 14650 | P94: -372712.2
A95: Employee Benefits | B95: 81.20576 | G95: 49.5 | P95: 130.70576
A96: Staff Welfare - Gift & Tokens | G96: 49.5 | P96: 49.5
A97: Staff Welfare - Meal & Refreshment | B97: 81.20576 | P97: 81.20576
A98: Headcount Costs | B98: 11741.11 | C98: 17192.28 | D98: 17024.85 | E98: 14379.89 | F98: 9577.69 | G98: 15208.6 | H98: 13650 | I98: 13650 | J98: 13650 | K98: 13650 | L98: 13650 | M98: 14650 | P98: 168024.42
A99: Salaries & Wages | B99: 11741.11 | C99: 15523.81 | D99: 11759 | E99: 13050.33 | F99: 8417.32 | G99: 13662.52 | H99: 12500 | I99: 12500 | J99: 12500 | K99: 12500 | L99: 12500 | M99: 13500 | P99: 150154.09
A100: Statutory Contribution | C100: 1668.47 | D100: 5265.85 | E100: 1329.56 | F100: 1160.37 | G100: 1546.08 | H100: 1150 | I100: 1150 | J100: 1150 | K100: 1150 | L100: 1150 | M100: 1150 | P100: 17870.33
A101: Office Supplies | B101: 8.8920307 | P101: 8.8920307
...

Sheet Detail2
A1: Details for Sum of Amount (USD) - Account Category: Headcount Costs, Entity: MY, Group: ERROR, Years (Payment Date/ Planned Date ): 2026, Department : Business Operation (+)
A3: Status | B3: Entity | C3: Billing Date | D3: Due Date | E3: Payment Date/ Planned Date | F3: Currency | G3: Sub Total | H3: Tax | I3: Total Amount | J3: Amount (USD) | K3: Payee | L3: Invoice Number | M3: Description | N3: Account Code | O3: Account Category | P3: Department | Q3: Group | R3: Submitter | S3: Approval | T3: Authorisation | U3: Remarks | V3: GST Claimable
A4: Paid | B4: MY | C4: 46173 | D4: 46173 | E4: 46171 | F4: MYR | J4: 15742.95 | K4: MY Staff | L4: Net Pay - May 2026 | M4: Net Pay - May 2026 | N4: Salaries & Wages | O4: Headcount Costs | P4: R&D - MY Team | Q4: ERROR

Sheet Sheet5
A1: Department | B1: (All)
A3: Sum of Amount (USD) | B3: Column Labels
B4: 2026 | C4: 2027 | D4: Grand Total
A5: Row Labels
A6: DSC | B6: 431233.48 | D6: 431233.48
A7: MY | B7: 131037.15 | D7: 131037.15
A8: Direct Costs | B8: 47494.427 | D8: 47494.427
A9: Contract Services - Project delivery | B9: 47494.427 | D9: 47494.427
A10: Employee Benefits | B10: 376.30431 | D10: 376.30431
A11: Staff Welfare - Gift & Tokens | B11: 49.5625 | D11: 49.5625
A12: Staff Welfare - Meal & Refreshment | B12: 326.74181 | D12: 326.74181
A13: General Expenses | B13: 7.435 | D13: 7.435
A14: General Expenses | B14: 7.435 | D14: 7.435
A15: Headcount Costs | B15: 73903.076 | D15: 73903.076
A16: Salaries & Wages | B16: 61906.02 | D16: 61906.02
A17: Statutory Contribution | B17: 11997.056 | D17: 11997.056
... A40: Transportation fee - National | B40: 43730.382 | D40: 43730.382
A41: General & Administrative | B41: 1.0473674e+09 | C41: 22906.007 | D41: 1.0473903e+09
A42: CN | B42: 15329.584 | D42: 15329.584
A43: Bank Charges | B43: 35.751991 | D43: 35.751991
A44: Bank Charges | B44: 35.751991 | D44: 35.751991
A45: Courier Charges | B45: 23.498153 | D45: 23.498153
A46: Courier Charges | B46: 23.498153 | D46: 23.498153
A47: Employee Benefits | B47: 623.98009 | D47: 623.98009
A48: Insurance expenses | B48: 51.50009 | D48: 51.50009
A49: Staff Welfare - Gift & Tokens | B49: 136.69 | D49: 136.69
A50: Staff Welfare - Meal & Refreshment | B50: 435.79 | D50: 435.79
A51: Headcount Costs | B51: 1968.27 | D51: 1968.27
A52: Bank Charges | B52: 4.82 | D52: 4.82
A53: Salaries & Wages | B53: 1566.2 | D53: 1566.2
... A77: Professional & Consultancy Fees | B77: 62.24 | D77: 62.24
A78: MY | B78: 576724.06 | C78: 4330.5908 | D78: 581054.65
A79: Accrual | B79: 8795.22 | D79: 8795.22
A80: Accrual | B80: 8795.22 | D80: 8795.22
A81: Accrual - Expenses of 2025 | B81: 28969.618 | D81: 28969.618
A82: Accrual - Expenses of 2025 | B82: 28969.618 | D82: 28969.618
A83: Bank | B83: -57411.38 | D83: -57411.38
A84: OCBC MY - USD | B84: -57411.38 | D84: -57411.38
A85: Bank Charges | B85: 48.737741 | D85: 48.737741
A86: Bank Charges | B86: 48.737741 | D86: 48.737741
A87: Compliance Costs | B87: 130.6939 | D87: 130.6939
A88: Stamp Duty | B88: 130.6939 | D88: 130.6939
A89: Corporate Tax Expenses | B89: 182023.95 | C89: 4074.2003 | D89: 186098.15
A90: Corporate Income Tax Expenses | B90: 182023.95 | C90: 4074.2003 | D90: 186098.15
A91: Current Asset | B91: 5582.6683 | D91: 5582.6683
A92: Security Deposit | B92: 5582.6683 | D92: 5582.6683
A93: Current Liabilities | B93: 69000 | D93: 69000
A94: Short Term Loan | B94: 69000 | D94: 69000
A95: Employee Benefits | B95: 10929.632 | D95: 10929.632
A96: Insurance expenses | B96: 8498.0064 | D96: 8498.0064
A97: Staff Welfare - Gift & Tokens | B97: 321.27512 | D97: 321.27512
A98: Staff Welfare - Meal & Refreshment | B98: 187.42014 | D98: 187.42014
A99: Staff Welfare - Medical Expenses | B99: 201.18008 | D99: 201.18008
A100: Staff Welfare - Professional Subscription | B100: 1721.75 | D100: 1721.75
A101: ERROR | B101: 2789.5338 | D101: 2789.5338
A102: Lease Liabilities | B102: 2789.5338 | D102: 2789.5338
... A115: Leasing | B115: 1480.8408 | D115: 1480.8408
A116: Network & Server | B116: 1255.6153 | C116: 108.89055 | D116: 1364.5058
A117: Network & Server | B117: 1255.6153 | C117: 108.89055 | D117: 1364.5058
A118: Non-Current Liabilities | B118: 18758.407 | D118: 18758.407
A119: Leasing | B119: 18758.407 | D119: 18758.407
A120: Office Supplies | B120: 3272.3834 | C120: 30 | D120: 3302.3834
A121: Office Supplies | B121: 3183.4029 | C121: 30 | D121: 3213.4029
A122: Printing & Stationery | B122: 88.980475 | D122: 88.980475
A123: Other Income | B123: -314.58911 | D123: -314.58911
A124: Interest Income | B124: -314.58911 | D124: -314.58911
A125: Professional & Consultancy Fees | B125: 2547.5761 | D125: 2547.5761
A126: Professional & Consultancy Fees | B126: 2547.5761 | D126: 2547.5761
A127: Rental | B127: 25289.466 | D127: 25289.466
A128: Rental of Office | B128: 25289.466 | D128: 25289.466
A129: Subscription Fee | B129: 11342.56 | D129: 11342.56
A130: Subscription Fee | B130: 11342.56 | D130: 11342.56
A131: Tax Expenses (GST/SST/VAT) | B131: 5840.7243 | D131: 5840.7243
A132: Tax Expenses (GST/SST/VAT) | B132: 5840.7243 | D132: 5840.7243
A133: Telecommunication | B133: 6.91614 | D133: 6.91614
... A140: Transportation fee - National | B140: 714.08833 | D140: 714.08833
A141: Upkeep of Office | B141: 1185.5974 | C141: 117.5 | D141: 1303.0974
A142: Cleaning Fees | B142: 1094.2055 | C142: 117.5 | D142: 1211.7055
A143: Upkeep of Offices | B143: 91.39185 | D143: 91.39185
A144: SG | B144: 1.0467754e+09 | C144: 18575.416 | D144: 1.0467939e+09
A145: Accrual | B145: 19716.608 | D145: 19716.608
A146: Accrual | B146: 19716.608 | D146: 19716.608
A147: Accrual - Expenses of 2025 | B147: 161370.83 | D147: 161370.83
A148: Accrual - Expenses of 2025 | B148: 161370.83 | D148: 161370.83
A149: Bank | B149: 3021.488 | D149: 3021.488
A150: OCBC SG - SGD | B150: 242760.77 | D150: 242760.77
A151: OCBC SG - USD | B151: -239739.28 | D151: -239739.28
A152: Bank Charges | B152: 245.81397 | D152: 245.81397
A153: Bank Charges | B153: 245.81397 | D153: 245.81397
A154: Corporate Tax Expenses | B154: 8853.79 | D154: 8853.79
A155: Corporate Income Tax Expenses | B155: 8853.79 | D155: 8853.79
A156: Courier Charges | B156: 222.47407 | D156: 222.47407
... A199: Penalty | B199: 231.03751 | D199: 231.03751
A200: Professional & Consultancy Fees | B200: 96903.388 | C200: 18483.001 | D200: 115386.39
A201: Professional & Consultancy Fees | B201: 96903.388 | C201: 18483.001 | D201: 115386.39
A202: Recruitment Related Fees | B202: 2889.2492 | D202: 2889.2492
A203: Recruitment Related Fees | B203: 2889.2492 | D203: 2889.2492
A204: Rental | B204: 221061.75 | D204: 221061.75
A205: Rental of Office | B205: 221061.75 | D205: 221061.75
A206: Repair & Maintenance | B206: 316.5984 | D206: 316.5984
...

Sheet CF
A1: Status | B1: Entity | C1: Billing Date | D1: Due Date | E1: Payment Date/ Planned Date | F1: Currency | G1: Sub Total | H1: Tax | I1: Total Amount | J1: Amount (USD) | K1: Payee | L1: Invoice Number | M1: Description | N1: Account Code | O1: Account Category | P1: Department | Q1: Group | R1: Submitter | S1: Approval | T1: Authorisation | U1: Remarks | V1: GST Claimable
A2: Paid | B2: CN | C2: 46024 | D2: 46024 | E2: 46024 | F2: CNY | G2: 25 | H2: 0 | I2: 25 | J2: 3.596375 | K2: 招商银行 - 基本户 | M2: 网上企业银行-网上企业银行服务费 | N2: Bank Charges | O2: Bank Charges | P2: Finance | Q2: General & Administrative
A3: Paid | B3: CN | C3: 46024 | D3: 46024 | E3: 46024 | F3: CNY | G3: 4.38 | H3: 0 | I3: 4.38 | J3: 0.6300849 | K3: 招商银行 - 基本户 | M3: 网银支付-跨行-异地手续费 | N3: Bank Charges | O3: Bank Charges | P3: Finance | Q3: General & Administrative
A4: Paid | B4: CN | C4: 46024 | D4: 46024 | E4: 46024 | F4: CNY | G4: 2.67 | H4: 0 | I4: 2.67 | J4: 0.38409285 | K4: 招商银行 - 基本户 | M4: 网银支付-跨行-本地普通手续费 | N4: Bank Charges | O4: Bank Charges | P4: Finance | Q4: General & Administrative
A5: Paid | B5: CN | C5: 46031 | D5: 46031 | E5: 46031 | F5: CNY | G5: 10785 | H5: 0 | I5: 10785 | J5: 1551.4762 | K5: 福建省泉州宾馆有限责任公司 | L5: 09S137BF000004738176 | M5: 会务场地费 | N5: Accommodation - National | O5: Travelling Expenses | P5: General | Q5: General & Administrative
A6: Paid | B6: CN | C6: 46037 | D6: 46037 | E6: 46037 | F6: CNY | G6: 95.5 | H6: 0 | I6: 95.5 | J6: 13.738153 | K6: 报销 | L6: 报销12月 | M6: Total Courier Charges | N6: Courier Charges | O6: Courier Charges | P6: General | Q6: General & Administrative
A7: Paid | B7: CN | C7: 46037 | D7: 46037 | E7: 46037 | F7: CNY | G7: 4875 | H7: 0 | I7: 4875 | J7: 701.29313 | K7: 报销 | L7: 报销12月 | M7: Total General Expenses | N7: General Expenses | O7: General Expenses | P7: R&D - China | Q7: Research & Development
A8: Paid | B8: CN | C8: 46037 | D8: 46037 | E8: 46037 | F8: CNY | G8: 358 | H8: 0 | I8: 358 | J8: 51.50009 | K8: 报销 | L8: 报销12月 | M8: Total Insurance expenses | N8: Insurance expenses | O8: Employee Benefits | P8: HR | Q8: General & Administrative
A9: Paid | B9: CN | C9: 46037 | D9: 46037 | E9: 46037 | F9: CNY | G9: 906.15 | H9: 0 | I9: 906.15 | J9: 130.35421 | K9: 报销 | L9: 报销12月 | M9: Total Office Supplies | N9: Office Supplies | O9: Office Supplies | P9: General | Q9: General & Administrative
A10: Paid | B10: CN | C10: 46037 | D10: 46037 | E10: 46037 | F10: CNY | G10: 29 | H10: 0 | I10: 29 | J10: 4.171795 | K10: 报销 | L10: 报销12月 | M10: Total Office Supplies | N10: Office Supplies | O10: Office Supplies | P10: General | Q10: General & Administrative
A11: Paid | B11: CN | C11: 46037 | D11: 46037 | E11: 46037 | F11: CNY | G11: 3362.13 | H11: 0 | I11: 3362.13 | J11: 483.65921 | K11: 报销 | L11: 报销12月 | M11: Total Personal Meals - International | N11: Transportation fee - International | O11: Travelling Expenses | P11: Business Operation | Q11: Sales & Marketing
A12: Paid | B12: CN | C12: 46037 | D12: 46037 | E12: 46037 | F12: CNY | G12: 400 | H12: 0 | I12: 400 | J12: 57.542 | K12: 报销 | L12: 报销12月 | M12: Total Personal Meals - National | N12: Transportation fee - National | O12: Travelling Expenses | P12: R&D - China | Q12: Research & Development
A13: Paid | B13: CN | C13: 46037 | D13: 46037 | E13: 46037 | F13: CNY | G13: 0.01 | H13: 0 | I13: 0.01 | J13: 0.00143855 | K13: 报销 | L13: 报销12月 | M13: Total Rounding | N13: Bank Charges | O13: Bank Charges | P13: Finance | Q13: General & Administrative
A14: Paid | B14: CN | C14: 46037 | D14: 46037 | E14: 46037 | F14: CNY | G14: 2073.32 | H14: 0 | I14: 2073.32 | J14: 298.25745 | K14: 报销 | L14: 报销12月 | M14: Total Subscription Fee | N14: Subscription Fee | O14: Subscription Fee | P14: Finance | Q14: General & Administrative
A15: Paid | B15: CN | C15: 46037 | D15: 46037 | E15: 46037 | F15: CNY | G15: 66.89 | H15: 0 | I15: 66.89 | J15: 9.622461 | K15: 报销 | L15: 报销12月 | M15: Total Telecommunication | N15: Telecommunication | O15: Telecommunication | P15: Business Operation | Q15: Sales & Marketing
A16: Paid | B16: CN | C16: 46037 | D16: 46037 | E16: 46037 | F16: CNY | G16: 4292.8 | H16: 0 | I16: 4292.8 | J16: 617.54074 | K16: 报销 | L16: 报销12月 | M16: Total Transportation fee - International | N16: Transportation fee - International | O16: Travelling Expenses | P16: Business Operation | Q16: Sales & Marketing
... A19: Paid | B19: CN | C19: 46037 | D19: 46037 | E19: 46037 | F19: CNY | G19: 204 | H19: 0 | I19: 204 | J19: 29.34642 | K19: 报销 | L19: 报销12月 | M19: Total Transportation fee - National | N19: Transportation fee - National | O19: Travelling Expenses | P19: R&D - China | Q19: Research & Development
A20: Paid | B20: CN | C20: 46037 | D20: 46037 | E20: 46037 | F20: CNY | G20: 671.44 | H20: 0 | I20: 671.44 | J20: 96.590001 | K20: 上海融聚全才企业服务有限公司 | M20: 代理记账服务费-2026.01 | N20: Statutory Contribution | O20: Headcount Costs | P20: Finance | Q20: General & Administrative
A21: Paid | B21: CN | C21: 46037 | D21: 46037 | E21: 46037 | F21: CNY | G21: 426.88 | H21: 0 | I21: 426.88 | J21: 61.408822 | K21: 上海卓川人力资源有限公司 | M21: 人力资源服务费-成都，上海 | N21: Professional & Consultancy Fees | O21: Professional & Consultancy Fees | P21: HR | Q21: General & Administrative
A22: Paid | B22: CN | C22: 46037 | D22: 46037 | E22: 46037 | F22: CNY | G22: 246.53 | H22: 0 | I22: 246.53 | J22: 35.464573 | K22: 上海德必飞虹文化科技发展有限公司 | M22: 办公室电费 | N22: Electricity | O22: Utilities | P22: General | Q22: General & Administrative
A23: Paid | B23: CN | C23: 46037 | D23: 46037 | E23: 46037 | F23: CNY | G23: 277 | H23: 0 | I23: 277 | J23: 39.847835 | K23: 北京易点淘网络技术有限公司 | M23: 显示器租赁费-2025年12月 | N23: Leasing | O23: Non-Current Liabilities | P23: IT | Q23: General & Administrative
A24: Paid | B24: CN | C24: 46038 | D24: 46038 | E24: 46038 | F24: CNY | G24: 5503 | H24: 0 | I24: 5503 | J24: 791.63407 | K24: 北京芯普思信息技术有限公司 | L24: 09S137C5000002056994 | M24: 货款 | N24: R&D Contract Services | O24: R&D Contract Services | P24: R&D - China | Q24: Research & Development
A25: Paid | B25: CN | C25: 46045 | D25: 46045 | E25: 46045 | F25: CNY | G25: -569458.5 | H25: 0 | I25: -569458.5 | J25: -81919.453 | K25: 格创东智（深圳）科技有限公司 | L25: INV-0001 | M25: GT 001-202511-章鱼 | N25: Sales - Services Fees | O25: Revenue | P25: R&D - China | Q25: Research & Development
A26: Paid | B26: CN | C26: 46052 | D26: 46052 | E26: 46052 | F26: CNY | G26: -381.92 | H26: 0 | I26: -381.92 | J26: -54.941102 | K26: 招商银行 - 基本户 | M26: Interest Received | N26: Interest Income | O26: Other Income | P26: Finance | Q26: General & Administrative
A27: Paid | B27: CN | C27: 46053 | D27: 46053 | E27: 46053 | F27: CNY | J27: 1920.72 | K27: CN Staff | M27: Net Pay - January 2026 | N27: Salaries & Wages | O27: Headcount Costs | P27: Business Operation | Q27: =_xlfn.XLOOKUP(P27,[1]!Table2[Department],[1]!Table2[Group],"ERROR") -> Sales & Marketing
A28: Paid | B28: CN | C28: 46053 | D28: 46053 | E28: 46053 | F28: CNY | J28: 10359.73 | K28: CN Staff | M28: Net Pay - January 2026 | N28: Salaries & Wages | O28: Headcount Costs | P28: R&D - China | Q28: =_xlfn.XLOOKUP(P28,[1]!Table2[Department],[1]!Table2[Group],"ERROR") -> Research & Development
A29: Paid | B29: CN | C29: 46055 | D29: 46055 | E29: 46055 | F29: CNY | G29: 17.69 | H29: 0 | I29: 17.69 | J29: 2.54 | K29: 招商银行 - 基本户 | M29: 网银支付-跨行-异地手续费 | N29: Bank Charges | O29: Bank Charges | P29: Finance | Q29: General & Administrative
A30: Paid | B30: CN | C30: 46055 | D30: 46055 | E30: 46055 | F30: CNY | G30: 2.67 | H30: 0 | I30: 2.67 | J30: 0.38 | K30: 招商银行 - 基本户 | M30: 网银支付-跨行-本地普通手续费 | N30: Bank Charges | O30: Bank Charges | P30: Finance | Q30: General & Administrative
A31: Paid | B31: CN | C31: 46055 | D31: 46055 | E31: 46055 | F31: CNY | G31: 25 | H31: 0 | I31: 25 | J31: 3.6 | K31: 招商银行 - 基本户 | M31: 网上企业银行-网上企业银行服务费 | N31: Bank Charges | O31: Bank Charges | P31: Finance | Q31: General & Administrative
A32: Paid | B32: CN | C32: 46066 | D32: 46066 | E32: 46066 | F32: CNY | G32: 3029.4 | H32: 0 | I32: 3029.4 | J32: 435.79 | K32: 报销 | L32: 报销1月 | M32: Total Business Meals - International | N32: Staff Welfare - Meal & Refreshment | O32: Employee Benefits | P32: HR | Q32: General & Administrative
A33: Paid | B33: CN | C33: 46066 | D33: 46066 | E33: 46066 | F33: CNY | G33: 12 | H33: 0 | I33: 12 | J33: 1.73 | K33: 报销 | L33: 报销1月 | M33: Total Courier Charges | N33: Courier Charges | O33: Courier Charges | P33: General | Q33: General & Administrative
A34: Paid | B34: CN | C34: 46066 | D34: 46066 | E34: 46066 | F34: CNY | G34: 397.48 | H34: 0 | I34: 397.48 | J34: 57.18 | K34: 报销 | L34: 报销1月 | M34: Total Office Supplies | N34: Office Supplies | O34: Office Supplies | P34: General | Q34: General & Administrative
A35: Paid | B35: CN | C35: 46066 | D35: 46066 | E35: 46066 | F35: CNY | G35: 172.5 | H35: 0 | I35: 172.5 | J35: 24.81 | K35: 报销 | L35: 报销1月 | M35: Total Personal Meals - International | N35: Personal Meals - International | O35: Travelling Expenses | P35: HR | Q35: General & Administrative
A36: Paid | B36: CN | C36: 46066 | D36: 46066 | E36: 46066 | F36: CNY | G36: 350.19 | H36: 0 | I36: 350.19 | J36: 50.38 | K36: 报销 | L36: 报销1月 | M36: Total Staff Welfare - Gift & Tokens | N36: Staff Welfare - Gift & Tokens | O36: Employee Benefits | P36: HR | Q36: General & Administrative
A37: Paid | B37: CN | C37: 46066 | D37: 46066 | E37: 46066 | F37: CNY | G37: 600 | H37: 0 | I37: 600 | J37: 86.31 | K37: 报销 | L37: 报销1月 | M37: Total Staff Welfare - Gift & Tokens | N37: Staff Welfare - Gift & Tokens | O37: Employee Benefits | P37: HR | Q37: General & Administrative
A38: Paid | B38: CN | C38: 46066 | D38: 46066 | E38: 46066 | F38: CNY | G38: 656.77 | H38: 0 | I38: 656.77 | J38: 94.48 | K38: 报销 | L38: 报销1月 | M38: Total Subscription Fee | N38: Subscription Fee | O38: Subscription Fee | P38: Finance | Q38: General & Administrative
A39: Paid | B39: CN | C39: 46066 | D39: 46066 | E39: 46066 | F39: CNY | G39: 1610.42 | H39: 0 | I39: 1610.42 | J39: 231.67 | K39: 报销 | L39: 报销1月 | M39: Total Transportation fee - National | N39: Transportation fee - National | O39: Travelling Expenses | P39: General | Q39: General & Administrative
A40: Paid | B40: CN | C40: 46066 | D40: 46066 | E40: 46066 | F40: CNY | G40: 86.7 | H40: 0 | I40: 86.7 | J40: 12.47 | K40: 报销 | L40: 报销1月 | M40: Total Transportation fee - National | N40: Transportation fee - National | O40: Travelling Expenses | P40: General | Q40: General & Administrative
A41: Paid | B41: CN | C41: 46066 | D41: 46066 | E41: 46066 | F41: CNY | G41: 528.69 | H41: 0 | I41: 528.69 | J41: 76.05 | K41: 上海德必飞虹文化科技发展有限公司 | M41: 办公室电费 | N41: Electricity | O41: Utilities | P41: General | Q41: General & Administrative
A42: Paid | B42: CN | C42: 46066 | D42: 46066 | E42: 46066 | F42: CNY | G42: 426.88 | H42: 0 | I42: 426.88 | J42: 61.41 | K42: 上海卓川人力资源有限公司 | M42: 人力资源服务费-成都，上海 | N42: Professional & Consultancy Fees | O42: Professional & Consultancy Fees | P42: HR | Q42: General & Administrative
A43: Paid | B43: CN | C43: 46066 | D43: 46066 | E43: 46066 | F43: CNY | G43: 1011.2 | H43: 0 | I43: 1011.2 | J43: 145.47 | K43: 上海融聚全才企业服务有限公司 | M43: 上海记账代理服务费-2026年2月 | N43: Professional & Consultancy Fees | O43: Professional & Consultancy Fees | P43: Finance | Q43: General & Administrative
A44: Paid | B44: CN | C44: 46066 | D44: 46066 | E44: 46066 | F44: CNY | G44: 158 | H44: 0 | I44: 158 | J44: 22.73 | K44: 深圳海域信息技术有限公司 | M44: 域名续费 | N44: Intercompany - Alpha X Technology Pte Ltd | O44: Intercompany | P44: Others | Q44: Others
A45: Paid | B45: CN | C45: 46066 | D45: 46066 | E45: 46066 | F45: CNY | G45: 277 | H45: 0 | I45: 277 | J45: 39.85 | K45: 北京易点淘网络技术有限公司 | M45: 显示器租赁费-2025年1月 | N45: Leasing | O45: Non-Current Liabilities | P45: IT | Q45: General & Administrative
A46: Paid | B46: CN | C46: 46053 | D46: 46053 | E46: 46067 | F46: CNY | J46: 985.05 | K46: CN Staff | M46: Net Pay - January 2026 | N46: Salaries & Wages | O46: Headcount Costs | P46: Business Operation | Q46: =_xlfn.XLOOKUP(P46,[1]!Table2[Department],[1]!Table2[Group],"ERROR") -> Sales & Marketing
A47: Paid | B47: CN | C47: 46053 | D47: 46053 | E47: 46067 | F47: CNY | J47: 6789.57 | K47: CN Staff | M47: Net Pay - January 2026 | N47: Salaries & Wages | O47: Headcount Costs | P47: R&D - China | Q47: =_xlfn.XLOOKUP(P47,[1]!Table2[Department],[1]!Table2[Group],"ERROR") -> Research & Development
A48: Paid | B48: CN | C48: 46081 | D48: 46081 | E48: 46080 | F48: CNY | J48: 2165.09 | K48: CN Staff | M48: Net Pay - February 2026 | N48: Salaries & Wages | O48: Headcount Costs | P48: Business Operation | Q48: =_xlfn.XLOOKUP(P48,[1]!Table2[Department],[1]!Table2[Group],"ERROR") -> Sales & Marketing
A49: Paid | B49: CN | C49: 46081 | D49: 46081 | E49: 46080 | F49: CNY | J49: 11374.61 | K49: CN Staff | M49: Net Pay - February 2026 | N49: Salaries & Wages | O49: Headcount Costs | P49: R&D - China | Q49: =_xlfn.XLOOKUP(P49,[1]!Table2[Department],[1]!Table2[Group],"ERROR") -> Research & Development
A50: Paid | B50: CN | C50: 46083 | D50: 46083 | E50: 46083 | F50: CNY | G50: 8.76 | H50: 0 | I50: 8.76 | J50: 1.28 | K50: 招商银行 - 基本户 | M50: 网银支付-跨行-异地手续费 | N50: Bank Charges | O50: Bank Charges | P50: Finance | Q50: General & Administrative
A51: Paid | B51: CN | C51: 46083 | D51: 46083 | E51: 46083 | F51: CNY | G51: 2.67 | H51: 0 | I51: 2.67 | J51: 0.39 | K51: 招商银行 - 基本户 | M51: 网银支付-跨行-本地普通手续费 | N51: Bank Charges | O51: Bank Charges | P51: Finance | Q51: General & Administrative
A52: Paid | B52: CN | C52: 46083 | D52: 46083 | E52: 46083 | F52: CNY | G52: 25 | H52: 0 | I52: 25 | J52: 3.64 | K52: 招商银行 - 基本户 | M52: 网上企业银行-网上企业银行服务费 | N52: Bank Charges | O52: Bank Charges | P52: Finance | Q52: General & Administrative
A53: Paid | B53: CN | C53: 46097 | D53: 46097 | E53: 46097 | F53: CNY | G53: 400 | H53: 0 | I53: 400 | J53: 58.32 | K53: 报销 | L53: 报销2月 | M53: Total Personal Meals - National | N53: Personal Meals - National | O53: Travelling Expenses | P53: R&D - China | Q53: Research & Development
A54: Paid | B54: CN | C54: 46097 | D54: 46097 | E54: 46097 | F54: CNY | G54: 624 | H54: 0 | I54: 624 | J54: 90.98 | K54: 报销 | L54: 报销2月 | M54: Total Professional & Consultancy Fees | N54: Professional & Consultancy Fees | O54: Professional & Consultancy Fees | P54: General | Q54: General & Administrative
A55: Paid | B55: CN | C55: 46097 | D55: 46097 | E55: 46097 | F55: CNY | G55: 624.03 | H55: 0 | I55: 624.03 | J55: 90.98 | K55: 报销 | L55: 报销2月 | M55: Total Subscription Fee | N55: Subscription Fee | O55: Subscription Fee | P55: Finance | Q55: General & Administrative
A56: Paid | B56: CN | C56: 46097 | D56: 46097 | E56: 46097 | F56: CNY | G56: 1011.2 | H56: 0 | I56: 1011.2 | J56: 147.43 | K56: 上海融聚全才企业服务有限公司 | M56: 上海记账代理服务费-2026年3月 | N56: Professional & Consultancy Fees | O56: Professional & Consultancy Fees | P56: Finance | Q56: General & Administrative
A57: Paid | B57: CN | C57: 46097 | D57: 46097 | E57: 46097 | F57: CNY | G57: 426.88 | I57: 426.88 | J57: 62.24 | K57: 上海卓川人力资源有限公司 | M57: 人力资源服务费-成都，上海 | N57: Professional & Consultancy Fees | P57: HR | Q57: General & Administrative
A58: Paid | B58: CN | C58: 46097 | D58: 46097 | E58: 46097 | F58: CNY | G58: 520.18 | H58: 0 | I58: 520.18 | J58: 75.84 | K58: 上海德必飞虹文化科技发展有限公司 | L58: 电费 | M58: 电费+空调费2026-01-01 2026-01-31 | N58: Electricity | O58: Utilities | P58: General | Q58: General & Administrative
A59: Paid | B59: CN | C59: 46097 | D59: 46097 | E59: 46097 | F59: CNY | G59: 50801 | H59: 0 | I59: 50801 | J59: 7406.63 | K59: 上海德必飞虹文化科技发展有限公司 | L59: 办公室租金 | M59: 房租2026-04-01 2026-06-30 | N59: Rental of Office | O59: Rental | P59: General | Q59: General & Administrative
A60: Paid | B60: CN | C60: 46097 | D60: 46097 | E60: 46097 | F60: CNY | G60: 277 | H60: 0 | I60: 277 | J60: 40.39 | K60: 北京易点淘网络技术有限公司 | M60: 显示器租赁费-2026年2月 | N60: Leasing | O60: Non-Current Liabilities | P60: IT | Q60: General & Administrative
A61: Paid | B61: CN | C61: 46081 | D61: 46081 | E61: 46097 | F61: CNY | J61: 1322.67 | K61: CN Staff | M61: Net Pay - February 2026 | N61: Salaries & Wages | O61: Headcount Costs | P61: Business Operation | Q61: =_xlfn.XLOOKUP(P61,[1]!Table2[Department],[1]!Table2[Group],"ERROR") -> Sales & Marketing
A62: Paid | B62: CN | C62: 46081 | D62: 46081 | E62: 46097 | F62: CNY | J62: 6244.75 | K62: CN Staff | M62: Net Pay - February 2026 | N62: Salaries & Wages | O62: Headcount Costs | P62: R&D - China | Q62: =_xlfn.XLOOKUP(P62,[1]!Table2[Department],[1]!Table2[Group],"ERROR") -> Research & Development
A63: Paid | B63: CN | C63: 46102 | D63: 46102 | E63: 46102 | F63: CNY | G63: -50.63 | H63: 0 | I63: -50.63 | J63: -7.38 | K63: 招商银行 - 基本户 | M63: Interest Received | N63: Interest Income | O63: Other Income | P63: Finance | Q63: General & Administrative
A64: Paid | B64: CN | C64: 46112 | D64: 46112 | E64: 46112 | F64: CNY | J64: 4179.73 | K64: CN Staff | M64: Net Pay - March 2026 | N64: Salaries & Wages | O64: Headcount Costs | P64: Business Operation | Q64: =_xlfn.XLOOKUP(P64,[1]!Table2[Department],[1]!Table2[Group],"ERROR") -> Sales & Marketing
A65: Paid | B65: CN | C65: 46112 | D65: 46112 | E65: 46112 | F65: CNY | J65: 22514.19 | K65: CN Staff | M65: Net Pay - March 2026 | N65: Salaries & Wages | O65: Headcount Costs | P65: R&D - China | Q65: =_xlfn.XLOOKUP(P65,[1]!Table2[Department],[1]!Table2[Group],"ERROR") -> Research & Development
A66: Paid | B66: CN | C66: 46114 | D66: 46114 | E66: 46114 | F66: CNY | G66: 2.67 | H66: 0 | I66: 2.67 | J66: 0.39 | K66: 招商银行 - 基本户 | M66: 网银支付-跨行-本地普通手续费 | N66: Bank Charges | O66: Bank Charges | P66: Finance | Q66: General & Administrative
A67: Paid | B67: CN | C67: 46114 | D67: 46114 | E67: 46114 | F67: CNY | G67: 25 | H67: 0 | I67: 25 | J67: 3.64 | K67: 招商银行 - 基本户 | M67: 网上企业银行-网上企业银行服务费 | N67: Bank Charges | O67: Bank Charges | P67: Finance | Q67: General & Administrative
A68: Paid | B68: CN | C68: 46114 | D68: 46114 | E68: 46114 | F68: CNY | G68: 4.38 | H68: 0 | I68: 4.38 | J68: 0.64 | K68: 招商银行 - 基本户 | M68: 网银支付-跨行-异地手续费 | N68: Bank Charges | O68: Bank Charges | P68: Finance | Q68: General & Administrative
A69: Paid | B69: CN | C69: 46127 | D69: 46127 | E69: 46127 | F69: CNY | G69: 1186.73 | H69: 0 | I69: 1186.73 | J69: 173.02 | K69: 上海融聚全才企业服务有限公司 | M69: 上海记账代理服务费-2026年4月 | N69: Professional & Consultancy Fees | O69: Professional & Consultancy Fees | P69: Finance | Q69: General & Administrative
A70: Paid | B70: CN | C70: 46127 | D70: 46127 | E70: 46127 | F70: CNY | G70: 320.16 | H70: 0 | I70: 320.16 | J70: 46.68 | K70: 上海卓川人力资源有限公司 | M70: 上海人事代理服务费-2026年3月 | N70: Professional & Consultancy Fees | O70: Professional & Consultancy Fees | P70: HR | Q70: General & Administrative
A71: Paid | B71: CN | C71: 46127 | D71: 46127 | E71: 46127 | F71: CNY | G71: 342.51 | H71: 0 | I71: 342.51 | J71: 49.94 | K71: 上海德必飞虹文化科技发展有限公司 | M71: 办公室电费 | N71: Electricity | O71: Utilities | P71: General | Q71: General & Administrative
A72: Paid | B72: CN | C72: 46127 | D72: 46127 | E72: 46127 | F72: CNY | G72: 277 | H72: 0 | I72: 277 | J72: 40.39 | K72: 北京易点淘网络技术有限公司 | M72: 显示器租赁费-2026年3月 | N72: Leasing | O72: Non-Current Liabilities | P72: IT | Q72: General & Administrative
A73: Paid | B73: CN | C73: 46127 | D73: 46127 | E73: 46127 | F73: CNY | G73: 55.1 | H73: 0 | I73: 55.1 | J73: 8.03 | K73: 报销 | L73: 报销3月 | M73: Total Courier Charges | N73: Courier Charges | O73: Courier Charges | P73: General | Q73: General & Administrative
A74: Paid | B74: CN | C74: 46127 | D74: 46127 | E74: 46127 | F74: CNY | G74: 293.95 | H74: 0 | I74: 293.95 | J74: 42.86 | K74: 报销 | L74: 报销3月 | M74: Total Office Supplies | N74: Office Supplies | O74: Office Supplies | P74: General | Q74: General & Administrative
A75: Paid | B75: CN | C75: 46127 | D75: 46127 | E75: 46127 | F75: CNY | G75: 6900 | H75: 0 | I75: 6900 | J75: 1006 | K75: 报销 | L75: 报销3月 | M75: Total Staff Welfare - Meal & Refreshment | N75: Staff Welfare - Meal & Refreshment | O75: Employee Benefits | P75: R&D - China | Q75: Research & Development
A76: Paid | B76: CN | C76: 46127 | D76: 46127 | E76: 46127 | F76: CNY | G76: 657.15 | H76: 0 | I76: 657.15 | J76: 95.81 | K76: 报销 | L76: 报销3月 | M76: Total Subscription Fee | N76: Subscription Fee | O76: Subscription Fee | P76: Finance | Q76: General & Administrative
A77: Paid | B77: CN | C77: 46127 | D77: 46127 | E77: 46127 | F77: CNY | G77: 45.61 | H77: 0 | I77: 45.61 | J77: 6.65 | K77: 报销 | L77: 报销3月 | M77: Total Transportation fee - National | N77: Transportation fee - National | O77: Travelling Expenses | P77: R&D - China | Q77: Research & Development
A78: Paid | B78: CN | C78: 46127 | D78: 46127 | E78: 46127 | F78: CNY | G78: 2221 | H78: 0 | I78: 2221 | J78: 323.82 | K78: 报销 | L78: 报销3月 | M78: Total Transportation fee - National | N78: Transportation fee - National | O78: Travelling Expenses | P78: R&D - China | Q78: Research & Development
A79: Paid | B79: CN | C79: 46112 | D79: 46112 | E79: 46128 | F79: CNY | J79: 106.85 | K79: CN Staff | M79: Net Pay - March 2026 | N79: Salaries & Wages | O79: Headcount Costs | P79: Business Operation | Q79: =_xlfn.XLOOKUP(P79,[1]!Table2[Department],[1]!Table2[Group],"ERROR") -> Sales & Marketing
A80: Paid | B80: CN | C80: 46112 | D80: 46112 | E80: 46128 | F80: CNY | J80: 1265.86 | K80: CN Staff | M80: Net Pay - March 2026 | N80: Salaries & Wages | O80: Headcount Costs | P80: R&D - China | Q80: =_xlfn.XLOOKUP(P80,[1]!Table2[Department],[1]!Table2[Group],"ERROR") -> Research & Development
A81: Paid | B81: CN | C81: 46136 | D81: 46136 | E81: 46136 | F81: CNY | G81: -92866.78 | H81: 0 | I81: -92866.78 | J81: -13539.7 | K81: 芯元智控（上海）科技有限公司 | M81: 汇入汇款流程解付 | N81: Internal Fund Transfer | O81: Internal Fund Transfer | P81: Others | Q81: Others
A82: Paid | B82: CN | C82: 46140 | D82: 46142 | E82: 46142 | F82: CNY | G82: 4000 | H82: 0 | I82: 4000 | J82: 583.19 | K82: 上海三礼企业发展有限公司 | L82: 服务费 | M82: 企业现代服务-法人变更 | N82: Professional & Consultancy Fees | O82: Professional & Consultancy Fees | P82: General | Q82: General & Administrative | R82: PV2604013
A83: Paid | B83: CN | C83: 46142 | D83: 46142 | E83: 46142 | F83: CNY | J83: 2075.31 | K83: CN Staff | M83: Net Pay - April 2026 | N83: Salaries & Wages | O83: Headcount Costs | P83: Business Operation | Q83: =_xlfn.XLOOKUP(P83,[1]!Table2[Department],[1]!Table2[Group],"ERROR") -> Sales & Marketing
A84: Paid | B84: CN | C84: 46142 | D84: 46142 | E84: 46142 | F84: CNY | J84: 10417.49 | K84: CN Staff | M84: Net Pay - April 2026 | N84: Salaries & Wages | O84: Headcount Costs | P84: R&D - China | Q84: =_xlfn.XLOOKUP(P84,[1]!Table2[Department],[1]!Table2[Group],"ERROR") -> Research & Development
A85: Paid | B85: CN | C85: 46144 | D85: 46144 | E85: 46144 | F85: CNY | G85: 4.38 | H85: 0 | I85: 4.38 | J85: 0.64 | K85: 招商银行 - 基本户 | M85: 网银支付-跨行-异地手续费 | N85: Bank Charges | O85: Headcount Costs | P85: Finance | Q85: =_xlfn.XLOOKUP(P85,[1]!Table2[Department],[1]!Table2[Group],"ERROR") -> General & Administrative | U85: PV2605001
A86: Paid | B86: CN | C86: 46144 | D86: 46144 | E86: 46144 | F86: CNY | G86: 3.55 | H86: 0 | I86: 3.55 | J86: 0.52 | K86: 招商银行 - 基本户 | M86: 网银支付-跨行-本地普通手续费 | N86: Bank Charges | O86: Headcount Costs | P86: Finance | Q86: =_xlfn.XLOOKUP(P86,[1]!Table2[Department],[1]!Table2[Group],"ERROR") -> General & Administrative | U86: PV2605002
A87: Paid | B87: CN | C87: 46144 | D87: 46144 | E87: 46144 | F87: CNY | G87: 25 | H87: 0 | I87: 25 | J87: 3.66 | K87: 招商银行 - 基本户 | M87: 网上企业银行-网上企业银行服务费 | N87: Bank Charges | O87: Headcount Costs | P87: Finance | Q87: =_xlfn.XLOOKUP(P87,[1]!Table2[Department],[1]!Table2[Group],"ERROR") -> General & Administrative | U87: PV2605003
A88: Paid | B88: CN | C88: 46150 | D88: 46150 | E88: 46150 | F88: CNY | G88: -46851.89 | H88: 0 | I88: -46851.89 | J88: -6860.68 | K88: 芯元智控（上海）科技有限公司 | M88: 汇入汇款流程解付 | N88: Internal Fund Transfer | O88: Internal Fund Transfer | P88: Finance | Q88: General & Administrative | U88: OR2605001
A89: Paid | B89: CN | C89: 46150 | D89: 46150 | E89: 46150 | F89: CNY | G89: -32.68 | H89: 0 | I89: -32.68 | J89: -4.79 | K89: 芯元智控（上海）科技有限公司 | M89: 汇入汇款流程解付 | N89: Internal Fund Transfer | O89: Internal Fund Transfer | P89: Finance | Q89: General & Administrative | U89: OR2605002
A90: Paid | B90: CN | C90: 46143 | D90: 46157 | E90: 46157 | F90: CNY | G90: 1067.2 | H90: 0 | I90: 1067.2 | J90: 156.27 | K90: 上海融聚全才企业服务有限公司 | M90: 上海记账代理服务费-2026年5月 | N90: Professional & Consultancy Fees | O90: Professional & Consultancy Fees | P90: Finance | Q90: General & Administrative
A91: Paid | B91: CN | C91: 46147 | D91: 46157 | E91: 46157 | F91: CNY | G91: 640.32 | H91: 0 | I91: 640.32 | J91: 93.76 | K91: 上海卓川人力资源有限公司 | M91: 人力资源服务费-成都 & 上海 | N91: Professional & Consultancy Fees | O91: Professional & Consultancy Fees | P91: HR | Q91: General & Administrative
A92: Paid | B92: CN | C92: 46143 | D92: 46157 | E92: 46157 | F92: CNY | G92: 438.75 | H92: 0 | I92: 438.75 | J92: 64.25 | K92: 上海德必飞虹文化科技发展有限公司 | M92: 办公室电费+空调费-2026.03 | N92: Electricity | O92: Utilities | P92: General | Q92: General & Administrative
A93: Paid | B93: CN | C93: 46143 | D93: 46157 | E93: 46157 | F93: CNY | G93: 277 | H93: 0 | I93: 277 | J93: 40.56 | K93: 北京易点淘网络技术有限公司 | M93: 显示器租赁费-2026年4月 | N93: Leasing | O93: Non-Current Liabilities | P93: IT | Q93: General & Administrative
A94: Paid | B94: CN | C94: 46142 | D94: 46142 | E94: 46157 | F94: CNY | J94: 1392.4 | K94: CN Staff | M94: Net Pay - April 2026 | N94: Salaries & Wages | O94: Headcount Costs | P94: Business Operation | Q94: =_xlfn.XLOOKUP(P94,[1]!Table2[Department],[1]!Table2[Group],"ERROR") -> Sales & Marketing
A95: Paid | B95: CN | C95: 46142 | D95: 46142 | E95: 46157 | F95: CNY | J95: 7100.6 | K95: CN Staff | M95: Net Pay - April 2026 | N95: Salaries & Wages | O95: Headcount Costs | P95: R&D - China | Q95: =_xlfn.XLOOKUP(P95,[1]!Table2[Department],[1]!Table2[Group],"ERROR") -> Research & Development
A96: Paid | B96: CN | C96: 46161 | D96: 46161 | E96: 46161 | F96: CNY | G96: 50 | H96: 0 | I96: 50 | J96: 7.32 | K96: 招商银行 - 基本户 | M96: 对公中间业务收入-结算帐户管理收入 | N96: Bank Charges | O96: Bank Charges | P96: Finance | Q96: General & Administrative | R96: PV2605009
A97: Paid | B97: CN | C97: 46164 | D97: 46164 | E97: 46164 | F97: CNY | G97: 50 | H97: 0 | I97: 50 | J97: 7.32 | K97: 招商银行 - 基本户 | L97: 121984970910002印鉴变更手续费 | M97: 对公中间业务收入-结算帐户管理收入 | N97: Bank Charges | O97: Bank Charges | P97: Finance | Q97: General & Administrative | R97: PV2605012
A98: Paid | B98: CN | C98: 46169 | D98: 46169 | E98: 46169 | F98: CNY | G98: -9964 | H98: 0 | I98: -9964 | J98: -1459.06 | K98: 格创东智（武汉）科技有限公司 | L98: 款项 | N98: Sales - Services Fees | O98: Revenue | P98: Sales & Pre-Sales | Q98: Sales & Marketing | R98: OR2605003
A99: Paid | B99: CN | C99: 46169 | D99: 46169 | E99: 46169 | F99: CNY | G99: -426650 | H99: 0 | I99: -426650 | J99: -62475.78 | K99: 格创东智（深圳）科技有限公司 | L99: L4000236902369款项 | N99: Sales - Services Fees | O99: Revenue | P99: Sales & Pre-Sales | Q99: Sales & Marketing | R99: OR2605004
A100: Paid | B100: CN | C100: 46173 | D100: 46173 | E100: 46173 | F100: CNY | J100: 2000 | K100: CN Staff | M100: Net Pay - May 2026 | N100: Salaries & Wages | O100: Headcount Costs | P100: Business Operation | Q100: Sales & Marketing
A101: Paid | B101: CN | C101: 46173 | D101: 46173 | E101: 46173 | F101: CNY | J101: 12000 | K101: CN Staff | M101: Net Pay - May 2026 | N101: Salaries & Wages | O101: Headcount Costs | P101: R&D - China | Q101: Research & Development
A102: Paid | B102: CN | C102: 46173 | D102: 46173 | E102: 46173 | F102: CNY | J102: 2000 | K102: CN Staff | M102: Net Pay - May 2026 | N102: Salaries & Wages | O102: Headcount Costs | P102: Business Operation | Q102: Sales & Marketing
...

Sheet Receivable
A1: Alpha X Technology Pte Ltd (Singapore) | J1: SGD | K1: 0.77012503
A2: Status | B2: Entity | C2: Invoice Date | D2: Due Date | E2: Expected Inflow | F2: Payment Received Date | G2: Currency | H2: Sub Total | I2: Tax | J2: Total Amount | K2: Amount (USD) | L2: Client Name | M2: Invoice Number | N2: Description | O2: Project Code | Q2: Account Code | R2: Account Category | S2: Department | T2: SST | U2: Remarks
A3: Paid | B3: SG | C3: 46021 | D3: 46051 | E3: 46049 | F3: 46049 | G3: USD | H3: 8978 | I3: 808.02 | J3: =H3+I3 -> 9786.02 | K3: =IF(G3="SGD", J3*$K$1, J3) -> 9786.02 | L3: Soitec Microelectronics Singapore Pte Ltd | M3: INV 2512002 | N3: Development Support Services for PR1 Visual Inspect automation - December 2025 | O3: Soitec 001-202501- PR1 ADSS | P3: SG-00017-7 | Q3: Revenue | R3: Revenue | S3: Sales & Pre-sales | T3: Yes
A4: Paid | B4: SG | C4: 46043 | D4: 46073 | E4: 46108 | F4: 46108 | G4: SGD | H4: 8866.67 | I4: 798 | J4: =H4+I4 -> 9664.67 | K4: =IF(G4="SGD", J4*$K$1, J4) -> 7443.0043 | L4: VisionPower Semiconductor Manufacturing Company Pte Ltd | M4: INV 2601001 | N4: Power BI Consultant Fees - December 2025 | O4: VSMC 001-202508-Power BI | P4: SG-00010-1 | Q4: Revenue | R4: Revenue | S4: Sales & Pre-sales | T4: Yes
A5: Paid | B5: SG | C5: 46044 | D5: 46074 | E5: 46080 | F5: 46080 | G5: SGD | H5: 5000 | I5: 0 | J5: =H5+I5 -> 5000 | K5: =IF(G5="SGD", J5*$K$1, J5) -> 3850.6252 | L5: Armstrong Industrial Corporation Limited | M5: INV 2601002 | N5: AX JIT - IOT BOX (Tianjin) | O5: Armstrong 002-202509- AX JIT (AEM) | P5: SG-00031-1 | Q5: Revenue | R5: Revenue | S5: R&D - Team D | T5: No
A6: Paid | B6: SG | C6: 46052 | D6: 46082 | E6: 46080 | F6: 46080 | G6: SGD | H6: 26900 | I6: 2421 | J6: =H6+I6 -> 29321 | K6: =IF(G6="SGD", J6*$K$1, J6) -> 22580.836 | L6: Armstrong Industrial Corporation Limited | M6: INV 2601003 | N6: Implementation fees - CN Suzhou (Part 2) | O6: Armstrong 001-202508-MES | P6: SG-00008-Suzhou-2 | Q6: Revenue | R6: Revenue | S6: R&D - Team D | T6: Yes
A7: Paid | B7: SG | C7: 46056 | D7: 46086 | E7: 46142 | F7: 46140 | G7: SGD | H7: 8866.67 | I7: 798 | J7: =H7+I7 -> 9664.67 | K7: =IF(G7="SGD", J7*$K$1, J7) -> 7443.0043 | L7: VisionPower Semiconductor Manufacturing Company Pte Ltd | M7: INV 2602001 | N7: Power BI Consultant Fees - January 2026 | O7: VSMC 001-202508-Power BI | P7: SG-00010-2 | Q7: Revenue | R7: Revenue | S7: Sales & Pre-sales | T7: Yes
A8: Paid | B8: SG | C8: 46056 | D8: 46086 | E8: 46091 | F8: 46091 | G8: USD | H8: 8978 | I8: 808.02 | J8: =H8+I8 -> 9786.02 | K8: =IF(G8="SGD", J8*$K$1, J8) -> 9786.02 | L8: Soitec Microelectronics Singapore Pte Ltd | M8: INV 2602002 | N8: Development Support Services for PR1 Visual Inspect automation - January 2026 | O8: Soitec 001-202501- PR1 ADSS | P8: SG-00017-8 | Q8: Revenue | R8: Revenue | S8: Sales & Pre-sales | T8: Yes
A9: Paid | B9: SG | C9: 46062 | D9: 46092 | E9: 46142 | F9: 46125 | G9: SGD | H9: 26900 | I9: 2421 | J9: =H9+I9 -> 29321 | K9: =IF(G9="SGD", J9*$K$1, J9) -> 22580.836 | L9: Armstrong Industrial Corporation Limited | M9: INV 2602003 | N9: Implementation fees - CN Tianjin (UAT Completion) | O9: Armstrong 001-202508-MES | P9: SG-00008-Tianjin-5 | Q9: Revenue | R9: Revenue | S9: R&D - Team D | T9: Yes
A10: Paid | B10: SG | C10: 46063 | D10: 46093 | E10: 46142 | F10: 46125 | G10: SGD | H10: 2609.69 | I10: 234.87 | J10: =H10+I10 -> 2844.56 | K10: =IF(G10="SGD", J10*$K$1, J10) -> 2190.6669 | L10: Armstrong Industrial Corporation Limited | M10: INV 2602004 | N10: Consultation Fee : AOT 17th Nov to 21st Nov 2025 | O10: Armstrong 001-202508-MES | Q10: Revenue | R10: Revenue | S10: R&D - Team D | T10: Yes
A11: Paid | B11: SG | C11: 46080 | D11: 46110 | E11: 46142 | F11: 46125 | G11: SGD | H11: 1948.24 | I11: 175.34 | J11: =H11+I11 -> 2123.58 | K11: =IF(G11="SGD", J11*$K$1, J11) -> 1635.4221 | L11: Armstrong Industrial Corporation Limited | M11: INV 2602005 | N11: Consultation Fee: AOT and ATS 4th Jan - 16th Jan 2026 | O11: Armstrong 001-202508-MES | Q11: Revenue | R11: Revenue | S11: R&D - Team D | T11: Yes
A12: Paid | B12: SG | C12: 46084 | D12: 46114 | E12: 46142 | F12: 46154 | G12: SGD | H12: 585.13 | I12: 52.66 | J12: =H12+I12 -> 637.79 | K12: =IF(G12="SGD", J12*$K$1, J12) -> 491.17804 | L12: Armstrong Industrial Corporation Limited | M12: INV 2603001 | N12: Consultation Fee : ATS Go Live 2 Feb - 6 Feb 2026. | O12: Armstrong 001-202508-MES | Q12: Revenue | R12: Revenue | S12: R&D - Team D | T12: Yes
A13: Paid | B13: SG | C13: 46084 | D13: 46114 | E13: 46142 | F13: 46149 | G13: SGD | H13: 8866.67 | I13: 798 | J13: =H13+I13 -> 9664.67 | K13: =IF(G13="SGD", J13*$K$1, J13) -> 7443.0043 | L13: VisionPower Semiconductor Manufacturing Company Pte Ltd | M13: INV 2603002 | N13: Power BI Consultant Fees - February 2026 | O13: VSMC 001-202508-Power BI | P13: SG-00010-3 | Q13: Revenue | R13: Revenue | S13: Sales & Pre-sales | T13: Yes
A14: Paid | B14: SG | C14: 46086 | D14: 46116 | E14: 46107 | F14: 46107 | G14: USD | H14: 8978 | I14: 808.02 | J14: =H14+I14 -> 9786.02 | K14: =IF(G14="SGD", J14*$K$1, J14) -> 9786.02 | L14: Soitec Microelectronics Singapore Pte Ltd | M14: INV 2603003 | N14: Development Support Services for PR1 Visual Inspect automation - February 2025 | O14: Soitec 001-202501- PR1 ADSS | P14: SG-00017-9 | Q14: Revenue | R14: Revenue | S14: Sales & Pre-sales | T14: Yes
A15: Paid | B15: SG | C15: 46087 | D15: 46117 | E15: 46090 | F15: 46090 | G15: SGD | H15: 2099 | I15: 188.91 | J15: =H15+I15 -> 2287.91 | K15: =IF(G15="SGD", J15*$K$1, J15) -> 1761.9768 | L15: Infinix Hospitality Management Pte Ltd | M15: INV 2603004 | N15: AI Scheduler Setup Fee (Phase 1) + AI Scheduler Monthly Subscription | O15: Infinix 001-202603-AX trace | P15: SG-00045-1 | Q15: Revenue | R15: Revenue | S15: R&D - Team D | T15: Yes
A16: Paid | B16: SG | C16: 46093 | D16: 46123 | E16: 46142 | F16: 46154 | G16: SGD | H16: 46400 | I16: 4176 | J16: =H16+I16 -> 50576 | K16: =IF(G16="SGD", J16*$K$1, J16) -> 38949.844 | L16: Armstrong Industrial Corporation Limited | M16: INV 2603005 | N16: Implementation Fees – CN Changchun (Kick Off) | O16: Armstrong 001-202508-MES | P16: SG-00008-Changchun-7 | Q16: Revenue | R16: Revenue | S16: R&D - Team D | T16: Yes
A17: Paid | B17: SG | C17: 46094 | D17: 46124 | E17: 46107 | F17: 46107 | G17: USD | H17: 1000 | I17: 90 | J17: =H17+I17 -> 1090 | K17: =IF(G17="SGD", J17*$K$1, J17) -> 1090 | L17: Gtrontec Technology Pte Ltd | M17: INV 2603006 | N17: AX Trace Digital Marketing Solution 19 Feb 2026 – 18 Mar 2026 (1/6) | O17: GT 002-202602-AX Trace Digital Mktg Solution | P17: SG-00041-1 | R17: Revenue | S17: R&D - Team D | T17: Yes
A18: Paid | B18: SG | C18: 46111 | D18: 46141 | E18: 46173 | F18: 46139 | G18: USD | H18: 8978 | I18: 808.02 | J18: =H18+I18 -> 9786.02 | K18: =IF(G18="SGD", J18*$K$1, J18) -> 9786.02 | L18: Soitec Microelectronics Singapore Pte Ltd | M18: INV 2603007 | N18: Development Support Services for PR1 Visual Inspect automation - March 2026 | O18: Soitec 001-202501- PR1 ADSS | P18: SG-00017-10 | Q18: Revenue | R18: Revenue | S18: Sales & Pre-sales | T18: Yes
A19: Paid | B19: SG | C19: 46113 | D19: 46143 | E19: 46173 | F19: 46170 | G19: SGD | H19: 8866.67 | I19: 798 | J19: =H19+I19 -> 9664.67 | K19: =IF(G19="SGD", J19*$K$1, J19) -> 7443.0043 | L19: VisionPower Semiconductor Manufacturing Company Pte Ltd | M19: INV 2604001 | N19: Power BI Consultant Fees - March 2026 | O19: VSMC 001-202508-Power BI (1st)
A20: Paid | B20: SG | C20: 46113 | D20: 46143 | E20: 46173 | F20: 46170 | G20: SGD | H20: 8866.67 | I20: 798 | J20: =H20+I20 -> 9664.67 | K20: =IF(G20="SGD", J20*$K$1, J20) -> 7443.0043 | L20: VisionPower Semiconductor Manufacturing Company Pte Ltd | M20: INV 2604002 | N20: Power BI Consultant Fees - March 2026 | O20: VSMC 004-202603-Power BI (2nd)
A21: Paid | B21: SG | C21: 46113 | D21: 46143 | E21: 46173 | F21: 46188 | G21: SGD | H21: 16000 | I21: 1440 | J21: =H21+I21 -> 17440 | K21: =IF(G21="SGD", J21*$K$1, J21) -> 13430.981 | L21: Armstrong Industrial Corporation Limited | M21: INV 2604003 | N21: Project milestone: Phase 1 - 40% upon kick off AX Trace Smart Factory Data Platform | O21: Armstrong 004-202603-AX Trace Smart Factory Data Platform
A22: Declined | B22: SG | C22: 46119 | D22: 46127 | E22: 46142 | G22: SGD | H22: 76345 | I22: 6871.05 | J22: =H22+I22 -> 83216.05 | K22: =IF(G22="SGD", J22*$K$1, J22) -> 64086.763 | L22: Gtrontec Technology Pte Ltd | M22: INV 2604004 | N22: OHT related IP License Fee for 2 years | O22: Nil
A23: Due | B23: SG | C23: 46121 | D23: 46151 | E23: 46234 | G23: SGD | H23: 10800 | I23: 972 | J23: =H23+I23 -> 11772 | K23: =IF(G23="SGD", J23*$K$1, J23) -> 9065.9119 | L23: Armstrong Industrial Corporation Limited | M23: INV 2604005 | N23: Implementation Fees - MY JB (Kick Off) | O23: Armstrong 001-202508-MES
A24: Due | B24: SG | C24: 46121 | D24: 46151 | E24: 46234 | G24: SGD | H24: 46400 | I24: 4176 | J24: =H24+I24 -> 50576 | K24: =IF(G24="SGD", J24*$K$1, J24) -> 38949.844 | L24: Armstrong Industrial Corporation Limited | M24: INV 2604006 | N24: Implementation Fees - MY JB (Kick Off) | O24: Armstrong 001-202508-MES
A25: Due | B25: SG | C25: 46121 | D25: 46151 | E25: 46234 | G25: SGD | H25: 40000 | I25: 3600 | J25: =H25+I25 -> 43600 | K25: =IF(G25="SGD", J25*$K$1, J25) -> 33577.451 | L25: Armstrong Industrial Corporation Limited | M25: INV 2604007 | N25: Implementation Fees - CN Wuhan | O25: Armstrong 001-202508-MES
A26: Paid | B26: SG | C26: 46122 | D26: 46152 | E26: 46173 | F26: 46153 | G26: SGD | H26: 99 | I26: 8.91 | J26: =H26+I26 -> 107.91 | K26: =IF(G26="SGD", J26*$K$1, J26) -> 83.104192 | L26: Infinix Hospitality Management Pte Ltd | M26: INV 2604008 | N26: Ax Trace AI Scheduler Monthly Subscription - April 2026 (2/6) | O26: Infinix 001-202603-AX trace | P26: SG-00045-2 | Q26: Revenue | R26: Revenue | S26: R&D - Team D | T26: Yes
A27: Paid | B27: SG | C27: 46126 | D27: 46156 | E27: 46173 | F27: 46155 | G27: USD | H27: 1000 | I27: 90 | J27: =H27+I27 -> 1090 | K27: =IF(G27="SGD", J27*$K$1, J27) -> 1090 | L27: Gtrontec Technology Pte Ltd | M27: INV 2604009 | N27: Ax Trace Digital Marketing Solution a) Website content audit & revamp plan b) New LinkedIn page setup blog framework & ongoing blog / content creation (weekly) Period : 19 Mar 2026 – 18 Apr 2026 | O27: GT 002-202602-AX Trace Digital Mktg Solution | P27: AXQ00028 | Q27: Revenue | R27: Revenue | T27: Yes
A28: Paid | B28: SG | C28: 46133 | D28: 46163 | E28: 46173 | F28: 46199 | G28: SGD | H28: 8866.67 | I28: 798.0003 | J28: =H28+I28 -> 9664.6703 | K28: =IF(G28="SGD", J28*$K$1, J28) -> 7443.0045 | L28: VisionPower Semiconductor Manufacturing Company Pte Ltd | M28: INV 2604011 | N28: POWER BI CONSULTANTS AS QUO : AXQ00015 for the month of April 2026 | O28: VSMC 001-202508-Power BI (1st) | P28: PO 3325001371 | Q28: Revenue | R28: Revenue | T28: Yes
A29: Paid | B29: SG | C29: 46133 | D29: 46163 | E29: 46173 | F29: 46170 | G29: SGD | H29: 8866.67 | I29: 798.0003 | J29: =H29+I29 -> 9664.6703 | K29: =IF(G29="SGD", J29*$K$1, J29) -> 7443.0045 | L29: VisionPower Semiconductor Manufacturing Company Pte Ltd | M29: INV 2604012 | N29: 2nd POWER BI CONSULTANTS AS QUO : AXQ00015 for the month of April 2026 | O29: VSMC 004-202603-Power BI (2nd) | P29: PO 3325001593 | Q29: Revenue | R29: Revenue | T29: Yes
A30: Pending | B30: SG | C30: 46133 | D30: 46194 | E30: 46265 | G30: USD | H30: 56000 | I30: 5040 | J30: =H30+I30 -> 61040 | K30: =IF(G30="SGD", J30*$K$1, J30) -> 61040 | L30: Advanced Micro Foundry Pte Ltd | M30: INV 2604010 | N30: Implementation of Equipment Automation for 4 equipment types | O30: AMF 003-202506-EAS | P30: PO002149 Ver. 1.2 | Q30: Revenue | R30: Revenue | T30: Yes
A31: Due | B31: SG | C31: 46140 | D31: 46170 | E31: 46234 | G31: SGD | H31: 2705.65 | I31: 243.5085 | J31: =H31+I31 -> 2949.1585 | K31: =IF(G31="SGD", J31*$K$1, J31) -> 2271.2208 | L31: Armstrong Industrial Corporation Limited | M31: INV 2604013 | N31: Consultation Fee: Tianjin (AOT) Go-Live 4 Mar, and Changchun (AOC) kick off 9 Mar - 13 Mar 2026 | O31: Armstrong 001-202508-MES | P31: PO26M00038 | Q31: Revenue | R31: Revenue | T31: Yes
A32: Paid | B32: SG | C32: 46141 | D32: 46142 | E32: 46172 | F32: 46150 | G32: USD | H32: 59000 | I32: 0 | J32: =H32+I32 -> 59000 | K32: =IF(G32="SGD", J32*$K$1, J32) -> 59000 | L32: Shanghai Wilson Optimus Technology Co., Ltd., | M32: INV 2604014 | N32: Taiwan IP License | O32: Wilson 001-202604-IP Licenseout | Q32: Revenue | R32: Revenue
A33: Paid | B33: SG | C33: 46147 | D33: 46177 | E33: 46203 | F33: 46168 | G33: USD | H33: 8978 | I33: 808.02 | J33: =H33+I33 -> 9786.02 | K33: =IF(G33="SGD", J33*$K$1, J33) -> 9786.02 | L33: Soitec Microelectronics Singapore Pte Ltd | M33: INV 2605001 | N33: Development Support Services for PR1 Visual Inspect automation - April 2026 | O33: Soitec 001-202501- PR1 ADSS | P33: SG-00017-11 | Q33: Revenue | R33: Revenue
A34: Paid | B34: SG | C34: 46150 | D34: 46180 | E34: 46203 | F34: 46176 | G34: CNY | H34: 1575966.3 | I34: 0 | J34: =H34+I34 -> 1575966.3 | K34: 232853.75 | L34: Getech (ShenZhen) Co., Ltd | M34: INV 2605002 | N34: Technical Service Fee - 50% kick off payment | O34: GT 001-202604-Resources Service | Q34: Revenue | R34: Revenue
A35: Pending | B35: SG | C35: 46157 | D35: 46187 | E35: 46234 | G35: SGD | H35: 18800 | I35: 1692 | J35: =H35+I35 -> 20492 | K35: =IF(G35="SGD", J35*$K$1, J35) -> 15781.402 | L35: Armstrong Industrial Corporation Limited | M35: INV 2605003 | N35: Implementation Fees – CHN ChangChun (UAT) | O35: Armstrong 001-202508-MES | P35: PO25M00126 | Q35: Revenue | R35: Revenue | T35: Yes
A36: Pending | B36: SG | C36: 46157 | D36: 46187 | E36: 46234 | G36: SGD | H36: 8100 | I36: 729 | J36: =H36+I36 -> 8829 | K36: =IF(G36="SGD", J36*$K$1, J36) -> 6799.4339 | L36: Armstrong Industrial Corporation Limited | M36: INV 2605004 | N36: Implementation Fees – MY JB (UAT) | O36: Armstrong 001-202508-MES | P36: PO26M00034 | Q36: Revenue | R36: Revenue | T36: Yes
A37: Pending | B37: SG | C37: 46157 | D37: 46187 | E37: 46234 | G37: SGD | H37: 18800 | I37: 1692 | J37: =H37+I37 -> 20492 | K37: =IF(G37="SGD", J37*$K$1, J37) -> 15781.402 | L37: Armstrong Industrial Corporation Limited | M37: INV 2605005 | N37: Implementation Fees – MY JB (UAT) | O37: Armstrong 001-202508-MES | P37: PO25M00126 | Q37: Revenue | R37: Revenue | T37: Yes
A38: Forecast | B38: SG | C38: 46157 | D38: 46218 | E38: 46233 | G38: USD | J38: =H38+I38 -> 0 | K38: =IF(G38="SGD", J38*$K$1, J38) -> 0 | L38: Advanced Micro Foundry Pte Ltd | M38: N/A | N38: 20% payment (every 4 tools) | O38: AMF 003-202506-EAS | P38: SG-00005-2
A39: Forecast | B39: SG | C39: 46157 | D39: 46218 | E39: 46233 | G39: USD | J39: =H39+I39 -> 0 | K39: =IF(G39="SGD", J39*$K$1, J39) -> 0 | L39: Advanced Micro Foundry Pte Ltd | M39: N/A | N39: 20% payment (1 tool only) | O39: AMF 003-202506-EAS | P39: SG-00005-3
A40: Paid | B40: SG | C40: 46164 | D40: 46194 | E40: 46203 | F40: 46202 | G40: SGD | H40: 2599 | I40: 233.91 | J40: =H40+I40 -> 2832.91 | K40: =IF(G40="SGD", J40*$K$1, J40) -> 2181.6949 | L40: Infinix Hospitality Management Pte Ltd | M40: INV 2605006 | N40: Ax Trace AI Scheduler Monthly Subscription - May 2026 (3/6) | O40: Infinix 001-202603-AX trace | P40: SG-00045-3 | Q40: Revenue | R40: Revenue | S40: R&D - Team D | T40: Yes
A41: Paid | B41: SG | C41: 46164 | D41: 46194 | E41: 46203 | F41: 46199 | G41: SGD | H41: 8866.67 | I41: 798 | J41: =H41+I41 -> 9664.67 | K41: =IF(G41="SGD", J41*$K$1, J41) -> 7443.0043 | L41: VisionPower Semiconductor Manufacturing Company Pte Ltd | M41: INV 2605008 | N41: Power BI Consultant Fees - May 2026 | O41: VSMC 001-202508-Power BI (1st) | P41: SG-00010-6 | Q41: Revenue | R41: Revenue | S41: Sales & Pre-sales | T41: Yes
A42: Paid | B42: SG | C42: 46164 | D42: 46194 | E42: 46203 | F42: 46199 | G42: SGD | H42: 8866.67 | I42: 798 | J42: =H42+I42 -> 9664.67 | K42: =IF(G42="SGD", J42*$K$1, J42) -> 7443.0043 | L42: VisionPower Semiconductor Manufacturing Company Pte Ltd | M42: INV 2605009 | N42: Power BI Consultant Fees - May 2026 | O42: VSMC 004-202603-Power BI (2nd) | P42: SG-00010-6 | Q42: Revenue | R42: Revenue | S42: Sales & Pre-sales | T42: Yes
A43: Pending | B43: SG | C43: 46164 | D43: 46194 | E43: 46234 | G43: USD | H43: 1000 | I43: 90 | J43: =H43+I43 -> 1090 | K43: =IF(G43="SGD", J43*$K$1, J43) -> 1090 | L43: Gtrontec Technology Pte Ltd | M43: INV 2605007 | N43: AX Trace Digital Marketing Solution 19 Apr 2026 – 18 May 2026 (2/6) | O43: GT 002-202602-AX Trace Digital Mktg Solution | P43: SG-00041-2 | R43: Revenue | S43: R&D - Team D | T43: Yes
A44: Pending | B44: SG | C44: 46170 | D44: 46200 | E44: 46234 | G44: USD | H44: 8978 | I44: 808.02 | J44: =H44+I44 -> 9786.02 | K44: =IF(G44="SGD", J44*$K$1, J44) -> 9786.02 | L44: Soitec Microelectronics Singapore Pte Ltd | M44: INV 2605010 | N44: Development Support Services for PR1 Visual Inspect automation - May 2026 | O44: Soitec 001-202501- PR1 ADSS | P44: SG-00017-12 | Q44: Revenue | R44: Revenue | S44: Sales & Pre-sales | T44: Yes
A45: Pending | B45: SG | C45: 46176 | D45: 46206 | E45: 46234 | G45: SGD | H45: 569.41 | I45: 51.25 | J45: =H45+I45 -> 620.66 | K45: =IF(G45="SGD", J45*$K$1, J45) -> 477.9858 | L45: Armstrong Industrial Corporation Limited | M45: INV 2606001 | N45: Consultation Fee: AOC UAT 13th to 17th April 2026 | O45: Armstrong 001-202508-MES | P45: PO26M00053 | Q45: Revenue | R45: Revenue | T45: Yes
A46: Pending | B46: SG | C46: 46176 | D46: 46206 | E46: 46234 | G46: SGD | H46: 2093.66 | I46: 188.43 | J46: =H46+I46 -> 2282.09 | K46: =IF(G46="SGD", J46*$K$1, J46) -> 1757.4946 | L46: Armstrong Industrial Corporation Limited | M46: INV 2606002 | N46: Consultation Fee: AEM Kick Off 7th to 10th Apr 2026 | O46: Armstrong 001-202508-MES | P46: PO26M00054 | Q46: Revenue | R46: Revenue | T46: Yes
A47: Pending | B47: SG | C47: 46191 | D47: 46221 | E47: 46234 | G47: SGD | H47: 8866.67 | I47: 798 | J47: 9664.67 | K47: 7443.0043 | L47: VisionPower Semiconductor Manufacturing Company Pte Ltd | M47: INV 2606003 | N47: Power BI Consultant Fees - June 2026 | O47: VSMC 001-202508-Power BI (1st) | P47: SG-00010-7 | Q47: Revenue | R47: Revenue | S47: Sales & Pre-sales | T47: Yes
A48: Pending | B48: SG | C48: 46195 | D48: 46225 | E48: 46234 | G48: SGD | H48: 2364.12 | I48: 212.77 | J48: =H48+I48 -> 2576.89 | K48: =IF(G48="SGD", J48*$K$1, J48) -> 1984.5275 | L48: Armstrong Industrial Corporation Limited | M48: INV 2606004 | N48: Consultation fee for AEM MES UAT between 10th to 15th May 2026 | O48: Armstrong 001-202508-MES | Q48: Revenue | R48: Revenue | S48: Sales & Pre-sales | T48: Yes
A49: Pending | B49: SG | C49: 46195 | D49: 46225 | E49: 46234 | G49: SGD | H49: 1700.91 | I49: 153.08 | J49: =H49+I49 -> 1853.99 | K49: =IF(G49="SGD", J49*$K$1, J49) -> 1427.8041 | L49: Armstrong Industrial Corporation Limited | M49: INV 2606005 | N49: Consultation fee for AOC MES Go-Live between 19th May to 27th May 2026 | O49: Armstrong 001-202508-MES | Q49: Revenue | R49: Revenue | S49: Sales & Pre-sales | T49: Yes
A50: Paid | B50: SG | C50: 46195 | D50: 46225 | E50: 46234 | F50: 46195 | G50: SGD | H50: 99 | I50: 8.91 | J50: =H50+I50 -> 107.91 | K50: 7444.0043 | L50: Infinix Hospitality Management Pte Ltd | M50: INV 2606006 | N50: Ax Trace AI Scheduler Monthly Subscription - June 2026 (4/6) | O50: Infinix 001-202603-AX trace | P50: SG-00045-4 | Q50: Revenue | R50: Revenue | S50: Sales & Pre-sales | T50: Yes
A51: Pending | B51: SG | C51: 46197 | D51: 46227 | E51: 46234 | G51: SGD | H51: 15000 | I51: 1350 | J51: =H51+I51 -> 16350 | K51: =IF(G51="SGD", J51*$K$1, J51) -> 12591.544 | L51: Armstrong Industrial Corporation Limited | M51: INV 2606007 | N51: MES Consulting service for Wuhan (AOW) 29 June 2026 - 28 July 2026 | O51: Armstrong 011-202606-UAT and GO Live support for Wuhan (AOW) | P51: SG-00065-1 | Q51: Revenue | R51: Revenue | S51: Sales & Pre-sales | T51: Yes
A52: Pending | B52: SG | C52: 46198 | D52: 46228 | E52: 46234 | G52: USD | H52: 1000 | I52: 90 | J52: 1090 | K52: 1090 | L52: Gtrontec Technology Pte Ltd | M52: INV 2606008 | N52: AX Trace Digital Marketing Solution 19 May 2026 – 18 Jun 2026 (3/6) | O52: GT 002-202602-AX Trace Digital Mktg Solution | P52: SG-00041-3 | Q52: Revenue | R52: Revenue | S52: Sales & Pre-sales | T52: Yes
A53: Forecast | B53: SG | C53: 46204 | D53: 46235 | E53: 46265 | G53: SGD | H53: 18900 | I53: 1701 | J53: =H53+I53 -> 20601 | K53: =IF(G53="SGD", J53*$K$1, J53) -> 15865.346 | L53: Armstrong Industrial Corporation Limited | M53: N/A | N53: (Suzhou)Go Live 18% Payment | O53: Armstrong 001-202508-MES | P53: SG-00008-Suzhou-3
A54: Forecast | B54: SG | C54: 46235 | D54: 46266 | E54: 46295 | G54: SGD | H54: 18900 | I54: 1701 | J54: =H54+I54 -> 20601 | K54: =IF(G54="SGD", J54*$K$1, J54) -> 15865.346 | L54: Armstrong Industrial Corporation Limited | M54: N/A | N54: (Tianjin)Go Live 18% Payment | O54: Armstrong 001-202508-MES | P54: SG-00008-Tianjin-6
A55: Forecast | B55: SG | C55: 46235 | D55: 46266 | E55: 46295 | G55: SGD | H55: 14318.08 | I55: 1288.6272 | J55: =H55+I55 -> 15606.707 | K55: =IF(G55="SGD", J55*$K$1, J55) -> 12019.116 | L55: Armstrong Industrial Corporation Limited | M55: N/A | N55: (Changchun) UAT 17% Payment | O55: Armstrong 001-202508-MES | P55: SG-00008-Changchun-8
A56: Forecast | B56: SG | C56: 46266 | D56: 46296 | E56: 46325 | G56: SGD | H56: 8225.28 | I56: 740.2752 | J56: =H56+I56 -> 8965.5552 | K56: =IF(G56="SGD", J56*$K$1, J56) -> 6904.5985 | L56: Armstrong Industrial Corporation Limited | M56: N/A | N56: (Changchun) Go Live 16% Payment | O56: Armstrong 001-202508-MES | P56: SG-00008-Changchun-9
A57: Forecast | B57: SG | C57: 46296 | D57: 46327 | E57: 46356 | G57: SGD | H57: 46400 | I57: 4176 | J57: =H57+I57 -> 50576 | K57: =IF(G57="SGD", J57*$K$1, J57) -> 38949.844 | L57: Armstrong Industrial Corporation Limited | M57: N/A | N57: (Thailand) Kick Off 61% Payment | O57: Armstrong 001-202508-MES | P57: SG-00008-Thailand-13
A58: Forecast | B58: SG | C58: 46332 | D58: 46362 | E58: 46387 | G58: SGD | H58: 18800 | I58: 1692 | J58: =H58+I58 -> 20492 | K58: =IF(G58="SGD", J58*$K$1, J58) -> 15781.402 | L58: Armstrong Industrial Corporation Limited | M58: N/A | N58: (JB) UAT 25% Payment | O58: Armstrong 001-202508-MES | P58: SG-00008-JB-11
A59: Forecast | B59: SG | C59: 46332 | D59: 46362 | E59: 46387 | G59: SGD | H59: 10800 | I59: 972 | J59: =H59+I59 -> 11772 | K59: =IF(G59="SGD", J59*$K$1, J59) -> 9065.9119 | L59: Armstrong Industrial Corporation Limited | M59: N/A | N59: (JB) Go Live 14% Payment | O59: Armstrong 001-202508-MES | P59: SG-00008-JB-12
A60: Forecast | B60: SG | C60: 46341 | D60: 46371 | E60: 46387 | G60: SGD | H60: 18800 | I60: 1692 | J60: =H60+I60 -> 20492 | K60: =IF(G60="SGD", J60*$K$1, J60) -> 15781.402 | L60: Armstrong Industrial Corporation Limited | M60: N/A | N60: (Thailand) UAT 25% Payment | O60: Armstrong 001-202508-MES | P60: SG-00008-Thailand-14
A61: Forecast | B61: SG | C61: 46371 | D61: 46402 | E61: 46418 | G61: SGD | H61: 10800 | I61: 972 | J61: =H61+I61 -> 11772 | K61: =IF(G61="SGD", J61*$K$1, J61) -> 9065.9119 | L61: Armstrong Industrial Corporation Limited | M61: N/A | N61: (Thailand) Go Live 14% Payment | O61: Armstrong 001-202508-MES | P61: SG-00008-Thailand-15
A62: Forecast | B62: SG | C62: 46402 | D62: 46433 | E62: 46446 | G62: SGD | H62: 40000 | I62: 3600 | J62: =H62+I62 -> 43600 | K62: =IF(G62="SGD", J62*$K$1, J62) -> 33577.451 | L62: Armstrong Industrial Corporation Limited | M62: N/A | N62: (Shen Yang) Go Live 100% | O62: Armstrong 001-202508-MES | P62: SG-00008-Shen Yang-17
A63: Forecast | B63: SG | E63: 46234 | G63: SGD | H63: 99 | I63: 8.91 | J63: =H63+I63 -> 107.91 | K63: =IF(G63="SGD", J63*$K$1, J63) -> 83.104192 | L63: Infinix Hospitality Management Pte Ltd | M63: N/A | N63: Ax Trace AI Scheduler Monthly Subscription - June 2026 (4/6) | O63: Infinix 001-202603-AX trace | P63: SG-00045-4
A64: Forecast | B64: SG | E64: 46265 | G64: SGD | H64: 99 | I64: 8.91 | J64: =H64+I64 -> 107.91 | K64: =IF(G64="SGD", J64*$K$1, J64) -> 83.104192 | L64: Infinix Hospitality Management Pte Ltd | M64: N/A | N64: Ax Trace AI Scheduler Monthly Subscription - July 2026 (5/6) | O64: Infinix 001-202603-AX trace | P64: SG-00045-5
A65: Forecast | B65: SG | E65: 46295 | G65: SGD | H65: 99 | I65: 8.91 | J65: =H65+I65 -> 107.91 | K65: =IF(G65="SGD", J65*$K$1, J65) -> 83.104192 | L65: Infinix Hospitality Management Pte Ltd | M65: N/A | N65: Ax Trace AI Scheduler Monthly Subscription - August 2026 (6/6) | O65: Infinix 001-202603-AX trace | P65: SG-00045-6
A66: Forecast | B66: SG | E66: 46265 | G66: SGD | H66: 8866.67 | I66: 798 | J66: =H66+I66 -> 9664.67 | K66: =IF(G66="SGD", J66*$K$1, J66) -> 7443.0043 | L66: VisionPower Semiconductor Manufacturing Company Pte Ltd | M66: N/A | N66: Power BI Consultant Fees - June 2026 | O66: VSMC 001-202508-Power BI (1st) | P66: SG-00010-7
A67: Forecast | B67: SG | E67: 46295 | G67: SGD | H67: 8866.67 | I67: 798 | J67: =H67+I67 -> 9664.67 | K67: =IF(G67="SGD", J67*$K$1, J67) -> 7443.0043 | L67: VisionPower Semiconductor Manufacturing Company Pte Ltd | M67: N/A | N67: Power BI Consultant Fees - July 2026 | O67: VSMC 001-202508-Power BI (1st) | P67: SG-00010-8
A68: Forecast | B68: SG | E68: 46326 | G68: SGD | H68: 8866.67 | I68: 798 | J68: =H68+I68 -> 9664.67 | K68: =IF(G68="SGD", J68*$K$1, J68) -> 7443.0043 | L68: VisionPower Semiconductor Manufacturing Company Pte Ltd | M68: N/A | N68: Power BI Consultant Fees - August 2026 | O68: VSMC 001-202508-Power BI (1st) | P68: SG-00010-9
A69: Forecast | B69: SG | E69: 46356 | G69: SGD | H69: 8866.67 | I69: 798 | J69: =H69+I69 -> 9664.67 | K69: =IF(G69="SGD", J69*$K$1, J69) -> 7443.0043 | L69: VisionPower Semiconductor Manufacturing Company Pte Ltd | M69: N/A | N69: Power BI Consultant Fees - September 2026 | O69: VSMC 001-202508-Power BI (1st) | P69: SG-00010-10
A70: Forecast | B70: SG | E70: 46387 | G70: SGD | H70: 8866.67 | I70: 798 | J70: =H70+I70 -> 9664.67 | K70: =IF(G70="SGD", J70*$K$1, J70) -> 7443.0043 | L70: VisionPower Semiconductor Manufacturing Company Pte Ltd | M70: N/A | N70: Power BI Consultant Fees - October 2026 | O70: VSMC 001-202508-Power BI (1st) | P70: SG-00010-11
A71: Forecast | B71: SG | E71: 46418 | G71: SGD | H71: 8866.67 | I71: 798 | J71: =H71+I71 -> 9664.67 | K71: =IF(G71="SGD", J71*$K$1, J71) -> 7443.0043 | L71: VisionPower Semiconductor Manufacturing Company Pte Ltd | M71: N/A | N71: Power BI Consultant Fees - November 2026 | O71: VSMC 001-202508-Power BI (1st) | P71: SG-00010-12
A72: Forecast | B72: SG | E72: 46265 | G72: SGD | H72: 8866.67 | I72: 798 | J72: =H72+I72 -> 9664.67 | K72: =IF(G72="SGD", J72*$K$1, J72) -> 7443.0043 | L72: VisionPower Semiconductor Manufacturing Company Pte Ltd | M72: N/A | N72: Power BI Consultant Fees - June 2026 | O72: VSMC 004-202603-Power BI (2nd) | P72: SG-00010-7
A73: Forecast | B73: SG | E73: 46295 | G73: SGD | H73: 8866.67 | I73: 798 | J73: =H73+I73 -> 9664.67 | K73: =IF(G73="SGD", J73*$K$1, J73) -> 7443.0043 | L73: VisionPower Semiconductor Manufacturing Company Pte Ltd | M73: N/A | N73: Power BI Consultant Fees - July 2026 | O73: VSMC 004-202603-Power BI (2nd) | P73: SG-00010-8
A74: Forecast | B74: SG | E74: 46326 | G74: SGD | H74: 8866.67 | I74: 798 | J74: =H74+I74 -> 9664.67 | K74: =IF(G74="SGD", J74*$K$1, J74) -> 7443.0043 | L74: VisionPower Semiconductor Manufacturing Company Pte Ltd | M74: N/A | N74: Power BI Consultant Fees - August 2026 | O74: VSMC 004-202603-Power BI (2nd) | P74: SG-00010-9
... A87: Forecast | B87: SG | E87: 46418 | G87: USD | H87: 8978 | I87: 808.02 | J87: =H87+I87 -> 9786.02 | K87: =IF(G87="SGD", J87*$K$1, J87) -> 9786.02 | L87: Soitec Microelectronics Singapore Pte Ltd | M87: N/A | N87: Development Support Services for PR1 Visual Inspect automation - November 2026 | O87: Soitec 003-202605-6 months Application Development Services | P87: SG-00051-6
J88: =H88+I88 -> 0 | K88: =IF(G88="SGD", J88*$K$1, J88) -> 0
J89: =H89+I89 -> 0 | K89: =IF(G89="SGD", J89*$K$1, J89) -> 0
J90: =H90+I90 -> 0 | K90: =IF(G90="SGD", J90*$K$1, J90) -> 0
J91: =H91+I91 -> 0 | K91: =IF(G91="SGD", J91*$K$1, J91) -> 0
J92: =H92+I92 -> 0 | K92: =IF(G92="SGD", J92*$K$1, J92) -> 0
H94: =SUM(H3:H93) -> 2582927.2 | I94: =SUM(I3:I93) -> 84866.472 | J94: =SUM(J3:J93) -> 2667793.7 | K94: =SUM(K3:K93) -> 1137651.7
A97: Alpha X Innovation Sdn Bhd (Malaysia) | J97: MYR | K97: 0.24197899
A98: Status | B98: Entity | C98: Invoice Date | D98: Due Date | E98: Expected Inflow | F98: Payment Received Date | G98: Currency | H98: Sub Total | I98: Tax | J98: Total Amount | K98: Amount (USD) | L98: Client Name | M98: Invoice Number | N98: Description | O98: Project Code | Q98: Account Code | R98: Account Category | S98: Department | T98: SST | U98: Remarks
A99: Paid | B99: MY | C99: 46000 | D99: 46090 | E99: 46142 | F99: 46135 | G99: MYR | H99: 197700 | I99: 15816 | J99: =H99+I99 -> 213516 | K99: =IF(G99="MYR", J99*$K$97, J99) -> 51666.386 | L99: S.E.H (Shah Alam) Sdn Bhd | M99: INV 2512001 | N99: 99-SPOT-PRO3743L / PROJECT-90504 | O99: SEH 001-202505-napson | P99: MY-00006-1 | Q99: Revenue | R99: Revenue | S99: Sales & Pre-sales | T99: Yes
A100: Paid | B100: MY | C100: 46008 | D100: 46038 | E100: 46081 | F100: 46066 | G100: MYR | H100: 1876020 | I100: 7200 | J100: =H100+I100 -> 1883220 | K100: =IF(G100="MYR", J100*$K$97, J100) -> 455699.68 | L100: Dai-Ichi Jitsugyo (Malaysia) Sdn Bhd | M100: INV 2512002 | N100: Phase 2 - 60% payment milestone upon Hardware Delivery, Installation of License and MES Integration Test | O100: MIMOS 001-202504-MES, EAS | P100: MY-00004-2 | Q100: Revenue | R100: Revenue | S100: Sales & Pre-sales | T100: Yes
A101: Paid | B101: MY | C101: 46057 | D101: 46087 | E101: 46112 | F101: 46094 | G101: MYR | H101: 32000 | I101: 0 | J101: =H101+I101 -> 32000 | K101: =IF(G101="MYR", J101*$K$97, J101) -> 7743.3277 | L101: Dai-Ichi Jitsugyo (Malaysia) Sdn Bhd | M101: INV 2502001 | N101: Phase 1 - Project Implementation (Balance payment milestone) | O101: Denso 001-202509-Simulation | P101: MY-00032-2 | Q101: Revenue | R101: Revenue | S101: Sales & Pre-sales | T101: No
A102: Pending | B102: MY | C102: 46147 | D102: 46238 | E102: 46265 | G102: MYR | H102: 26000 | I102: 2080 | J102: =H102+I102 -> 28080 | K102: =IF(G102="MYR", J102*$K$97, J102) -> 6794.7701 | L102: S.E.H (Shah Alam) Sdn Bhd | M102: INV 2605001 | N102: Software compatibility alignment, interface configuration & data handling, Deployment readiness & support | O102: SEH 006-202603-stocker change request | P102: PO No.: SAPO024440
A103: Pending | B103: MY | C103: 46147 | D103: 46238 | E103: 46265 | G103: MYR | H103: 102990 | I103: 8239.2 | J103: =H103+I103 -> 111229.2 | K103: =IF(G103="MYR", J103*$K$97, J103) -> 26915.13 | L103: S.E.H (Shah Alam) Sdn Bhd | M103: INV 2605002 | N103: Software & Licenses, Services & Support | O103: SEH 003-202411-Stocker | P103: PO No.: SAPO018003
A104: Paid | B104: MY | C104: 46149 | D104: 46179 | E104: 46173 | F104: 46171 | G104: MYR | H104: 4000 | I104: 0 | J104: =H104+I104 -> 4000 | K104: =IF(G104="MYR", J104*$K$97, J104) -> 967.91597 | L104: Dai-Ichi Jitsugyo (Malaysia) Sdn Bhd | M104: INV 2605003 | N104: Enhancement for Burn In and I/R Simulation Project | O104: Denso 002-202604-Simulation Enhancement | P104: PO No.: HP/26/04/512 as at 07/04/2026
A105: Pending | B105: MY | C105: 46164 | D105: 46254 | E105: 46264 | G105: MYR | H105: 241470 | I105: 19317.6 | J105: =H105+I105 -> 260787.6 | K105: =IF(G105="MYR", J105*$K$97, J105) -> 63105.121 | L105: S.E.H (Shah Alam) Sdn Bhd | M105: INV 2605004 | N105: IG#11 & IG#12 Automation Implementation | O105: SEH 002-202506-IG Project | P105: PO No.: SAPO023182 | Q105: Revenue | R105: Revenue | T105: Yes
A106: Pending | B106: MY | C106: 46171 | D106: 46201 | E106: 46203 | G106: MYR | H106: 313870 | I106: 720 | J106: =H106+I106 -> 314590 | K106: =IF(G106="MYR", J106*$K$97, J106) -> 76124.171 | L106: Dai-Ichi Jitsugyo (Malaysia) Sdn Bhd | M106: INV 2605005 | N106: Phase 3 - 10% payment milestone upon Hardware Delivery, Installation of License and MES Integration Test | O106: MIMOS 001-202504-MES, EAS | P106: MY-00004-3 | Q106: Revenue | R106: Revenue | S106: Sales & Pre-sales | T106: Yes
J107: =H107+I107 -> 0 | K107: =IF(G107="MYR", J107*$K$97, J107) -> 0
J108: =H108+I108 -> 0 | K108: =IF(G108="MYR", J108*$K$97, J108) -> 0
J109: =H109+I109 -> 0 | K109: =IF(G109="MYR", J109*$K$97, J109) -> 0
J110: =H110+I110 -> 0 | K110: =IF(G110="MYR", J110*$K$97, J110) -> 0
J111: =H111+I111 -> 0 | K111: =IF(G111="MYR", J111*$K$97, J111) -> 0
J112: =H112+I112 -> 0 | K112: =IF(G112="MYR", J112*$K$97, J112) -> 0
I114: =SUM(I99:I113) -> 53372.8 | J114: =SUM(J99:J113) -> 2847422.8 | K114: =SUM(K99:K113) -> 689016.5
A117: 芯元智控（上海）科技有限公司 | J117: CNY | K117: 0.14086589
A118: Status | B118: Entity | C118: Invoice Date | D118: Due Date | E118: Expected Inflow | F118: Payment Received Date | G118: Currency | H118: Sub Total | I118: Tax | J118: Total Amount | K118: Amount (USD) | L118: Client Name | M118: Invoice Number | N118: Description | O118: Project Code | Q118: Account Code | R118: Account Category | S118: Department | U118: Remarks
...

Sheet PO Value
A3: Row Labels
A4: 2026
A5: Qtr1
A6: Feb
A7: CN
A8: SG
A9: Mar
A10: CN
A11: MY
A12: SG
A13: Qtr2
A14: Apr
... A25: Grand Total

Sheet PO
A1: PIC | B1: Entity | C1: Project Name | D1: PO Date | E1: PO Date -F | F1: Amount USD
A2: Kare Guan | B2: CN | C2: 晋华POC - AX insights & Smart Assistant | D2: 46077 | E2: 46077 | F2: 12443
A3: Kare Guan | B3: CN | C3: JCET 长电绍兴-POC | D3: 46094 | E3: 46094 | F3: 1360
A4: Kare Guan | B4: CN | C4: Wilson 001-202604-IP Licenseout | D4: 46142 | E4: 46142 | F4: 59000
A5: Kare Guan | B5: CN | C5: GT - AI product resources service | D5: 46142 | E5: 46142 | F5: 231185
A6: Alex Chan | B6: MY | C6: SEH - Stocker ( Change request) | D6: 46090 | E6: 46090 | F6: 6624
A7: Lucca Lam | B7: MY | C7: DJK (Denso)- Simulation Enhancement | D7: 46119 | E7: 46119 | F7: 1022
A8: Danny Kwok | B8: SG | C8: Armstrong-Smart Factory Data Platform | D8: 46108 | E8: 46108 | F8: 30464
A9: Mei Inn Koh | B9: SG | C9: GT - Marketing Resouces | D9: 46062 | E9: 46062 | F9: 6000
A10: Chris Chan | B10: SG | C10: Infinix Hospitality Management - AX Trace | D10: 46084 | E10: 46084 | F10: 4355
A11: Danny Kwok | B11: SG | C11: Armstrong - MES for JB AEM with integrations | D11: 46108 | E11: 46108 | F11: 21020
A12: Teresa Tham | B12: SG | C12: Soitec - 6 months Application Development Support Services | D12: 46150 | E12: 46150 | F12: 53868
A13: Mei Inn Koh | B13: SG | C13: Armstrong - Maintenance Contract | D13: 46136 | E13: 46136 | F13: 20399
... A20: Danny Kwok | B20: SG | C20: Armstrong UAT support for Wuhan | D20: 46185 | E20: 46185 | F20: 11650

Sheet Setting
A1: Cost Category | B1: Account Code | D1: Department | E1: Group | H1: MY Employee | I1: Department
A2: Revenue | B2: Sales - Software | D2: Management | E2: General & Administrative | H2: CHAN YIN HOCK | I2: Sales & Pre-Sales
A3: Revenue | B3: Sales - Hardware | D3: Sales & Pre-Sales | E3: Sales & Marketing | H3: LIM SHU WEN | I3: DSC
A4: Revenue | B4: Sales - Services Fees | D4: DSC | E4: DSC | H4: YEAP JIA SHUNG | I4: Sales & Pre-Sales
A5: Other Income | B5: Interest Income | D5: Marketing | E5: Sales & Marketing | H5: WAN NURUL AMIRA BINTI WAN MOHAMAD | I5: Sales & Pre-Sales
A6: Other Income | B6: Management Fees | D6: Business Operation | E6: Sales & Marketing | H6: CHEY PUI YAN | I6: HR
A7: Other Income | B7: Disbursement Income | D7: HR | E7: General & Administrative | H7: LOW LEE CHWIN | I7: Finance
A8: Other Income | B8: Grant Received | D8: Finance | E8: General & Administrative | H8: GOH AI PING | I8: DSC
A9: Direct Costs | B9: Carriage Inwards | D9: R&D - Team W | E9: Research & Development | H9: CHEW KWANG HWEE | I9: DSC
A10: Direct Costs | B10: Contract Services - Project delivery | D10: R&D - Team D | E10: Research & Development | H10: NG JIA YONG | I10: DSC
A11: Direct Costs | B11: Direct Labour | D11: R&D - China | E11: Research & Development | H11: LIN CHAORAN | I11: Business Operation
A12: Direct Costs | B12: Direct Materials | D12: R&D - DSC | E12: Research & Development | H12: YU CHEAN FEI | I12: DSC
... A15: Direct Costs | B15: Import/Custom Fees | D15: IT | E15: General & Administrative | H15: BEH YEAN SHIN | I15: Finance
A16: Bank | B16: OCBC SG - SGD | D16: Others | E16: Others
A17: Bank | B17: OCBC SG - USD
A18: Bank | B18: OCBC SG - CNH
A19: Bank | B19: East West Bank | D19: Pending | E19: SG
A20: Bank | B20: OCBC MY - MYR | D20: Paid | E20: MY
A21: Bank | B21: OCBC MY - USD | D21: New | E21: CN
A22: Bank Charges | B22: Bank Charges | D22: Forecast | E22: TW
A23: Compliance Costs | B23: Audit Fees | D23: Declined | E23: US
A24: Compliance Costs | B24: Stamp Duty | D24: Due | E24: IND
A25: Corporate Tax Expenses | B25: Corporate Income Tax Expenses
A26: Courier Charges | B26: Courier Charges
A27: Depreciation | B27: Depreciation
A28: Director Fees | B28: Director Fees
A29: Employee Benefits | B29: Insurance expenses
A30: Employee Benefits | B30: Staff Welfare - Gift & Tokens
A31: Employee Benefits | B31: Staff Welfare - Meal & Refreshment
A32: Employee Benefits | B32: Staff Welfare - Medical Expenses
A33: Employee Benefits | B33: Staff Welfare - Professional Subscription
A34: Employee Benefits | B34: Staff Welfare - Recreation, Training & Events
A35: Expense | B35: Expenses - unidentified
A36: Foreign Exchange | B36: Foreign Exchange
... A93: Utilities | B93: Water

Sheet FOREX
A1: Month | B1: Currency | C1: Rate | E1: Month | F1: Currency | G1: Rate | I1: Month | J1: Currency | K1: Rate
A2: 46053 | B2: SGD | C2: 0.787321 | E2: 46053 | F2: MYR | G2: 0.253768 | I2: 46053 | J2: CNY | K2: 0.143855
A3: 46081 | B3: SGD | C3: 0.790614 | E3: 46081 | F3: MYR | G3: 0.256912 | I3: 46081 | J3: CNY | K3: 0.145797
A4: 46112 | B4: SGD | C4: 0.775146 | E4: 46112 | F4: MYR | G4: 0.247005 | I4: 46112 | J4: CNY | K4: 0.144959
A5: 46142 | B5: SGD | C5: 0.78487574 | E5: 46142 | F5: MYR | G5: 0.25188297 | I5: 46142 | J5: CNY | K5: 0.14643332
A6: 46173 | B6: SGD | C6: 0.7832 | E6: 46173 | F6: MYR | G6: 0.252015 | I6: 46173 | J6: CNY | K6: 0.147753
A7: 46203 | B7: SGD | C7: =C6 -> 0.7832 | E7: 46203 | F7: MYR | G7: =G6 -> 0.252015 | I7: 46203 | J7: CNY | K7: =K6 -> 0.147753
A8: 46234 | B8: SGD | C8: =C7 -> 0.7832 | E8: 46234 | F8: MYR | G8: =G7 -> 0.252015 | I8: 46234 | J8: CNY | K8: =K7 -> 0.147753
A9: 46265 | B9: SGD | C9: =C8 -> 0.7832 | E9: 46265 | F9: MYR | G9: =G8 -> 0.252015 | I9: 46265 | J9: CNY | K9: =K8 -> 0.147753
A10: 46295 | B10: SGD | C10: =C9 -> 0.7832 | E10: 46295 | F10: MYR | G10: =G9 -> 0.252015 | I10: 46295 | J10: CNY | K10: =K9 -> 0.147753
A11: 46326 | B11: SGD | C11: =C10 -> 0.7832 | E11: 46326 | F11: MYR | G11: =G10 -> 0.252015 | I11: 46326 | J11: CNY | K11: =K10 -> 0.147753
A12: 46356 | B12: SGD | C12: =C11 -> 0.7832 | E12: 46356 | F12: MYR | G12: =G11 -> 0.252015 | I12: 46356 | J12: CNY | K12: =K11 -> 0.147753
A13: 46387 | B13: SGD | C13: =C12 -> 0.7832 | E13: 46387 | F13: MYR | G13: =G12 -> 0.252015 | I13: 46387 | J13: CNY | K13: =K12 -> 0.147753

Sheet AXT - USD
A2: Alpha X Technology Pte Ltd (Singapore)
J3: USD
A4: Status | B4: Entity | C4: Billing Date | D4: Due Date | E4: Payment Date | F4: Currency | G4: Sub Total | H4: Tax | J4: Total Amount | K4: Payee | L4: Invoice Number | M4: Description | N4: Account Code | O4: Account Category | P4: Department | Q4: Group | R4: Submitter | S4: Approval | T4: Authorisation | U4: Remarks | V4: GST Claimable
A5: Opening b/f | E5: 46023 | F5: USD | J5: 57825.83
A6: Paid | B6: SG | C6: 46037 | D6: 46037 | E6: 46037 | F6: USD | G6: -2000 | H6: 0 | J6: =SUM(G6:H6) -> -2000 | K6: OCBC SGD | L6: Internal Transfer 2026/01-01 | M6: Internal Transfer from SGD to USD | N6: Internal Fund Transfer | O6: =_xlfn.XLOOKUP(N6,costcategory[Account Code],costcategory[Cost Category],"ERROR") -> Internal Fund Transfer | P6: Others | Q6: =_xlfn.XLOOKUP(P6,Table2[Department],Table2[Group],"ERROR") -> Others | R6: Cathfrine Low | S6: Leon Chan | T6: Cathfrine Low | V6: No
A7: Paid | B7: SG | C7: 46037 | D7: 46037 | E7: 46037 | F7: USD | G7: 58000 | H7: 0 | J7: =SUM(G7:H7) -> 58000 | K7: Alpha X Innovation Sdn Bhd | L7: Intercompany Loan MY/2026/01 | M7: Intercompany Loan to MY entity | N7: Intercompany - Alpha X Innovation Sdn Bhd | O7: =_xlfn.XLOOKUP(N7,costcategory[Account Code],costcategory[Cost Category],"ERROR") -> Intercompany | P7: Finance | Q7: =_xlfn.XLOOKUP(P7,Table2[Department],Table2[Group],"ERROR") -> General & Administrative | R7: Cathfrine Low | S7: Leon Chan | T7: Cathfrine Low | V7: No
A8: Paid | B8: SG | C8: 46037 | D8: 46037 | E8: 46037 | F8: USD | G8: 23.49 | H8: 0 | J8: =SUM(G8:H8) -> 23.49 | K8: OCBC USD | L8: Bank charges 15/01/2026 | M8: Bank charges - Intercompany Loan to MY entity | N8: Bank Charges | O8: =_xlfn.XLOOKUP(N8,costcategory[Account Code],costcategory[Cost Category],"ERROR") -> Bank Charges | P8: Finance | Q8: =_xlfn.XLOOKUP(P8,Table2[Department],Table2[Group],"ERROR") -> General & Administrative | R8: Direct | S8: - | T8: - | V8: No
A9: Paid | B9: SG | C9: 46038 | D9: 46038 | E9: 46038 | F9: USD | G9: -300000 | H9: 0 | J9: =SUM(G9:H9) -> -300000 | K9: Eastwest Bank | L9: Internal Transfer 2026/01-03 | M9: Internal Transfer from Eastwest bank to OCBC USD | N9: Internal Fund Transfer | O9: =_xlfn.XLOOKUP(N9,costcategory[Account Code],costcategory[Cost Category],"ERROR") -> Internal Fund Transfer | P9: Others | Q9: =_xlfn.XLOOKUP(P9,Table2[Department],Table2[Group],"ERROR") -> Others | R9: Cathfrine Low | S9: Leon Chan | T9: Cathfrine Low | V9: No
A10: Paid | B10: SG | C10: 46038 | D10: 46038 | E10: 46038 | F10: USD | G10: 30 | H10: 0 | J10: =SUM(G10:H10) -> 30 | K10: OCBC USD | L10: Bank charges 16/01/2026 | M10: Bank charges - Internal Transfer from Eastwest bank to OCBC USD | N10: Bank Charges | O10: =_xlfn.XLOOKUP(N10,costcategory[Account Code],costcategory[Cost Category],"ERROR") -> Bank Charges | P10: Finance | Q10: =_xlfn.XLOOKUP(P10,Table2[Department],Table2[Group],"ERROR") -> General & Administrative | R10: Direct | S10: - | T10: - | V10: No
A11: Paid | B11: SG | C11: 46038 | D11: 46038 | E11: 46038 | F11: USD | G11: 7.7 | H11: 0 | J11: =SUM(G11:H11) -> 7.7 | K11: OCBC USD | L11: Bank charges 16/01/2026 | M11: Bank charges - Internal Transfer from Eastwest bank to OCBC USD | N11: Bank Charges | O11: =_xlfn.XLOOKUP(N11,costcategory[Account Code],costcategory[Cost Category],"ERROR") -> Bank Charges | P11: Finance | Q11: =_xlfn.XLOOKUP(P11,Table2[Department],Table2[Group],"ERROR") -> General & Administrative | R11: Direct | S11: - | T11: - | V11: No
A12: Paid | B12: SG | C12: 46045 | D12: 46045 | E12: 46045 | F12: USD | G12: 235849.06 | H12: 0 | J12: =SUM(G12:H12) -> 235849.06 | K12: OCBC SGD | L12: Internal Transfer 2026/01-02 | M12: Internal Transfer from USD to SGD | N12: Internal Fund Transfer | O12: =_xlfn.XLOOKUP(N12,costcategory[Account Code],costcategory[Cost Category],"ERROR") -> Internal Fund Transfer | P12: Others | Q12: =_xlfn.XLOOKUP(P12,Table2[Department],Table2[Group],"ERROR") -> Others | R12: Cathfrine | S12: Leon Chan | T12: Cathfrine Low | V12: No
A13: Paid | B13: SG | C13: 46048 | D13: 46048 | E13: 46048 | F13: USD | G13: 63000 | H13: 0 | J13: =SUM(G13:H13) -> 63000 | K13: Alpha X Innovation Sdn Bhd | L13: Intercompany Loan MY/2026/01 | M13: Intercompany Loan to MY entity | N13: Intercompany - Alpha X Innovation Sdn Bhd | O13: =_xlfn.XLOOKUP(N13,costcategory[Account Code],costcategory[Cost Category],"ERROR") -> Intercompany | P13: Finance | Q13: =_xlfn.XLOOKUP(P13,Table2[Department],Table2[Group],"ERROR") -> General & Administrative | R13: Cathfrine Low | S13: Leon Chan | T13: Cathfrine Low | V13: No
A14: Paid | B14: SG | C14: 46048 | D14: 46048 | E14: 46048 | F14: USD | G14: 23.84 | H14: 0 | J14: =SUM(G14:H14) -> 23.84 | K14: OCBC USD | L14: Bank charges 26/01/2026 | M14: Bank charges - Intercompany Loan to MY entity | N14: Bank Charges | O14: =_xlfn.XLOOKUP(N14,costcategory[Account Code],costcategory[Cost Category],"ERROR") -> Bank Charges | P14: Finance | Q14: =_xlfn.XLOOKUP(P14,Table2[Department],Table2[Group],"ERROR") -> General & Administrative | R14: Direct | S14: - | T14: - | V14: No
A15: Paid | B15: SG | C15: 46021 | D15: 46051 | E15: 46049 | F15: USD | G15: -8978 | H15: -808.02 | J15: =SUM(G15:H15) -> -9786.02 | K15: Soitec Microelectronics Singapore Pte Ltd | L15: INV 2512002 | M15: Development Support Services for PR1 Visual Inspect automation - December 2025 | N15: Sales - Services Fees | O15: =_xlfn.XLOOKUP(N15,costcategory[Account Code],costcategory[Cost Category],"ERROR") -> Revenue | P15: Sales & Pre-Sales | Q15: =_xlfn.XLOOKUP(P15,Table2[Department],Table2[Group],"ERROR") -> Sales & Marketing | R15: - | S15: - | T15: - | V15: Yes
A16: Paid | B16: SG | C16: 46049 | D16: 46049 | E16: 46049 | F16: USD | G16: 7.81 | H16: 0 | J16: =SUM(G16:H16) -> 7.81 | K16: OCBC USD | L16: Bank charges 27/01/2026 | M16: Bank charges - INV 2512002 | N16: Bank Charges | O16: =_xlfn.XLOOKUP(N16,costcategory[Account Code],costcategory[Cost Category],"ERROR") -> Bank Charges | P16: Finance | Q16: =_xlfn.XLOOKUP(P16,Table2[Department],Table2[Group],"ERROR") -> General & Administrative | R16: Direct | S16: - | T16: - | V16: No
F17: USD | J17: =SUM(J6:J16) -> 45155.88
A18: Closing c/f | E18: 46053 | F18: USD | J18: =J5-J17 -> 12669.95
A20: Status | B20: Entity | C20: Billing Date | D20: Due Date | E20: Payment Date | F20: Currency | G20: Sub Total | H20: Tax | J20: Total Amount | K20: Payee | L20: Invoice Number | M20: Description | N20: Account Code | O20: Account Category | P20: Department | Q20: Group | R20: Submitter | S20: Approval | T20: Authorisation | U20: Remarks | V20: GST Claimable
A21: Opening b/f | E21: 46082 | F21: USD | J21: =J18 -> 12669.95
A22: Paid | B22: SG | C22: 46083 | D22: 46083 | E22: 46083 | F22: USD | G22: 12000 | H22: 0 | J22: =SUM(G22:H22) -> 12000 | K22: OCBC SGD | L22: Internal Transfer | M22: Internal Transfer from USD to SGD | N22: Internal Fund Transfer | O22: =_xlfn.XLOOKUP(N22,costcategory[Account Code],costcategory[Cost Category],"ERROR") -> Internal Fund Transfer | P22: Others | Q22: =_xlfn.XLOOKUP(P22,Table2[Department],Table2[Group],"ERROR") -> Others | V22: No
A23: Paid | B23: SG | C23: 46083 | D23: 46083 | E23: 46083 | F23: USD | G23: -349970 | H23: 0 | J23: =SUM(G23:H23) -> -349970 | K23: Eastwest Bank | L23: Internal Transfer | M23: Internal Transfer from Eastwest bank to OCBC USD | N23: Internal Fund Transfer | O23: =_xlfn.XLOOKUP(N23,costcategory[Account Code],costcategory[Cost Category],"ERROR") -> Internal Fund Transfer | P23: Others | Q23: =_xlfn.XLOOKUP(P23,Table2[Department],Table2[Group],"ERROR") -> Others | V23: No
A24: Paid | B24: SG | C24: 46083 | D24: 46083 | E24: 46083 | F24: USD | G24: 7.83 | H24: 0 | J24: =SUM(G24:H24) -> 7.83 | K24: OCBC USD | L24: Bank charges | M24: Bank charges - Intercompany Loan to SG entity | N24: Bank Charges | O24: =_xlfn.XLOOKUP(N24,costcategory[Account Code],costcategory[Cost Category],"ERROR") -> Bank Charges | P24: Finance | Q24: =_xlfn.XLOOKUP(P24,Table2[Department],Table2[Group],"ERROR") -> General & Administrative | V24: No
A25: Paid | B25: SG | C25: 46083 | D25: 46083 | E25: 46083 | F25: USD | G25: 200000 | H25: 0 | J25: =SUM(G25:H25) -> 200000 | K25: OCBC SGD | L25: Internal Transfer | M25: Internal Transfer from USD to SGD | N25: Internal Fund Transfer | O25: =_xlfn.XLOOKUP(N25,costcategory[Account Code],costcategory[Cost Category],"ERROR") -> Internal Fund Transfer | P25: Others | Q25: =_xlfn.XLOOKUP(P25,Table2[Department],Table2[Group],"ERROR") -> Others | V25: No
A26: Paid | B26: SG | C26: 46091 | D26: 46091 | E26: 46091 | F26: USD | G26: -9786.02 | H26: 0 | J26: =SUM(G26:H26) -> -9786.02 | K26: Soitec Microelectronics Singapore Pte Ltd | L26: INV 2602002 | M26: Application Development Support Services for PR1 Visual Inspect automation for the month of January 2026 | N26: Sales - Services Fees | O26: =_xlfn.XLOOKUP(N26,costcategory[Account Code],costcategory[Cost Category],"ERROR") -> Revenue | P26: Sales & Pre-Sales | Q26: =_xlfn.XLOOKUP(P26,Table2[Department],Table2[Group],"ERROR") -> Sales & Marketing | V26: Yes
A27: Paid | B27: SG | C27: 46091 | D27: 46091 | E27: 46091 | F27: USD | G27: 7.8 | H27: 0 | J27: =SUM(G27:H27) -> 7.8 | K27: OCBC USD | L27: Bank charges | M27: Bank charges - Intercompany Loan to SG entity | N27: Bank Charges | O27: =_xlfn.XLOOKUP(N27,costcategory[Account Code],costcategory[Cost Category],"ERROR") -> Bank Charges | P27: Finance | Q27: =_xlfn.XLOOKUP(P27,Table2[Department],Table2[Group],"ERROR") -> General & Administrative | V27: No
A28: Paid | B28: SG | C28: 46097 | D28: 46097 | E28: 46097 | F28: USD | G28: 4855.23 | H28: 0 | J28: =SUM(G28:H28) -> 4855.23 | K28: Chen Hong | M28: Payment on behalf of Taiwan - Consultation Fees | N28: Intercompany - Alpha X (Taiwan) Technology Co Ltd | O28: =_xlfn.XLOOKUP(N28,costcategory[Account Code],costcategory[Cost Category],"ERROR") -> Intercompany | P28: Others | Q28: =_xlfn.XLOOKUP(P28,Table2[Department],Table2[Group],"ERROR") -> Others | V28: No
A29: Paid | B29: SG | C29: 46097 | D29: 46097 | E29: 46097 | F29: USD | G29: 23.42 | H29: 0 | J29: =SUM(G29:H29) -> 23.42 | K29: OCBC USD | L29: Bank charges | M29: Bank charges | N29: Bank Charges | O29: =_xlfn.XLOOKUP(N29,costcategory[Account Code],costcategory[Cost Category],"ERROR") -> Bank Charges | P29: Finance | Q29: =_xlfn.XLOOKUP(P29,Table2[Department],Table2[Group],"ERROR") -> General & Administrative | V29: No
A30: Paid | B30: SG | C30: 46105 | D30: 46105 | E30: 46105 | F30: USD | G30: 100000 | H30: 0 | J30: =SUM(G30:H30) -> 100000 | K30: OCBC SGD | L30: Internal Transfer | M30: Internal Transfer from USD to SGD | N30: Internal Fund Transfer | O30: =_xlfn.XLOOKUP(N30,costcategory[Account Code],costcategory[Cost Category],"ERROR") -> Internal Fund Transfer | P30: Others | Q30: =_xlfn.XLOOKUP(P30,Table2[Department],Table2[Group],"ERROR") -> Others | V30: No
A31: Paid | B31: SG | C31: 46105 | D31: 46105 | E31: 46105 | F31: USD | G31: -1090 | H31: 0 | J31: =SUM(G31:H31) -> -1090 | K31: GTRONTEC TECHNOLOGY PTE LTD | L31: INV 2603006 | M31: AX Trace Digital Marketing Solution | N31: Sales - Services Fees | O31: =_xlfn.XLOOKUP(N31,costcategory[Account Code],costcategory[Cost Category],"ERROR") -> Revenue | P31: Marketing | Q31: =_xlfn.XLOOKUP(P31,Table2[Department],Table2[Group],"ERROR") -> Sales & Marketing | V31: Yes
A32: Paid | B32: SG | C32: 46107 | D32: 46107 | E32: 46107 | F32: USD | G32: -9786.02 | H32: 0 | J32: =SUM(G32:H32) -> -9786.02 | K32: Soitec Microelectronics Singapore Pte Ltd | L32: INV 2603003 | M32: Application Development Support Services for PR1 Visual Inspect automation for the month of February 2026 | N32: Sales - Services Fees | O32: =_xlfn.XLOOKUP(N32,costcategory[Account Code],costcategory[Cost Category],"ERROR") -> Revenue | P32: Sales & Pre-Sales | Q32: =_xlfn.XLOOKUP(P32,Table2[Department],Table2[Group],"ERROR") -> Sales & Marketing | V32: Yes
A33: Paid | B33: SG | C33: 46107 | D33: 46107 | E33: 46107 | F33: USD | G33: 7.74 | H33: 0 | J33: =SUM(G33:H33) -> 7.74 | K33: OCBC USD | L33: Bank charges | M33: Bank charges | N33: Bank Charges | O33: =_xlfn.XLOOKUP(N33,costcategory[Account Code],costcategory[Cost Category],"ERROR") -> Bank Charges | P33: Finance | Q33: =_xlfn.XLOOKUP(P33,Table2[Department],Table2[Group],"ERROR") -> General & Administrative | V33: No
F34: USD | J34: =SUM(J22:J33) -> -53730.02
A35: Closing c/f | E35: 46112 | F35: USD | J35: =J21-J34 -> 66399.97
A37: Status | B37: Entity | C37: Billing Date | D37: Due Date | E37: Payment Date | F37: Currency | G37: Sub Total | H37: Tax | J37: Total Amount | K37: Payee | L37: Invoice Number | M37: Description | N37: Account Code | O37: Account Category | P37: Department | Q37: Group | R37: Submitter | S37: Approval | T37: Authorisation | U37: Remarks | V37: GST Claimable
A38: Opening b/f | E38: 46113 | F38: USD | J38: 66399.97
A39: Paid | B39: SG | C39: 46113 | D39: 46113 | E39: 46113 | F39: USD | G39: 4637 | H39: 0 | J39: =SUM(G39:H39) -> 4637 | K39: Chance Accountancy | L39: 412, 448, 422 | M39: 40 min Tax Consultation on 11/5/2025, Renew 2026 Statement of Information, Annual Agent of Service 2026, Prepare 2025 C Corp Income Tax Return with 5471 Filings | N39: Intercompany - Alpha X (US) Technology Pte Ltd | O39: =_xlfn.XLOOKUP(N39,costcategory[Account Code],costcategory[Cost Category],"ERROR") -> Intercompany | P39: Finance | Q39: =_xlfn.XLOOKUP(P39,Table2[Department],Table2[Group],"ERROR") -> General & Administrative | V39: No
A40: Paid | B40: SG | C40: 46113 | D40: 46113 | E40: 46113 | F40: USD | G40: 23.56 | H40: 0 | J40: =SUM(G40:H40) -> 23.56 | K40: OCBC USD | L40: Bank charges | M40: Bank charges | N40: Bank Charges | O40: =_xlfn.XLOOKUP(N40,costcategory[Account Code],costcategory[Cost Category],"ERROR") -> Bank Charges | P40: Finance | Q40: =_xlfn.XLOOKUP(P40,Table2[Department],Table2[Group],"ERROR") -> General & Administrative | V40: No
A41: Paid | B41: SG | C41: 46125 | D41: 46125 | E41: 46125 | F41: USD | G41: -47.33 | H41: 0 | J41: =SUM(G41:H41) -> -47.33 | K41: OCBC USD | L41: Bank charges | M41: Bank charges | N41: Bank Charges | O41: =_xlfn.XLOOKUP(N41,costcategory[Account Code],costcategory[Cost Category],"ERROR") -> Bank Charges | P41: Finance | Q41: =_xlfn.XLOOKUP(P41,Table2[Department],Table2[Group],"ERROR") -> General & Administrative | V41: No
A42: Paid | B42: SG | C42: 46128 | D42: 46128 | E42: 46128 | F42: USD | G42: -249970 | H42: 0 | J42: =SUM(G42:H42) -> -249970 | K42: Eastwest Bank | L42: Internal Transfer | M42: Internal Transfer from Eastwest bank to OCBC USD | N42: Internal Fund Transfer | O42: =_xlfn.XLOOKUP(N42,costcategory[Account Code],costcategory[Cost Category],"ERROR") -> Internal Fund Transfer | P42: Others | Q42: =_xlfn.XLOOKUP(P42,Table2[Department],Table2[Group],"ERROR") -> Others
A43: Paid | B43: SG | C43: 46128 | D43: 46128 | E43: 46128 | F43: USD | G43: 7.81 | H43: 0 | J43: =SUM(G43:H43) -> 7.81 | K43: OCBC USD | L43: Bank charges | M43: Bank charges | N43: Bank Charges | O43: =_xlfn.XLOOKUP(N43,costcategory[Account Code],costcategory[Cost Category],"ERROR") -> Bank Charges | P43: Finance | Q43: =_xlfn.XLOOKUP(P43,Table2[Department],Table2[Group],"ERROR") -> General & Administrative | V43: No
A44: Paid | B44: SG | C44: 46135 | D44: 46135 | E44: 46135 | F44: USD | G44: 197160.88 | H44: 0 | J44: 197160.88 | K44: OCBC SGD | L44: Internal Transfer | M44: Internal Transfer from USD to SGD | N44: Internal Fund Transfer | O44: =_xlfn.XLOOKUP(N44,costcategory[Account Code],costcategory[Cost Category],"ERROR") -> Internal Fund Transfer | P44: Others | Q44: =_xlfn.XLOOKUP(P44,Table2[Department],Table2[Group],"ERROR") -> Others
A45: Paid | B45: SG | C45: 46139 | D45: 46139 | E45: 46139 | F45: USD | G45: -9786.02 | H45: 0 | J45: =SUM(G45:H45) -> -9786.02 | K45: Soitec Microelectronics Singapore Pte Ltd | L45: INV 2603007 | M45: Application Development Support Services for PR1 Visual Inspect automation for the month of March 2026 | N45: Sales - Services Fees | O45: =_xlfn.XLOOKUP(N45,costcategory[Account Code],costcategory[Cost Category],"ERROR") -> Revenue | P45: Sales & Pre-Sales | Q45: =_xlfn.XLOOKUP(P45,Table2[Department],Table2[Group],"ERROR") -> Sales & Marketing | U45: ORU2604002 | V45: Yes
A46: Paid | B46: SG | C46: 46139 | D46: 46139 | E46: 46139 | F46: USD | G46: 7.77 | H46: 0 | J46: =SUM(G46:H46) -> 7.77 | K46: OCBC USD | L46: Bank charges | M46: Bank charges | N46: Bank Charges | O46: =_xlfn.XLOOKUP(N46,costcategory[Account Code],costcategory[Cost Category],"ERROR") -> Bank Charges | P46: Finance | Q46: =_xlfn.XLOOKUP(P46,Table2[Department],Table2[Group],"ERROR") -> General & Administrative | U46: PVU2604005 | V46: No
J47: =SUM(J39:J46) -> -57966.33
A48: Closing c/f | E48: 46142 | F48: USD | J48: =J38-J47 -> 124366.3
A50: Status | B50: Entity | C50: Billing Date | D50: Due Date | E50: Payment Date | F50: Currency | G50: Sub Total | H50: Tax | J50: Total Amount | K50: Payee | L50: Invoice Number | M50: Description | N50: Account Code | O50: Account Category | P50: Department | Q50: Group | R50: Submitter | S50: Approval | T50: Authorisation | U50: Remarks | V50: GST Claimable
A51: Opening b/f | E51: 46143 | F51: USD | J51: =J48 -> 124366.3
A52: Paid | B52: SG | C52: 46150 | D52: 46150 | E52: 46150 | F52: USD | G52: -59000 | H52: 0 | J52: -59000 | K52: Shanghai Wilson Optimus Technology Co., Ltd., | L52: INV 2604014 | M52: Taiwan IP License | N52: Sales - Services Fees | O52: =_xlfn.XLOOKUP(N52,costcategory[Account Code],costcategory[Cost Category],"ERROR") -> Revenue | P52: Sales & Pre-Sales | Q52: =_xlfn.XLOOKUP(P52,Table2[Department],Table2[Group],"ERROR") -> Sales & Marketing | U52: ORU2605001 | V52: No
A53: Paid | B53: SG | C53: 46150 | D53: 46150 | E53: 46150 | F53: USD | G53: 25 | H53: 0 | J53: 25 | K53: OCBC USD | L53: Bank charges | M53: Bank charges for INV 2604014 | N53: Bank Charges | O53: =_xlfn.XLOOKUP(N53,costcategory[Account Code],costcategory[Cost Category],"ERROR") -> Bank Charges | P53: Finance | Q53: =_xlfn.XLOOKUP(P53,Table2[Department],Table2[Group],"ERROR") -> General & Administrative | U53: ORU2605001 | V53: No
A54: Paid | B54: SG | C54: 46150 | D54: 46150 | E54: 46150 | F54: USD | G54: 7.82 | H54: 0 | J54: 7.82 | K54: OCBC USD | L54: Bank charges | M54: Bank charges | N54: Bank Charges | O54: =_xlfn.XLOOKUP(N54,costcategory[Account Code],costcategory[Cost Category],"ERROR") -> Bank Charges | P54: Finance | Q54: =_xlfn.XLOOKUP(P54,Table2[Department],Table2[Group],"ERROR") -> General & Administrative | U54: PVU2605001 | V54: No
A55: Paid | B55: SG | C55: 46160 | D55: 46160 | E55: 46160 | F55: USD | G55: 180760.77 | H55: 0 | J55: =G55+H55 -> 180760.77 | K55: OCBC SGD | L55: Internal Transfer | M55: Internal Transfer from USD to SGD | N55: OCBC SG - SGD | O55: =_xlfn.XLOOKUP(N55,costcategory[Account Code],costcategory[Cost Category],"ERROR") -> Bank | P55: Finance | Q55: =_xlfn.XLOOKUP(P55,Table2[Department],Table2[Group],"ERROR") -> General & Administrative
A56: Paid | B56: SG | C56: 46147 | D56: 46177 | E56: 46168 | F56: USD | G56: -9786.02 | H56: 0 | I56: -9786.02 | J56: -9786.02 | K56: Soitec Microelectronics Singapore Pte Ltd | L56: INV 2605001 | M56: Application Development Support Services for PR1 Visual Inspect automation for the month of April 2026 | N56: Sales - Services Fees | O56: =_xlfn.XLOOKUP(N56,costcategory[Account Code],costcategory[Cost Category],"ERROR") -> Revenue | P56: Sales & Pre-Sales | Q56: =_xlfn.XLOOKUP(P56,Table2[Department],Table2[Group],"ERROR") -> Sales & Marketing | U56: ORU2605002 | V56: No
A57: Paid | B57: SG | C57: 46168 | D57: 46168 | E57: 46168 | F57: USD | G57: 7.77 | H57: 0 | I57: 7.77 | J57: 7.77 | K57: OCBC USD | L57: Bank charges | M57: Bank charges | N57: Bank Charges | O57: =_xlfn.XLOOKUP(N57,costcategory[Account Code],costcategory[Cost Category],"ERROR") -> Bank Charges | P57: Finance | Q57: =_xlfn.XLOOKUP(P57,Table2[Department],Table2[Group],"ERROR") -> General & Administrative | U57: PVU2605003 | V57: No
F58: USD | J58: =SUM(J52:J57) -> 112015.34
A59: Closing c/f | E59: 46173 | F59: USD | J59: =J51-J58 -> 12350.96 | K59: Bank Recon May 2026 - OK
A61: Status | B61: Entity | C61: Billing Date | D61: Due Date | E61: Payment Date | F61: Currency | G61: Sub Total | H61: Tax | J61: Total Amount | K61: Payee | L61: Invoice Number | M61: Description | N61: Account Code | O61: Account Category | P61: Department | Q61: Group | R61: Submitter | S61: Approval | T61: Authorisation | U61: Remarks | V61: GST Claimable
A62: Opening b/f | E62: 46174 | F62: USD | J62: =J59 -> 12350.96
A63: Paid | B63: SG | C63: 46195 | D63: 46195 | E63: 46195 | F63: USD | G63: -50000 | H63: 0 | I63: -50650 | J63: -50000 | K63: Alpha X Technology Co., Ltd | M63: Loan refund - USD50K | N63: Short Term Loan | O63: =_xlfn.XLOOKUP(N63,costcategory[Account Code],costcategory[Cost Category],"ERROR") -> Current Liabilities | P63: Finance | Q63: =_xlfn.XLOOKUP(P63,Table2[Department],Table2[Group],"ERROR") -> General & Administrative | U63: ORU2606001 | V63: No
A64: Paid | B64: SG | C64: 46195 | D64: 46195 | E64: 46195 | F64: USD | G64: -650 | H64: 0 | J64: -650 | K64: Alpha X Technology Co., Ltd | M64: Interest Income | N64: Interest Income | O64: =_xlfn.XLOOKUP(N64,costcategory[Account Code],costcategory[Cost Category],"ERROR") -> Other Income | P64: Finance | Q64: =_xlfn.XLOOKUP(P64,Table2[Department],Table2[Group],"ERROR") -> General & Administrative | U64: ORU2606001 | V64: No
A65: Paid | B65: SG | C65: 46195 | D65: 46195 | E65: 46195 | F65: USD | G65: 7.67 | H65: 0 | I65: -50650 | J65: 7.67 | K65: OCBC USD | L65: Bank charges | M65: Bank charges | N65: Bank Charges | O65: =_xlfn.XLOOKUP(N65,costcategory[Account Code],costcategory[Cost Category],"ERROR") -> Bank Charges | P65: Finance | Q65: =_xlfn.XLOOKUP(P65,Table2[Department],Table2[Group],"ERROR") -> General & Administrative | U65: PVU2606001 | V65: No
A66: Paid | B66: SG | C66: 46197 | D66: 46197 | E66: 46197 | F66: USD | G66: 62000 | H66: 0 | I66: -50650 | J66: =G66+H66 -> 62000 | K66: OCBC SGD | L66: Internal Transfer | M66: Internal Transfer from USD to SGD | N66: OCBC SG - SGD | O66: =_xlfn.XLOOKUP(N66,costcategory[Account Code],costcategory[Cost Category],"ERROR") -> Bank | P66: Finance | Q66: =_xlfn.XLOOKUP(P66,Table2[Department],Table2[Group],"ERROR") -> General & Administrative | U66: PVU2606002 | V66: No
A67: Paid | B67: SG | C67: 46197 | D67: 46197 | E67: 46197 | F67: USD | G67: -199970 | H67: 0 | I67: -50650 | J67: =G67+H67 -> -199970 | K67: Eastwest Bank | L67: Internal Transfer | M67: Internal Transfer from Eastwest bank to OCBC USD | N67: Internal Fund Transfer | O67: =_xlfn.XLOOKUP(N67,costcategory[Account Code],costcategory[Cost Category],"ERROR") -> Internal Fund Transfer | P67: Others | Q67: =_xlfn.XLOOKUP(P67,Table2[Department],Table2[Group],"ERROR") -> Others | U67: ORU2606002 | V67: No
A68: Paid | B68: SG | C68: 46197 | D68: 46197 | E68: 46197 | F68: USD | G68: 7.65 | H68: 0 | I68: -50650 | J68: =G68+H68 -> 7.65 | K68: OCBC USD | L68: Bank charges | M68: Bank charges | N68: Bank Charges | O68: =_xlfn.XLOOKUP(N68,costcategory[Account Code],costcategory[Cost Category],"ERROR") -> Bank Charges | P68: Finance | Q68: =_xlfn.XLOOKUP(P68,Table2[Department],Table2[Group],"ERROR") -> General & Administrative | U68: PVU2606002 | V68: No
A69: Paid | B69: SG | C69: 46170 | D69: 46200 | E69: 46199 | F69: USD | G69: -8978 | H69: -808.02 | I69: 9786.02 | J69: =G69+H69 -> -9786.02 | K69: Soitec Microelectronics Singapore Pte Ltd | L69: INV 2605010 | M69: Development Support Services for PR1 Visual Inspect automation - May 2026 | N69: Sales - Services Fees | O69: =_xlfn.XLOOKUP(N69,costcategory[Account Code],costcategory[Cost Category],"ERROR") -> Revenue | P69: Sales & Pre-Sales | Q69: =_xlfn.XLOOKUP(P69,Table2[Department],Table2[Group],"ERROR") -> Sales & Marketing | U69: ORU2606003 | V69: Yes
A70: Paid | B70: SG | C70: 46199 | D70: 46199 | E70: 46199 | F70: USD | G70: 7.65 | H70: 0 | I70: -50650 | J70: =G70+H70 -> 7.65 | K70: OCBC USD | L70: Bank charges | M70: Bank charges | N70: Bank Charges | O70: =_xlfn.XLOOKUP(N70,costcategory[Account Code],costcategory[Cost Category],"ERROR") -> Bank Charges | P70: Finance | Q70: =_xlfn.XLOOKUP(P70,Table2[Department],Table2[Group],"ERROR") -> General & Administrative | U70: PVU2606003 | V70: No
A71: Paid | B71: SG | F71: USD | O71: =_xlfn.XLOOKUP(N71,costcategory[Account Code],costcategory[Cost Category],"ERROR") -> ERROR | Q71: =_xlfn.XLOOKUP(P71,Table2[Department],Table2[Group],"ERROR") -> ERROR
A72: Paid | B72: SG | F72: USD | O72: =_xlfn.XLOOKUP(N72,costcategory[Account Code],costcategory[Cost Category],"ERROR") -> ERROR | Q72: =_xlfn.XLOOKUP(P72,Table2[Department],Table2[Group],"ERROR") -> ERROR
A73: Paid | B73: SG | F73: USD | O73: =_xlfn.XLOOKUP(N73,costcategory[Account Code],costcategory[Cost Category],"ERROR") -> ERROR | Q73: =_xlfn.XLOOKUP(P73,Table2[Department],Table2[Group],"ERROR") -> ERROR
F74: USD | J74: =SUM(J63:J73) -> -198383.05
A75: Closing c/f | E75: 46203 | F75: USD | J75: =J62-J74 -> 210734.01
A77: Status | B77: Entity | C77: Billing Date | D77: Due Date | E77: Payment Date | F77: Currency | G77: Sub Total | H77: Tax | J77: Total Amount | K77: Payee | L77: Invoice Number | M77: Description | N77: Account Code | O77: Account Category | P77: Department | Q77: Group | R77: Submitter | S77: Approval | T77: Authorisation | U77: Remarks | V77: GST Claimable
A78: Opening b/f | E78: 46204 | F78: USD | J78: =J75 -> 210734.01
O79: =_xlfn.XLOOKUP(N79,costcategory[Account Code],costcategory[Cost Category],"ERROR") -> ERROR | Q79: =_xlfn.XLOOKUP(P79,Table2[Department],Table2[Group],"ERROR") -> ERROR
O80: =_xlfn.XLOOKUP(N80,costcategory[Account Code],costcategory[Cost Category],"ERROR") -> ERROR | Q80: =_xlfn.XLOOKUP(P80,Table2[Department],Table2[Group],"ERROR") -> ERROR
J81: =SUM(J79:J80) -> 0
A82: Closing c/f | E82: 46234 | F82: USD | J82: =J78-J81 -> 210734.01
A84: Status | B84: Entity | C84: Billing Date | D84: Due Date | E84: Payment Date | F84: Currency | G84: Sub Total | H84: Tax | J84: Total Amount | K84: Payee | L84: Invoice Number | M84: Description | N84: Account Code | O84: Account Category | P84: Department | Q84: Group | R84: Submitter | S84: Approval | T84: Authorisation | U84: Remarks | V84: GST Claimable
A85: Opening b/f | E85: 46235 | F85: USD | J85: =J82 -> 210734.01
O86: =_xlfn.XLOOKUP(N86,costcategory[Account Code],costcategory[Cost Category],"ERROR") -> ERROR | Q86: =_xlfn.XLOOKUP(P86,Table2[Department],Table2[Group],"ERROR") -> ERROR
O87: =_xlfn.XLOOKUP(N87,costcategory[Account Code],costcategory[Cost Category],"ERROR") -> ERROR | Q87: =_xlfn.XLOOKUP(P87,Table2[Department],Table2[Group],"ERROR") -> ERROR
J88: =SUM(J86:J87) -> 0
A89: Closing c/f | E89: 46265 | F89: USD | J89: =J85-J88 -> 210734.01
A93: Status | B93: Entity | C93: Billing Date | D93: Due Date | E93: Payment Date | F93: Currency | G93: Sub Total | H93: Tax | J93: Total Amount | K93: Payee | L93: Invoice Number | M93: Description | N93: Account Code | O93: Account Category | P93: Department | Q93: Group | R93: Submitter | S93: Approval | T93: Authorisation | U93: Remarks | V93: GST Claimable
A94: Opening b/f | E94: 46266 | F94: USD | J94: =J89 -> 210734.01
O95: =_xlfn.XLOOKUP(N95,costcategory[Account Code],costcategory[Cost Category],"ERROR") -> ERROR | Q95: =_xlfn.XLOOKUP(P95,Table2[Department],Table2[Group],"ERROR") -> ERROR
O96: =_xlfn.XLOOKUP(N96,costcategory[Account Code],costcategory[Cost Category],"ERROR") -> ERROR | Q96: =_xlfn.XLOOKUP(P96,Table2[Department],Table2[Group],"ERROR") -> ERROR
J97: =SUM(J95:J96) -> 0
A98: Closing c/f | E98: 46295 | F98: USD | J98: =J94-J97 -> 210734.01
A100: Status | B100: Entity | C100: Billing Date | D100: Due Date | E100: Payment Date | F100: Currency | G100: Sub Total | H100: Tax | J100: Total Amount | K100: Payee | L100: Invoice Number | M100: Description | N100: Account Code | O100: Account Category | P100: Department | Q100: Group | R100: Submitter | S100: Approval | T100: Authorisation | U100: Remarks | V100: GST Claimable
A101: Opening b/f | E101: 46296 | F101: USD | J101: =J98 -> 210734.01
O102: =_xlfn.XLOOKUP(N102,costcategory[Account Code],costcategory[Cost Category],"ERROR") -> ERROR | Q102: =_xlfn.XLOOKUP(P102,Table2[Department],Table2[Group],"ERROR") -> ERROR
O103: =_xlfn.XLOOKUP(N103,costcategory[Account Code],costcategory[Cost Category],"ERROR") -> ERROR | Q103: =_xlfn.XLOOKUP(P103,Table2[Department],Table2[Group],"ERROR") -> ERROR
J104: =SUM(J102:J103) -> 0
A105: Closing c/f | E105: 46326 | F105: USD | J105: =J101-J104 -> 210734.01
A107: Status | B107: Entity | C107: Billing Date | D107: Due Date | E107: Payment Date | F107: Currency | G107: Sub Total | H107: Tax | J107: Total Amount | K107: Payee | L107: Invoice Number | M107: Description | N107: Account Code | O107: Account Category | P107: Department | Q107: Group | R107: Submitter | S107: Approval | T107: Authorisation | U107: Remarks | V107: GST Claimable
A108: Opening b/f | E108: 46327 | F108: USD | J108: =J105 -> 210734.01
O109: =_xlfn.XLOOKUP(N109,costcategory[Account Code],costcategory[Cost Category],"ERROR") -> ERROR | Q109: =_xlfn.XLOOKUP(P109,Table2[Department],Table2[Group],"ERROR") -> ERROR
O110: =_xlfn.XLOOKUP(N110,costcategory[Account Code],costcategory[Cost Category],"ERROR") -> ERROR | Q110: =_xlfn.XLOOKUP(P110,Table2[Department],Table2[Group],"ERROR") -> ERROR
J111: =SUM(J109:J110) -> 0
A112: Closing c/f | E112: 46356 | F112: USD | J112: =J108-J111 -> 210734.01
...

Sheet AXT- SGD
A2: Alpha X Technology Pte Ltd (Singapore)
I3: SGD | J3: =FOREX!C2 -> 0.787321
A4: Status | B4: Entity | C4: Billing Date | D4: Due Date | E4: Payment Date | F4: Currency | G4: Sub Total | H4: Tax | I4: Total Amount | J4: Amount (USD) | K4: Payee | L4: Invoice Number | M4: Description | N4: Account Code | O4: Account Category | P4: Department | Q4: Group | R4: Submitter | S4: Approval | T4: Authorisation | U4: Remarks | V4: GST Claimable
A5: Opening b/f | E5: 46023 | F5: SGD | I5: 173074.36
A6: Paid | B6: SG | C6: 46025 | D6: 46025 | E6: 46025 | F6: SGD | G6: 294.35 | H6: 0 | I6: =SUM(G6:H6) -> 294.35 | J6: =I6*$J$3 -> 231.74794 | K6: Sarai Fine Thai Cuisine Singapore | L6: Debit Card 3/1/2026 | M6: Sarai Fine Thai Cuisine Singapore | N6: Staff Welfare - Meal & Refreshment | O6: =_xlfn.XLOOKUP(N6,costcategory[Account Code],costcategory[Cost Category],"ERROR") -> Employee Benefits | P6: Management | Q6: =_xlfn.XLOOKUP(P6,Table2[Department],Table2[Group],"ERROR") -> General & Administrative | R6: Leon Chan | S6: - | T6: - | V6: No
A7: Paid | B7: SG | C7: 46027 | D7: 46027 | E7: 46027 | F7: SGD | G7: 10 | H7: 0 | I7: =SUM(G7:H7) -> 10 | J7: =I7*$J$3 -> 7.87321 | K7: OCBC SGD | L7: Bank Charges 05/01/2026 | M7: Bank Charges | N7: Bank Charges | O7: =_xlfn.XLOOKUP(N7,costcategory[Account Code],costcategory[Cost Category],"ERROR") -> Bank Charges | P7: Finance | Q7: =_xlfn.XLOOKUP(P7,Table2[Department],Table2[Group],"ERROR") -> General & Administrative | R7: Direct | S7: - | T7: - | U7: PV2601002 | V7: No
A8: Paid | B8: SG | C8: 46034 | D8: 46034 | E8: 46034 | F8: SGD | G8: 51030 | H8: 0 | I8: =SUM(G8:H8) -> 51030 | J8: =I8*$J$3 -> 40176.991 | K8: Central Provident Fund | L8: CPF 2025/12 | M8: CPF Contribution for December 2025 | N8: Accrual - Expenses of 2025 | O8: =_xlfn.XLOOKUP(N8,costcategory[Account Code],costcategory[Cost Category],"ERROR") -> Accrual - Expenses of 2025 | P8: HR | Q8: =_xlfn.XLOOKUP(P8,Table2[Department],Table2[Group],"ERROR") -> General & Administrative | R8: Stephanie | S8: Fan Li | T8: CK Beh | U8: PV2601E001 | V8: No
A9: Paid | B9: SG | C9: 46009 | D9: 46037 | E9: 46036 | F9: SGD | G9: 47.5 | H9: 4.28 | I9: =SUM(G9:H9) -> 51.78 | J9: =I9*$J$3 -> 40.767481 | K9: Kumpulan Development (S) Pte Ltd | L9: CE/2896961 | M9: Drink water for office | N9: Staff Welfare - Meal & Refreshment | O9: =_xlfn.XLOOKUP(N9,costcategory[Account Code],costcategory[Cost Category],"ERROR") -> Employee Benefits | P9: General | Q9: =_xlfn.XLOOKUP(P9,Table2[Department],Table2[Group],"ERROR") -> General & Administrative | R9: Mei Inn | S9: Cathfrine Low | T9: CK Beh | V9: Yes
A10: Paid | B10: SG | C10: 46023 | D10: 46023 | E10: 46036 | F10: SGD | G10: 500 | H10: 0 | I10: =SUM(G10:H10) -> 500 | J10: =I10*$J$3 -> 393.6605 | K10: Sutin Kwok Kwai Lian | L10: Decemeber2025 | M10: Cleaning Fees for December 2025 | N10: Accrual - Expenses of 2025 | O10: =_xlfn.XLOOKUP(N10,costcategory[Account Code],costcategory[Cost Category],"ERROR") -> Accrual - Expenses of 2025 | P10: General | Q10: =_xlfn.XLOOKUP(P10,Table2[Department],Table2[Group],"ERROR") -> General & Administrative | R10: Mei Inn | S10: Cathfrine Low | T10: CK Beh | V10: No
A11: Paid | B11: SG | C11: 46036 | D11: 46052 | E11: 46052 | F11: SGD | G11: 47.5 | H11: 4.28 | I11: =SUM(G11:H11) -> 51.78 | J11: =I11*$J$3 -> 40.767481 | K11: Kumpulan Development (S) Pte Ltd | L11: CE2902279 | M11: Drink water for office | N11: Staff Welfare - Meal & Refreshment | O11: =_xlfn.XLOOKUP(N11,costcategory[Account Code],costcategory[Cost Category],"ERROR") -> Employee Benefits | P11: General | Q11: =_xlfn.XLOOKUP(P11,Table2[Department],Table2[Group],"ERROR") -> General & Administrative | R11: Mei Inn | S11: Cathfrine Low | T11: CK Beh | U11: PV2601027 | V11: Yes
A12: Paid | B12: SG | C12: 46037 | D12: 46037 | E12: 46037 | F12: SGD | G12: =2693.19-G13 -> 1626.09 | H12: 0 | I12: =SUM(G12:H12) -> 1626.09 | J12: =I12*$J$3 -> 1280.2548 | K12: Staff Claim Dec25 | L12: Staff Claim 2025/12 | M12: Total Accommodation - International | N12: Accommodation - International | O12: =_xlfn.XLOOKUP(N12,costcategory[Account Code],costcategory[Cost Category],"ERROR") -> Travelling Expenses | P12: Management | Q12: =_xlfn.XLOOKUP(P12,Table2[Department],Table2[Group],"ERROR") -> General & Administrative | V12: No
A13: Paid | B13: SG | C13: 46037 | D13: 46037 | E13: 46037 | F13: SGD | G13: 1067.1 | H13: 0 | I13: =SUM(G13:H13) -> 1067.1 | J13: =I13*$J$3 -> 840.15024 | K13: Staff Claim Dec25 | L13: Staff Claim 2025/12 | M13: Total Accommodation - International | N13: Accommodation - International | O13: =_xlfn.XLOOKUP(N13,costcategory[Account Code],costcategory[Cost Category],"ERROR") -> Travelling Expenses | P13: HR | Q13: =_xlfn.XLOOKUP(P13,Table2[Department],Table2[Group],"ERROR") -> General & Administrative | V13: No
A14: Paid | B14: SG | C14: 46037 | D14: 46037 | E14: 46037 | F14: SGD | G14: =997.67-G15 -> 686.64 | H14: 0 | I14: =SUM(G14:H14) -> 686.64 | J14: =I14*$J$3 -> 540.60609 | K14: Staff Claim Dec25 | L14: Staff Claim 2025/12 | M14: Total Business Meals - International | N14: Business Meals - International | O14: =_xlfn.XLOOKUP(N14,costcategory[Account Code],costcategory[Cost Category],"ERROR") -> Sales Expenses | P14: Management | Q14: =_xlfn.XLOOKUP(P14,Table2[Department],Table2[Group],"ERROR") -> General & Administrative | V14: No
A15: Paid | B15: SG | C15: 46037 | D15: 46037 | E15: 46037 | F15: SGD | G15: 311.03 | H15: 0 | I15: =SUM(G15:H15) -> 311.03 | J15: =I15*$J$3 -> 244.88045 | K15: Staff Claim Dec25 | L15: Staff Claim 2025/12 | M15: Total Business Meals - International | N15: Business Meals - International | O15: =_xlfn.XLOOKUP(N15,costcategory[Account Code],costcategory[Cost Category],"ERROR") -> Sales Expenses | P15: HR | Q15: =_xlfn.XLOOKUP(P15,Table2[Department],Table2[Group],"ERROR") -> General & Administrative | V15: No
A16: Paid | B16: SG | C16: 46037 | D16: 46037 | E16: 46037 | F16: SGD | G16: 29.95 | H16: 2.69 | I16: =SUM(G16:H16) -> 32.64 | J16: =I16*$J$3 -> 25.698157 | K16: Staff Claim Dec25 | L16: Staff Claim 2025/12 | M16: Total Business Meals - National | N16: Business Meals - National | O16: =_xlfn.XLOOKUP(N16,costcategory[Account Code],costcategory[Cost Category],"ERROR") -> Sales Expenses | P16: HR | Q16: =_xlfn.XLOOKUP(P16,Table2[Department],Table2[Group],"ERROR") -> General & Administrative | V16: Yes
A17: Paid | B17: SG | C17: 46037 | D17: 46037 | E17: 46037 | F17: SGD | G17: 935.55 | H17: 84.2 | I17: =SUM(G17:H17) -> 1019.75 | J17: =I17*$J$3 -> 802.87059 | K17: Staff Claim Dec25 | L17: Staff Claim 2025/12 | M17: Total Business Meals - National | N17: Business Meals - National | O17: =_xlfn.XLOOKUP(N17,costcategory[Account Code],costcategory[Cost Category],"ERROR") -> Sales Expenses | P17: Business Operation | Q17: =_xlfn.XLOOKUP(P17,Table2[Department],Table2[Group],"ERROR") -> Sales & Marketing | V17: Yes
A18: Paid | B18: SG | C18: 46037 | D18: 46037 | E18: 46037 | F18: SGD | G18: 1509.43 | H18: 116.27 | I18: =SUM(G18:H18) -> 1625.7 | J18: =I18*$J$3 -> 1279.9477 | K18: Staff Claim Dec25 | L18: Staff Claim 2025/12 | M18: Total Business Meals - National | N18: Business Meals - National | O18: =_xlfn.XLOOKUP(N18,costcategory[Account Code],costcategory[Cost Category],"ERROR") -> Sales Expenses | P18: Management | Q18: =_xlfn.XLOOKUP(P18,Table2[Department],Table2[Group],"ERROR") -> General & Administrative | V18: Yes
A19: Paid | B19: SG | C19: 46037 | D19: 46037 | E19: 46037 | F19: SGD | G19: =127.57-G20 -> 75.57 | H19: 4.03 | I19: =SUM(G19:H19) -> 79.6 | J19: =I19*$J$3 -> 62.670752 | K19: Staff Claim Dec25 | L19: Staff Claim 2025/12 | M19: Total Consumable Tools | N19: Consumable Tools | O19: =_xlfn.XLOOKUP(N19,costcategory[Account Code],costcategory[Cost Category],"ERROR") -> Office Supplies | P19: General | Q19: =_xlfn.XLOOKUP(P19,Table2[Department],Table2[Group],"ERROR") -> General & Administrative | V19: Yes
A20: Paid | B20: SG | C20: 46037 | D20: 46037 | E20: 46037 | F20: SGD | G20: 52 | H20: 0 | I20: =SUM(G20:H20) -> 52 | J20: =I20*$J$3 -> 40.940692 | K20: Staff Claim Dec25 | L20: Staff Claim 2025/12 | M20: Total Consumable Tools | N20: Consumable Tools | O20: =_xlfn.XLOOKUP(N20,costcategory[Account Code],costcategory[Cost Category],"ERROR") -> Office Supplies | P20: R&D - Team W | Q20: =_xlfn.XLOOKUP(P20,Table2[Department],Table2[Group],"ERROR") -> Research & Development | V20: No
A21: Paid | B21: SG | C21: 46037 | D21: 46037 | E21: 46037 | F21: SGD | G21: 3.92 | H21: 0 | I21: 3.92 | J21: =I21*$J$3 -> 3.0862983 | K21: Staff Claim Dec25 | L21: Staff Claim 2025/12 | M21: Total Courier Charges | N21: Courier Charges | O21: =_xlfn.XLOOKUP(N21,costcategory[Account Code],costcategory[Cost Category],"ERROR") -> Courier Charges | P21: HR | Q21: =_xlfn.XLOOKUP(P21,Table2[Department],Table2[Group],"ERROR") -> General & Administrative | V21: No
A22: Paid | B22: SG | C22: 46037 | D22: 46037 | E22: 46037 | F22: SGD | G22: 33 | H22: 0 | I22: =SUM(G22:H22) -> 33 | J22: =I22*$J$3 -> 25.981593 | K22: Staff Claim Dec25 | L22: Staff Claim 2025/12 | M22: Total Courier Charges | N22: Courier Charges | O22: =_xlfn.XLOOKUP(N22,costcategory[Account Code],costcategory[Cost Category],"ERROR") -> Courier Charges | P22: General | Q22: =_xlfn.XLOOKUP(P22,Table2[Department],Table2[Group],"ERROR") -> General & Administrative | V22: No
A23: Paid | B23: SG | C23: 46037 | D23: 46037 | E23: 46037 | F23: SGD | G23: =251.9-G24 -> 189.44 | H23: 0 | I23: =SUM(G23:H23) -> 189.44 | J23: =I23*$J$3 -> 149.15009 | K23: Staff Claim Dec25 | L23: Staff Claim 2025/12 | M23: Total Hampers & Gift | N23: Hampers & Gift | O23: =_xlfn.XLOOKUP(N23,costcategory[Account Code],costcategory[Cost Category],"ERROR") -> Sales Expenses | P23: Management | Q23: =_xlfn.XLOOKUP(P23,Table2[Department],Table2[Group],"ERROR") -> General & Administrative | V23: No
A24: Paid | B24: SG | C24: 46037 | D24: 46037 | E24: 46037 | F24: SGD | G24: 62.46 | H24: 0 | I24: =SUM(G24:H24) -> 62.46 | J24: =I24*$J$3 -> 49.17607 | K24: Staff Claim Dec25 | L24: Staff Claim 2025/12 | M24: Total Hampers & Gift | N24: Hampers & Gift | O24: =_xlfn.XLOOKUP(N24,costcategory[Account Code],costcategory[Cost Category],"ERROR") -> Sales Expenses | P24: Business Operation | Q24: =_xlfn.XLOOKUP(P24,Table2[Department],Table2[Group],"ERROR") -> Sales & Marketing | V24: No
A25: Paid | B25: SG | C25: 46037 | D25: 46037 | E25: 46037 | F25: SGD | G25: 18.32 | H25: 0 | I25: =SUM(G25:H25) -> 18.32 | J25: =I25*$J$3 -> 14.423721 | K25: Staff Claim Dec25 | L25: Staff Claim 2025/12 | M25: Total Intercompany - China | N25: Intercompany - Alpha X (Shanghai) Technology Co Ltd | O25: =_xlfn.XLOOKUP(N25,costcategory[Account Code],costcategory[Cost Category],"ERROR") -> Intercompany | P25: R&D - Team W | Q25: =_xlfn.XLOOKUP(P25,Table2[Department],Table2[Group],"ERROR") -> Research & Development | V25: No
A26: Paid | B26: SG | C26: 46037 | D26: 46037 | E26: 46037 | F26: SGD | G26: 334.06 | H26: 9.19 | I26: =SUM(G26:H26) -> 343.25 | J26: =I26*$J$3 -> 270.24793 | K26: Staff Claim Dec25 | L26: Staff Claim 2025/12 | M26: Total Office Supplies | N26: Office Supplies | O26: =_xlfn.XLOOKUP(N26,costcategory[Account Code],costcategory[Cost Category],"ERROR") -> Office Supplies | P26: General | Q26: =_xlfn.XLOOKUP(P26,Table2[Department],Table2[Group],"ERROR") -> General & Administrative | V26: Yes
A27: Paid | B27: SG | C27: 46037 | D27: 46037 | E27: 46037 | F27: SGD | G27: 57.16 | H27: 0 | I27: =SUM(G27:H27) -> 57.16 | J27: =I27*$J$3 -> 45.003268 | K27: Staff Claim Dec25 | L27: Staff Claim 2025/12 | M27: Total Personal Meals - International | N27: Personal Meals - International | O27: =_xlfn.XLOOKUP(N27,costcategory[Account Code],costcategory[Cost Category],"ERROR") -> Travelling Expenses | P27: Management | Q27: =_xlfn.XLOOKUP(P27,Table2[Department],Table2[Group],"ERROR") -> General & Administrative | V27: No
A28: Paid | B28: SG | C28: 46037 | D28: 46037 | E28: 46037 | F28: SGD | G28: =97.65-G27 -> 40.49 | H28: 0 | I28: =SUM(G28:H28) -> 40.49 | J28: =I28*$J$3 -> 31.878627 | K28: Staff Claim Dec25 | L28: Staff Claim 2025/12 | M28: Total Personal Meals - International | N28: Personal Meals - International | O28: =_xlfn.XLOOKUP(N28,costcategory[Account Code],costcategory[Cost Category],"ERROR") -> Travelling Expenses | P28: HR | Q28: =_xlfn.XLOOKUP(P28,Table2[Department],Table2[Group],"ERROR") -> General & Administrative | V28: No
A29: Paid | B29: SG | C29: 46037 | D29: 46037 | E29: 46037 | F29: SGD | G29: 9.17 | H29: 0.83 | I29: =SUM(G29:H29) -> 10 | J29: =I29*$J$3 -> 7.87321 | K29: Staff Claim Dec25 | L29: Staff Claim 2025/12 | M29: Total Personal Meals - National | N29: Personal Meals - National | O29: =_xlfn.XLOOKUP(N29,costcategory[Account Code],costcategory[Cost Category],"ERROR") -> Travelling Expenses | P29: HR | Q29: =_xlfn.XLOOKUP(P29,Table2[Department],Table2[Group],"ERROR") -> General & Administrative | V29: Yes
A30: Paid | B30: SG | C30: 46037 | D30: 46037 | E30: 46037 | F30: SGD | G30: 212.55 | H30: 0 | I30: =SUM(G30:H30) -> 212.55 | J30: =I30*$J$3 -> 167.34508 | K30: Staff Claim Dec25 | L30: Staff Claim 2025/12 | M30: Total Professional & Consultancy Fees | N30: Professional & Consultancy Fees | O30: =_xlfn.XLOOKUP(N30,costcategory[Account Code],costcategory[Cost Category],"ERROR") -> Professional & Consultancy Fees | P30: General | Q30: =_xlfn.XLOOKUP(P30,Table2[Department],Table2[Group],"ERROR") -> General & Administrative | V30: No
A31: Paid | B31: SG | C31: 46037 | D31: 46037 | E31: 46037 | F31: SGD | G31: =2787.28-G32 -> 1557 | H31: 0 | I31: =SUM(G31:H31) -> 1557 | J31: =I31*$J$3 -> 1225.8588 | K31: Staff Claim Dec25 | L31: Staff Claim 2025/12 | M31: Total Small Value Assets | N31: Small Value Assets | O31: =_xlfn.XLOOKUP(N31,costcategory[Account Code],costcategory[Cost Category],"ERROR") -> Small Value Assets | P31: General | Q31: =_xlfn.XLOOKUP(P31,Table2[Department],Table2[Group],"ERROR") -> General & Administrative | V31: No
A32: Paid | B32: SG | C32: 46037 | D32: 46037 | E32: 46037 | F32: SGD | G32: 1230.28 | H32: 110.72 | I32: =SUM(G32:H32) -> 1341 | J32: =I32*$J$3 -> 1055.7975 | K32: Staff Claim Dec25 | L32: Staff Claim 2025/12 | M32: Total Small Value Assets | N32: Small Value Assets | O32: =_xlfn.XLOOKUP(N32,costcategory[Account Code],costcategory[Cost Category],"ERROR") -> Small Value Assets | P32: IT | Q32: =_xlfn.XLOOKUP(P32,Table2[Department],Table2[Group],"ERROR") -> General & Administrative | V32: Yes
A33: Paid | B33: SG | C33: 46037 | D33: 46037 | E33: 46037 | F33: SGD | G33: 909.63 | H33: 78.26 | I33: =SUM(G33:H33) -> 987.89 | J33: =I33*$J$3 -> 777.78654 | K33: Staff Claim Dec25 | L33: Staff Claim 2025/12 | M33: Total Staff Welfare - Meal & Refreshment | N33: Staff Welfare - Meal & Refreshment | O33: =_xlfn.XLOOKUP(N33,costcategory[Account Code],costcategory[Cost Category],"ERROR") -> Employee Benefits | P33: Management | Q33: =_xlfn.XLOOKUP(P33,Table2[Department],Table2[Group],"ERROR") -> General & Administrative | V33: Yes
A34: Paid | B34: SG | C34: 46037 | D34: 46037 | E34: 46037 | F34: SGD | G34: 56.53 | H34: 0 | I34: =SUM(G34:H34) -> 56.53 | J34: =I34*$J$3 -> 44.507256 | K34: Staff Claim Dec25 | L34: Staff Claim 2025/12 | M34: Total Subscription Fee | N34: Subscription Fee | O34: =_xlfn.XLOOKUP(N34,costcategory[Account Code],costcategory[Cost Category],"ERROR") -> Subscription Fee | P34: R&D - Team W | Q34: =_xlfn.XLOOKUP(P34,Table2[Department],Table2[Group],"ERROR") -> Research & Development | V34: No
A35: Paid | B35: SG | C35: 46037 | D35: 46037 | E35: 46037 | F35: SGD | G35: 1271.74 | H35: 0 | I35: =SUM(G35:H35) -> 1271.74 | J35: =I35*$J$3 -> 1001.2676 | K35: Staff Claim Dec25 | L35: Staff Claim 2025/12 | M35: Total Transportation fee - International | N35: Transportation fee - International | O35: =_xlfn.XLOOKUP(N35,costcategory[Account Code],costcategory[Cost Category],"ERROR") -> Travelling Expenses | P35: HR | Q35: =_xlfn.XLOOKUP(P35,Table2[Department],Table2[Group],"ERROR") -> General & Administrative | V35: No
A36: Paid | B36: SG | C36: 46037 | D36: 46037 | E36: 46037 | F36: SGD | G36: 7533.22 | H36: 0 | I36: =SUM(G36:H36) -> 7533.22 | J36: =I36*$J$3 -> 5931.0623 | K36: Staff Claim Dec25 | L36: Staff Claim 2025/12 | M36: Total Transportation fee - International | N36: Transportation fee - International | O36: =_xlfn.XLOOKUP(N36,costcategory[Account Code],costcategory[Cost Category],"ERROR") -> Travelling Expenses | P36: Management | Q36: =_xlfn.XLOOKUP(P36,Table2[Department],Table2[Group],"ERROR") -> General & Administrative | V36: No
A37: Paid | B37: SG | C37: 46037 | D37: 46037 | E37: 46037 | F37: SGD | G37: 467.93 | H37: 0 | I37: =SUM(G37:H37) -> 467.93 | J37: =I37*$J$3 -> 368.41112 | K37: Staff Claim Dec25 | L37: Staff Claim 2025/12 | M37: Total Transportation fee - International | N37: Transportation fee - International | O37: =_xlfn.XLOOKUP(N37,costcategory[Account Code],costcategory[Cost Category],"ERROR") -> Travelling Expenses | P37: R&D - Team W | Q37: =_xlfn.XLOOKUP(P37,Table2[Department],Table2[Group],"ERROR") -> Research & Development | V37: No
A38: Paid | B38: SG | C38: 46037 | D38: 46037 | E38: 46037 | F38: SGD | G38: 69.7 | H38: 0 | I38: =SUM(G38:H38) -> 69.7 | J38: =I38*$J$3 -> 54.876274 | K38: Staff Claim Dec25 | L38: Staff Claim 2025/12 | M38: Total Transportation fee - National | N38: Transportation fee - National | O38: =_xlfn.XLOOKUP(N38,costcategory[Account Code],costcategory[Cost Category],"ERROR") -> Travelling Expenses | P38: HR | Q38: =_xlfn.XLOOKUP(P38,Table2[Department],Table2[Group],"ERROR") -> General & Administrative | V38: No
A39: Paid | B39: SG | C39: 46037 | D39: 46037 | E39: 46037 | F39: SGD | G39: 52.5 | H39: 0 | I39: =SUM(G39:H39) -> 52.5 | J39: =I39*$J$3 -> 41.334353 | K39: Staff Claim Dec25 | L39: Staff Claim 2025/12 | M39: Total Transportation fee - National | N39: Transportation fee - National | O39: =_xlfn.XLOOKUP(N39,costcategory[Account Code],costcategory[Cost Category],"ERROR") -> Travelling Expenses | P39: R&D - Team W | Q39: =_xlfn.XLOOKUP(P39,Table2[Department],Table2[Group],"ERROR") -> Research & Development | V39: No
A40: Paid | B40: SG | C40: 46037 | D40: 46037 | E40: 46037 | F40: SGD | G40: 480 | H40: 0 | I40: =SUM(G40:H40) -> 480 | J40: =I40*$J$3 -> 377.91408 | K40: Staff Claim Dec25 | L40: Staff Claim 2025/12 | M40: Total Upkeep of Offices | N40: Upkeep of Offices | O40: =_xlfn.XLOOKUP(N40,costcategory[Account Code],costcategory[Cost Category],"ERROR") -> Upkeep of Office | P40: General | Q40: =_xlfn.XLOOKUP(P40,Table2[Department],Table2[Group],"ERROR") -> General & Administrative
A41: Paid | B41: SG | C41: 46037 | D41: 46037 | E41: 46037 | F41: SGD | G41: 2593 | H41: 0 | I41: =SUM(G41:H41) -> 2593 | J41: =I41*$J$3 -> 2041.5234 | K41: OCBC USD | L41: Internal Transfer 2026/01-01 | M41: Internal Transfer from SGD to USD | N41: Internal Fund Transfer | O41: =_xlfn.XLOOKUP(N41,costcategory[Account Code],costcategory[Cost Category],"ERROR") -> Internal Fund Transfer | P41: Others | Q41: =_xlfn.XLOOKUP(P41,Table2[Department],Table2[Group],"ERROR") -> Others | R41: Cathfrine | S41: Leon Chan | T41: Cathfrine Low | V41: No
